Workbook

Sheet Summary Tables
B2: GICS Industry | C2: % of Portfolio | D2: Dollar of Portfolio | G2: Portfolio Metrics
B3: Cash and Cash Equivalents | C3: =E3 -> 0.094854576 | D3: =SUMIF('Current Holdings'!D$4:D$61,B3,'Current Holdings'!I$4:I$61) -> 155033.52 | E3: =D3/$D$15 -> 0.094854576 | G3: Beta | H3: =SLOPE('Greek Scratch Work'!K2:K23,'Greek Scratch Work'!L2:L23) -> 0.86071282
B4: Utilities | C4: =E4 -> 0.055274158 | D4: =SUMIF('Current Holdings'!D$4:D$61,B4,'Current Holdings'!I$4:I$61) -> 90341.95 | E4: =D4/$D$15 -> 0.055274158 | G4: Alpha | H4: =INTERCEPT('Greek Scratch Work'!K2:K23,'Greek Scratch Work'!L2:L23) -> 0.0025829916
B5: Consumer Discretionary | C5: =E5 -> 0.082814981 | D5: =SUMIF('Current Holdings'!D$4:D$61,B5,'Current Holdings'!I$4:I$61) -> 135355.6 | E5: =D5/$D$15 -> 0.082814981 | G5: Sharpe Ratio | H5: =((AVERAGE('Greek Scratch Work'!C:C)-'Greek Scratch Work'!L26)/(_xlfn.STDEV.P('Greek Scratch Work'!C:C))*SQRT(252)) -> 0.94169005
B6: Consumer Staples | C6: =E6 -> 0.013038204 | D6: =SUMIF('Current Holdings'!D$4:D$61,B6,'Current Holdings'!I$4:I$61) -> 21310.08 | E6: =D6/$D$15 -> 0.013038204
B7: Health Care | C7: =E7 -> 0.13728091 | D7: =SUMIF('Current Holdings'!D$4:D$61,B7,'Current Holdings'!I$4:I$61) -> 224376.56 | E7: =D7/$D$15 -> 0.13728091
B8: Financials | C8: =E8 -> 0.17256703 | D8: =SUMIF('Current Holdings'!D$4:D$61,B8,'Current Holdings'!I$4:I$61) -> 282049.38 | E8: =D8/$D$15 -> 0.17256703
B9: Information Technology | C9: =E9 -> 0.13809048 | D9: =SUMIF('Current Holdings'!D$4:D$61,B9,'Current Holdings'!I$4:I$61) -> 225699.74 | E9: =D9/$D$15 -> 0.13809048
B10: Industrials | C10: =E10 -> 0.18421997 | D10: =SUMIF('Current Holdings'!D$4:D$61,B10,'Current Holdings'!I$4:I$61) -> 301095.34 | E10: =D10/$D$15 -> 0.18421997
B11: Energy | C11: =E11 -> 0.024596531 | D11: =SUMIF('Current Holdings'!D$4:D$61,B11,'Current Holdings'!I$4:I$61) -> 40201.4 | E11: =D11/$D$15 -> 0.024596531
B12: Real Estate | C12: =E12 -> 0.0075246611 | D12: =SUMIF('Current Holdings'!D$4:D$61,B12,'Current Holdings'!I$4:I$61) -> 12298.56 | E12: =D12/$D$15 -> 0.0075246611
B13: Communication Services | C13: =E13 -> 0.041126867 | D13: =SUMIF('Current Holdings'!D$4:D$61,B13,'Current Holdings'!I$4:I$61) -> 67219.14 | E13: =D13/$D$15 -> 0.041126867
B14: Materials | C14: =E14 -> 0.048611625 | D14: =SUMIF('Current Holdings'!D$4:D$61,B14,'Current Holdings'!I$4:I$61) -> 79452.48 | E14: =D14/$D$15 -> 0.048611625
D15: =sum(D3:D14) -> 1634433.8

Sheet Current Holdings
F2: 45658
B3: Name | C3: Ticker | D3: Sector | E3: Shares Owned | F3: Price on X Date: | G3: Current Price | H3: Average Purchase Price | I3: Current Market Value | J3: % of Portfolio | K3: Day Change | L3: Trend 30d | M3: Trend 180d | N3: $ Return | O3: YTD Return | P3: % Return Since Purchase
B4: =IFERROR(__xludf.DUMMYFUNCTION("GOOGLEFINANCE(C4,B$3)"),"Adobe Inc") -> Adobe Inc | C4: ADBE | D4: Information Technology | E4: 13 | F4: =IFERROR(__xludf.DUMMYFUNCTION("INDEX(GOOGLEFINANCE(C4,""close"",F$2),2,2)"),441.0) -> 441 | G4: =IFERROR(__xludf.DUMMYFUNCTION("GOOGLEFINANCE(C4)"),255.17) -> 255.17 | H4: 667.06 | I4: =E4*G4 -> 3317.21 | J4: =I4/$I$63 -> 0.0020295775 | K4: =IFERROR(__xludf.DUMMYFUNCTION("GOOGLEFINANCE(C4,""changepct"")/100"),0.0344) -> 0.0344 | L4: =IFERROR(__xludf.DUMMYFUNCTION("SPARKLINE(GoogleFinance(C4, ""price"", TODAY()-30,TODAY()))"),"") | M4: =IFERROR(__xludf.DUMMYFUNCTION("SPARKLINE(GoogleFinance(C4, ""price"", TODAY()-180,TODAY()))"),"") | N4: =(I4)-(H4*E4) -> -5354.57 | O4: =(G4-F4)/F4 -> -0.42138322 | P4: =((G4*E4)-(H4*E4))/(H4*E4) -> -0.61747069
B5: =IFERROR(__xludf.DUMMYFUNCTION("GOOGLEFINANCE(C5,B$3)"),"Amazon.com Inc") -> Amazon.com Inc | C5: AMZN | D5: Consumer Discretionary | E5: 260 | F5: =IFERROR(__xludf.DUMMYFUNCTION("INDEX(GOOGLEFINANCE(C5,""close"",F$2),2,2)"),220.22) -> 220.22 | G5: =IFERROR(__xludf.DUMMYFUNCTION("GOOGLEFINANCE(C5)"),208.56) -> 208.56 | H5: =(45533.8-35520.26)/E5 -> 38.513615 | I5: =E5*G5 -> 54225.6 | J5: =I5/$I$63 -> 0.033176995 | K5: =IFERROR(__xludf.DUMMYFUNCTION("GOOGLEFINANCE(C5,""changepct"")/100"),0.016) -> 0.016 | L5: =IFERROR(__xludf.DUMMYFUNCTION("SPARKLINE(GoogleFinance(C5, ""price"", TODAY()-30,TODAY()))"),"") | M5: =IFERROR(__xludf.DUMMYFUNCTION("SPARKLINE(GoogleFinance(C5, ""price"", TODAY()-180,TODAY()))"),"") | N5: =(I5)-(H5*E5) -> 44212.06 | O5: =(G5-F5)/F5 -> -0.052947053 | P5: =((G5*E5)-(H5*E5))/(H5*E5) -> 4.4152278
B6: =IFERROR(__xludf.DUMMYFUNCTION("GOOGLEFINANCE(C6,B$3)"),"American Water Works Co Inc") -> American Water Works Co Inc | C6: AWK | D6: Utilities | E6: 110 | F6: =IFERROR(__xludf.DUMMYFUNCTION("INDEX(GOOGLEFINANCE(C6,""close"",F$2),2,2)"),123.86) -> 123.86 | G6: =IFERROR(__xludf.DUMMYFUNCTION("GOOGLEFINANCE(C6)"),134.08) -> 134.08 | H6: =(15543-10503.83)/E6 -> 45.810636 | I6: =E6*G6 -> 14748.8 | J6: =I6/$I$63 -> 0.009023798 | K6: =IFERROR(__xludf.DUMMYFUNCTION("GOOGLEFINANCE(C6,""changepct"")/100"),0.009000000000000001) -> 0.009 | L6: =IFERROR(__xludf.DUMMYFUNCTION("SPARKLINE(GoogleFinance(C6, ""price"", TODAY()-30,TODAY()))"),"") | M6: =IFERROR(__xludf.DUMMYFUNCTION("SPARKLINE(GoogleFinance(C6, ""price"", TODAY()-180,TODAY()))"),"") | N6: =(I6)-(H6*E6) -> 9709.63 | O6: =(G6-F6)/F6 -> 0.082512514 | P6: =((G6*E6)-(H6*E6))/(H6*E6) -> 1.9268312
B7: =IFERROR(__xludf.DUMMYFUNCTION("GOOGLEFINANCE(C7,B$3)"),"Apple Inc") -> Apple Inc | C7: AAPL | D7: Information Technology | E7: 256 | F7: =IFERROR(__xludf.DUMMYFUNCTION("INDEX(GOOGLEFINANCE(C7,""close"",F$2),2,2)"),243.85) -> 243.85 | G7: =IFERROR(__xludf.DUMMYFUNCTION("GOOGLEFINANCE(C7)"),272.14) -> 272.14 | H7: =(58388.48-52163.94)/E7 -> 24.314609 | I7: =E7*G7 -> 69667.84 | J7: =I7/$I$63 -> 0.042625062 | K7: =IFERROR(__xludf.DUMMYFUNCTION("GOOGLEFINANCE(C7,""changepct"")/100"),0.022400000000000003) -> 0.0224 | L7: =IFERROR(__xludf.DUMMYFUNCTION("SPARKLINE(GoogleFinance(C7, ""price"", TODAY()-30,TODAY()))"),"") | M7: =IFERROR(__xludf.DUMMYFUNCTION("SPARKLINE(GoogleFinance(C7, ""price"", TODAY()-180,TODAY()))"),"") | N7: =(I7)-(H7*E7) -> 63443.3 | O7: =(G7-F7)/F7 -> 0.11601394 | P7: =((G7*E7)-(H7*E7))/(H7*E7) -> 10.192448
B8: =IFERROR(__xludf.DUMMYFUNCTION("GOOGLEFINANCE(C8,B$3)"),"Applied Materials Inc") -> Applied Materials Inc | C8: AMAT | D8: Information Technology | E8: 83 | F8: =IFERROR(__xludf.DUMMYFUNCTION("INDEX(GOOGLEFINANCE(C8,""close"",F$2),2,2)"),163.87) -> 163.87 | G8: =IFERROR(__xludf.DUMMYFUNCTION("GOOGLEFINANCE(C8)"),377.93) -> 377.93 | H8: =(16094.12-6122.77)/E8 -> 120.13675 | I8: =E8*G8 -> 31368.19 | J8: =I8/$I$63 -> 0.019192084 | K8: =IFERROR(__xludf.DUMMYFUNCTION("GOOGLEFINANCE(C8,""changepct"")/100"),0.011699999999999999) -> 0.0117 | L8: =IFERROR(__xludf.DUMMYFUNCTION("SPARKLINE(GoogleFinance(C8, ""price"", TODAY()-30,TODAY()))"),"") | M8: =IFERROR(__xludf.DUMMYFUNCTION("SPARKLINE(GoogleFinance(C8, ""price"", TODAY()-180,TODAY()))"),"") | N8: =(I8)-(H8*E8) -> 21396.84 | O8: =(G8-F8)/F8 -> 1.3062794 | P8: =((G8*E8)-(H8*E8))/(H8*E8) -> 2.1458318
B9: =IFERROR(__xludf.DUMMYFUNCTION("GOOGLEFINANCE(C9,B$3)"),"Bank of New York Mellon Corp") -> Bank of New York Mellon Corp | C9: BK | D9: Financials | E9: 188 | F9: =IFERROR(__xludf.DUMMYFUNCTION("INDEX(GOOGLEFINANCE(C9,""close"",F$2),2,2)"),77.41) -> 77.41 | G9: =IFERROR(__xludf.DUMMYFUNCTION("GOOGLEFINANCE(C9)"),116.55) -> 116.55 | H9: 55.46 | I9: =E9*G9 -> 21911.4 | J9: =I9/$I$63 -> 0.013406111 | K9: =IFERROR(__xludf.DUMMYFUNCTION("GOOGLEFINANCE(C9,""changepct"")/100"),0.0087) -> 0.0087 | L9: =IFERROR(__xludf.DUMMYFUNCTION("SPARKLINE(GoogleFinance(C9, ""price"", TODAY()-30,TODAY()))"),"") | M9: =IFERROR(__xludf.DUMMYFUNCTION("SPARKLINE(GoogleFinance(C9, ""price"", TODAY()-180,TODAY()))"),"") | N9: =(I9)-(H9*E9) -> 11484.92 | O9: =(G9-F9)/F9 -> 0.50561943 | P9: =((G9*E9)-(H9*E9))/(H9*E9) -> 1.1015146
B10: =IFERROR(__xludf.DUMMYFUNCTION("GOOGLEFINANCE(C10,B$3)"),"Barclays PLC") -> Barclays PLC | C10: BCS | D10: Financials | E10: 1000 | F10: =IFERROR(__xludf.DUMMYFUNCTION("INDEX(GOOGLEFINANCE(C10,""close"",F$2),2,2)"),13.13) -> 13.13 | G10: =IFERROR(__xludf.DUMMYFUNCTION("GOOGLEFINANCE(C10)"),25.14) -> 25.14 | H10: =(12064-1185.05)/E10 -> 10.87895 | I10: =E10*G10 -> 25140 | J10: =I10/$I$63 -> 0.015381474 | K10: =IFERROR(__xludf.DUMMYFUNCTION("GOOGLEFINANCE(C10,""changepct"")/100"),0.0012) -> 0.0012 | L10: =IFERROR(__xludf.DUMMYFUNCTION("SPARKLINE(GoogleFinance(C10, ""price"", TODAY()-30,TODAY()))"),"") | M10: =IFERROR(__xludf.DUMMYFUNCTION("SPARKLINE(GoogleFinance(C10, ""price"", TODAY()-180,TODAY()))"),"") | N10: =(I10)-(H10*E10) -> 14261.05 | O10: =(G10-F10)/F10 -> 0.91469916 | P10: =((G10*E10)-(H10*E10))/(H10*E10) -> 1.3108848
B11: =IFERROR(__xludf.DUMMYFUNCTION("GOOGLEFINANCE(C11,B$3)"),"Berkshire Hathaway Inc Class B") -> Berkshire Hathaway Inc Class B | C11: BRK.B | D11: Financials | E11: 102 | F11: =IFERROR(__xludf.DUMMYFUNCTION("INDEX(GOOGLEFINANCE(C11,""close"",F$2),2,2)"),451.1) -> 451.1 | G11: =IFERROR(__xludf.DUMMYFUNCTION("GOOGLEFINANCE(C11)"),494.51) -> 494.51 | H11: =(48054.75-14754.3)/E11 -> 326.475 | I11: =E11*G11 -> 50440.02 | J11: =I11/$I$63 -> 0.030860853 | K11: =IFERROR(__xludf.DUMMYFUNCTION("GOOGLEFINANCE(C11,""changepct"")/100"),7.000000000000001E-4) -> 0.0007 | L11: =IFERROR(__xludf.DUMMYFUNCTION("SPARKLINE(GoogleFinance(C11, ""price"", TODAY()-30,TODAY()))"),"") | M11: =IFERROR(__xludf.DUMMYFUNCTION("SPARKLINE(GoogleFinance(C11, ""price"", TODAY()-180,TODAY()))"),"") | N11: =(I11)-(H11*E11) -> 17139.57 | O11: =(G11-F11)/F11 -> 0.096231434 | P11: =((G11*E11)-(H11*E11))/(H11*E11) -> 0.51469485
B12: =IFERROR(__xludf.DUMMYFUNCTION("GOOGLEFINANCE(C12,B$3)"),"BHP Group Ltd") -> BHP Group Ltd | C12: BHP | D12: Materials | E12: 200 | F12: =IFERROR(__xludf.DUMMYFUNCTION("INDEX(GOOGLEFINANCE(C12,""close"",F$2),2,2)"),49.21) -> 49.21 | G12: =IFERROR(__xludf.DUMMYFUNCTION("GOOGLEFINANCE(C12)"),79.65) -> 79.65 | H12: =(10953+1304.56)/E12 -> 61.2878 | I12: =E12*G12 -> 15930 | J12: =I12/$I$63 -> 0.0097464948 | K12: =IFERROR(__xludf.DUMMYFUNCTION("GOOGLEFINANCE(C12,""changepct"")/100"),0.021) -> 0.021 | L12: =IFERROR(__xludf.DUMMYFUNCTION("SPARKLINE(GoogleFinance(C12, ""price"", TODAY()-30,TODAY()))"),"") | M12: =IFERROR(__xludf.DUMMYFUNCTION("SPARKLINE(GoogleFinance(C12, ""price"", TODAY()-180,TODAY()))"),"") | N12: =(I12)-(H12*E12) -> 3672.44 | O12: =(G12-F12)/F12 -> 0.61857346 | P12: =((G12*E12)-(H12*E12))/(H12*E12) -> 0.29960612
B13: =IFERROR(__xludf.DUMMYFUNCTION("GOOGLEFINANCE(C13,B$3)"),"Boston Scientific Corp") -> Boston Scientific Corp | C13: BSX | D13: Health Care | E13: 146 | F13: =IFERROR(__xludf.DUMMYFUNCTION("INDEX(GOOGLEFINANCE(C13,""close"",F$2),2,2)"),89.38) -> 89.38 | G13: =IFERROR(__xludf.DUMMYFUNCTION("GOOGLEFINANCE(C13)"),75.15) -> 75.15 | H13: 102.725 | I13: =E13*G13 -> 10971.9 | J13: =I13/$I$63 -> 0.0067129671 | K13: =IFERROR(__xludf.DUMMYFUNCTION("GOOGLEFINANCE(C13,""changepct"")/100"),0.0105) -> 0.0105 | L13: =IFERROR(__xludf.DUMMYFUNCTION("SPARKLINE(GoogleFinance(C13, ""price"", TODAY()-30,TODAY()))"),"") | M13: =IFERROR(__xludf.DUMMYFUNCTION("SPARKLINE(GoogleFinance(C13, ""price"", TODAY()-180,TODAY()))"),"") | N13: =(I13)-(H13*E13) -> -4025.95 | O13: =(G13-F13)/F13 -> -0.15920788 | P13: =((G13*E13)-(H13*E13))/(H13*E13) -> -0.26843514
B14: =IFERROR(__xludf.DUMMYFUNCTION("GOOGLEFINANCE(C14,B$3)"),"Cameco Corp") -> Cameco Corp | C14: CCJ | D14: Materials | E14: 417 | F14: =IFERROR(__xludf.DUMMYFUNCTION("INDEX(GOOGLEFINANCE(C14,""close"",F$2),2,2)"),52.16) -> 52.16 | G14: =IFERROR(__xludf.DUMMYFUNCTION("GOOGLEFINANCE(C14)"),121.08) -> 121.08 | H14: 47.86 | I14: =E14*G14 -> 50490.36 | J14: =I14/$I$63 -> 0.030891653 | K14: =IFERROR(__xludf.DUMMYFUNCTION("GOOGLEFINANCE(C14,""changepct"")/100"),0.0196) -> 0.0196 | L14: =IFERROR(__xludf.DUMMYFUNCTION("SPARKLINE(GoogleFinance(C14, ""price"", TODAY()-30,TODAY()))"),"") | M14: =IFERROR(__xludf.DUMMYFUNCTION("SPARKLINE(GoogleFinance(C14, ""price"", TODAY()-180,TODAY()))"),"") | N14: =(I14)-(H14*E14) -> 30532.74 | O14: =(G14-F14)/F14 -> 1.321319 | P14: =((G14*E14)-(H14*E14))/(H14*E14) -> 1.5298788
B15: =IFERROR(__xludf.DUMMYFUNCTION("GOOGLEFINANCE(C15,B$3)"),"Carrier Global Corp") -> Carrier Global Corp | C15: CARR | D15: Industrials | E15: 80 | F15: =IFERROR(__xludf.DUMMYFUNCTION("INDEX(GOOGLEFINANCE(C15,""close"",F$2),2,2)"),68.33) -> 68.33 | G15: =IFERROR(__xludf.DUMMYFUNCTION("GOOGLEFINANCE(C15)"),63.53) -> 63.53 | H15: =(5733.6-4358.57)/E15 -> 17.187875 | I15: =E15*G15 -> 5082.4 | J15: =I15/$I$63 -> 0.0031095785 | K15: =IFERROR(__xludf.DUMMYFUNCTION("GOOGLEFINANCE(C15,""changepct"")/100"),0.0011) -> 0.0011 | L15: =IFERROR(__xludf.DUMMYFUNCTION("SPARKLINE(GoogleFinance(C15, ""price"", TODAY()-30,TODAY()))"),"") | M15: =IFERROR(__xludf.DUMMYFUNCTION("SPARKLINE(GoogleFinance(C15, ""price"", TODAY()-180,TODAY()))"),"") | N15: =(I15)-(H15*E15) -> 3707.37 | O15: =(G15-F15)/F15 -> -0.070247329 | P15: =((G15*E15)-(H15*E15))/(H15*E15) -> 2.6962103
B16: -- | D16: Cash and Cash Equivalents | E16: 1 | I16: 65366 | J16: =I16/$I$63 -> 0.039993056
B17: =IFERROR(__xludf.DUMMYFUNCTION("GOOGLEFINANCE(C17,B$3)"),"Caterpillar Inc") -> Caterpillar Inc | C17: CAT | D17: Industrials | E17: 150 | F17: =IFERROR(__xludf.DUMMYFUNCTION("INDEX(GOOGLEFINANCE(C17,""close"",F$2),2,2)"),359.77) -> 359.77 | G17: =IFERROR(__xludf.DUMMYFUNCTION("GOOGLEFINANCE(C17)"),768.23) -> 768.23 | H17: 300.31 | I17: =E17*G17 -> 115234.5 | J17: =I17/$I$63 -> 0.070504234 | K17: =IFERROR(__xludf.DUMMYFUNCTION("GOOGLEFINANCE(C17,""changepct"")/100"),0.0147) -> 0.0147 | L17: =IFERROR(__xludf.DUMMYFUNCTION("SPARKLINE(GoogleFinance(C17, ""price"", TODAY()-30,TODAY()))"),"") | M17: =IFERROR(__xludf.DUMMYFUNCTION("SPARKLINE(GoogleFinance(C17, ""price"", TODAY()-180,TODAY()))"),"") | N17: =(I17)-(H17*E17) -> 70188 | O17: =(G17-F17)/F17 -> 1.1353365 | P17: =((G17*E17)-(H17*E17))/(H17*E17) -> 1.5581233
B18: =IFERROR(__xludf.DUMMYFUNCTION("GOOGLEFINANCE(C18,B$3)"),"Check Point Software Technologies Ltd") -> Check Point Software Technologies Ltd | C18: CHKP | D18: Information Technology | E18: 120 | F18: =IFERROR(__xludf.DUMMYFUNCTION("INDEX(GOOGLEFINANCE(C18,""close"",F$2),2,2)"),184.58) -> 184.58 | G18: =IFERROR(__xludf.DUMMYFUNCTION("GOOGLEFINANCE(C18)"),152.44) -> 152.44 | H18: 158.93 | I18: =E18*G18 -> 18292.8 | J18: =I18/$I$63 -> 0.011192133 | K18: =IFERROR(__xludf.DUMMYFUNCTION("GOOGLEFINANCE(C18,""changepct"")/100"),-0.0148) -> -0.0148 | L18: =IFERROR(__xludf.DUMMYFUNCTION("SPARKLINE(GoogleFinance(C18, ""price"", TODAY()-30,TODAY()))"),"") | M18: =IFERROR(__xludf.DUMMYFUNCTION("SPARKLINE(GoogleFinance(C18, ""price"", TODAY()-180,TODAY()))"),"") | N18: =(I18)-(H18*E18) -> -778.8 | O18: =(G18-F18)/F18 -> -0.17412504 | P18: =((G18*E18)-(H18*E18))/(H18*E18) -> -0.040835588
B19: =IFERROR(__xludf.DUMMYFUNCTION("GOOGLEFINANCE(C19,B$3)"),"Chevron Corp") -> Chevron Corp | C19: CVX | D19: Energy | E19: 80 | F19: =IFERROR(__xludf.DUMMYFUNCTION("INDEX(GOOGLEFINANCE(C19,""close"",F$2),2,2)"),146.71) -> 146.71 | G19: =IFERROR(__xludf.DUMMYFUNCTION("GOOGLEFINANCE(C19)"),185.34) -> 185.34 | H19: 147.43 | I19: =E19*G19 -> 14827.2 | J19: =I19/$I$63 -> 0.0090717657 | K19: =IFERROR(__xludf.DUMMYFUNCTION("GOOGLEFINANCE(C19,""changepct"")/100"),0.0023) -> 0.0023 | L19: =IFERROR(__xludf.DUMMYFUNCTION("SPARKLINE(GoogleFinance(C19, ""price"", TODAY()-30,TODAY()))"),"") | M19: =IFERROR(__xludf.DUMMYFUNCTION("SPARKLINE(GoogleFinance(C19, ""price"", TODAY()-180,TODAY()))"),"") | N19: =(I19)-(H19*E19) -> 3032.8 | O19: =(G19-F19)/F19 -> 0.26330857 | P19: =((G19*E19)-(H19*E19))/(H19*E19) -> 0.25713898
B20: =IFERROR(__xludf.DUMMYFUNCTION("GOOGLEFINANCE(C20,B$3)"),"Cigna Group") -> Cigna Group | C20: CI | D20: Health Care | E20: 88 | F20: =IFERROR(__xludf.DUMMYFUNCTION("INDEX(GOOGLEFINANCE(C20,""close"",F$2),2,2)"),274.49) -> 274.49 | G20: =IFERROR(__xludf.DUMMYFUNCTION("GOOGLEFINANCE(C20)"),281.0) -> 281 | H20: 255.56 | I20: =E20*G20 -> 24728 | J20: =I20/$I$63 -> 0.015129399 | K20: =IFERROR(__xludf.DUMMYFUNCTION("GOOGLEFINANCE(C20,""changepct"")/100"),-0.0077) -> -0.0077 | L20: =IFERROR(__xludf.DUMMYFUNCTION("SPARKLINE(GoogleFinance(C20, ""price"", TODAY()-30,TODAY()))"),"") | M20: =IFERROR(__xludf.DUMMYFUNCTION("SPARKLINE(GoogleFinance(C20, ""price"", TODAY()-180,TODAY()))"),"") | N20: =(I20)-(H20*E20) -> 2238.72 | O20: =(G20-F20)/F20 -> 0.023716711 | P20: =((G20*E20)-(H20*E20))/(H20*E20) -> 0.099546095
B21: =IFERROR(__xludf.DUMMYFUNCTION("GOOGLEFINANCE(C21,B$3)"),"Citizens Financial Group Inc") -> Citizens Financial Group Inc | C21: CFG | D21: Financials | E21: 250 | F21: =IFERROR(__xludf.DUMMYFUNCTION("INDEX(GOOGLEFINANCE(C21,""close"",F$2),2,2)"),43.6) -> 43.6 | G21: =IFERROR(__xludf.DUMMYFUNCTION("GOOGLEFINANCE(C21)"),62.07) -> 62.07 | H21: 40.31 | I21: =E21*G21 -> 15517.5 | J21: =I21/$I$63 -> 0.0094941138 | K21: =IFERROR(__xludf.DUMMYFUNCTION("GOOGLEFINANCE(C21,""changepct"")/100"),-0.0067) -> -0.0067 | L21: =IFERROR(__xludf.DUMMYFUNCTION("SPARKLINE(GoogleFinance(C21, ""price"", TODAY()-30,TODAY()))"),"") | M21: =IFERROR(__xludf.DUMMYFUNCTION("SPARKLINE(GoogleFinance(C21, ""price"", TODAY()-180,TODAY()))"),"") | N21: =(I21)-(H21*E21) -> 5440 | O21: =(G21-F21)/F21 -> 0.42362385 | P21: =((G21*E21)-(H21*E21))/(H21*E21) -> 0.53981642
B22: =IFERROR(__xludf.DUMMYFUNCTION("GOOGLEFINANCE(C22,B$3)"),"Coca-Cola Co") -> Coca-Cola Co | C22: KO | D22: Consumer Staples | E22: 264 | F22: =IFERROR(__xludf.DUMMYFUNCTION("INDEX(GOOGLEFINANCE(C22,""close"",F$2),2,2)"),61.84) -> 61.84 | G22: =IFERROR(__xludf.DUMMYFUNCTION("GOOGLEFINANCE(C22)"),80.72) -> 80.72 | H22: 36.67 | I22: =E22*G22 -> 21310.08 | J22: =I22/$I$63 -> 0.013038204 | K22: =IFERROR(__xludf.DUMMYFUNCTION("GOOGLEFINANCE(C22,""changepct"")/100"),0.0019) -> 0.0019 | L22: =IFERROR(__xludf.DUMMYFUNCTION("SPARKLINE(GoogleFinance(C22, ""price"", TODAY()-30,TODAY()))"),"") | M22: =IFERROR(__xludf.DUMMYFUNCTION("SPARKLINE(GoogleFinance(C22, ""price"", TODAY()-180,TODAY()))"),"") | N22: =(I22)-(H22*E22) -> 11629.2 | O22: =(G22-F22)/F22 -> 0.30530401 | P22: =((G22*E22)-(H22*E22))/(H22*E22) -> 1.2012544
B23: =IFERROR(__xludf.DUMMYFUNCTION("GOOGLEFINANCE(C23,B$3)"),"Consolidated Edison Inc") -> Consolidated Edison Inc | C23: ED | D23: Utilities | E23: 161 | F23: =IFERROR(__xludf.DUMMYFUNCTION("INDEX(GOOGLEFINANCE(C23,""close"",F$2),2,2)"),89.03) -> 89.03 | G23: =IFERROR(__xludf.DUMMYFUNCTION("GOOGLEFINANCE(C23)"),111.01) -> 111.01 | H23: 87.1 | I23: =E23*G23 -> 17872.61 | J23: =I23/$I$63 -> 0.010935047 | K23: =IFERROR(__xludf.DUMMYFUNCTION("GOOGLEFINANCE(C23,""changepct"")/100"),-0.009899999999999999) -> -0.0099 | L23: =IFERROR(__xludf.DUMMYFUNCTION("SPARKLINE(GoogleFinance(C23, ""price"", TODAY()-30,TODAY()))"),"") | M23: =IFERROR(__xludf.DUMMYFUNCTION("SPARKLINE(GoogleFinance(C23, ""price"", TODAY()-180,TODAY()))"),"") | N23: =(I23)-(H23*E23) -> 3849.51 | O23: =(G23-F23)/F23 -> 0.24688307 | P23: =((G23*E23)-(H23*E23))/(H23*E23) -> 0.27451206
B24: =IFERROR(__xludf.DUMMYFUNCTION("GOOGLEFINANCE(C24,B$3)"),"Digital Realty Trust Inc") -> Digital Realty Trust Inc | C24: DLR | D24: Real Estate | E24: 69 | F24: =IFERROR(__xludf.DUMMYFUNCTION("INDEX(GOOGLEFINANCE(C24,""close"",F$2),2,2)"),177.0) -> 177 | G24: =IFERROR(__xludf.DUMMYFUNCTION("GOOGLEFINANCE(C24)"),178.24) -> 178.24 | H24: 143.79 | I24: =E24*G24 -> 12298.56 | J24: =I24/$I$63 -> 0.0075246611 | K24: =IFERROR(__xludf.DUMMYFUNCTION("GOOGLEFINANCE(C24,""changepct"")/100"),0.012199999999999999) -> 0.0122 | L24: =IFERROR(__xludf.DUMMYFUNCTION("SPARKLINE(GoogleFinance(C24, ""price"", TODAY()-30,TODAY()))"),"") | M24: =IFERROR(__xludf.DUMMYFUNCTION("SPARKLINE(GoogleFinance(C24, ""price"", TODAY()-180,TODAY()))"),"") | N24: =(I24)-(H24*E24) -> 2377.05 | O24: =(G24-F24)/F24 -> 0.0070056497 | P24: =((G24*E24)-(H24*E24))/(H24*E24) -> 0.23958551
B25: =IFERROR(__xludf.DUMMYFUNCTION("GOOGLEFINANCE(C25,B$3)"),"Domino's Pizza Inc") -> Domino's Pizza Inc | C25: DPZ | D25: Consumer Discretionary | E25: 13 | F25: =IFERROR(__xludf.DUMMYFUNCTION("INDEX(GOOGLEFINANCE(C25,""close"",F$2),2,2)"),434.93) -> 434.93 | G25: =IFERROR(__xludf.DUMMYFUNCTION("GOOGLEFINANCE(C25)"),414.2) -> 414.2 | H25: 389.85 | I25: =E25*G25 -> 5384.6 | J25: =I25/$I$63 -> 0.0032944743 | K25: =IFERROR(__xludf.DUMMYFUNCTION("GOOGLEFINANCE(C25,""changepct"")/100"),0.0346) -> 0.0346 | L25: =IFERROR(__xludf.DUMMYFUNCTION("SPARKLINE(GoogleFinance(C25, ""price"", TODAY()-30,TODAY()))"),"") | M25: =IFERROR(__xludf.DUMMYFUNCTION("SPARKLINE(GoogleFinance(C25, ""price"", TODAY()-180,TODAY()))"),"") | N25: =(I25)-(H25*E25) -> 316.55 | O25: =(G25-F25)/F25 -> -0.047662842 | P25: =((G25*E25)-(H25*E25))/(H25*E25) -> 0.06245992
B26: =IFERROR(__xludf.DUMMYFUNCTION("GOOGLEFINANCE(C26,B$3)"),"eBay Inc") -> eBay Inc | C26: EBAY | D26: Consumer Discretionary | E26: 150 | F26: =IFERROR(__xludf.DUMMYFUNCTION("INDEX(GOOGLEFINANCE(C26,""close"",F$2),2,2)"),62.27) -> 62.27 | G26: =IFERROR(__xludf.DUMMYFUNCTION("GOOGLEFINANCE(C26)"),85.3) -> 85.3 | H26: 41.07 | I26: =E26*G26 -> 12795 | J26: =I26/$I$63 -> 0.0078283993 | K26: =IFERROR(__xludf.DUMMYFUNCTION("GOOGLEFINANCE(C26,""changepct"")/100"),0.011699999999999999) -> 0.0117 | L26: =IFERROR(__xludf.DUMMYFUNCTION("SPARKLINE(GoogleFinance(C26, ""price"", TODAY()-30,TODAY()))"),"") | M26: =IFERROR(__xludf.DUMMYFUNCTION("SPARKLINE(GoogleFinance(C26, ""price"", TODAY()-180,TODAY()))"),"") | N26: =(I26)-(H26*E26) -> 6634.5 | O26: =(G26-F26)/F26 -> 0.36984101 | P26: =((G26*E26)-(H26*E26))/(H26*E26) -> 1.0769418
B27: =IFERROR(__xludf.DUMMYFUNCTION("GOOGLEFINANCE(C27,B$3)"),"Exxon Mobil Corp") -> Exxon Mobil Corp | C27: XOM | D27: Energy | E27: 170 | F27: =IFERROR(__xludf.DUMMYFUNCTION("INDEX(GOOGLEFINANCE(C27,""close"",F$2),2,2)"),107.31) -> 107.31 | G27: =IFERROR(__xludf.DUMMYFUNCTION("GOOGLEFINANCE(C27)"),149.26) -> 149.26 | H27: 102.81 | I27: =E27*G27 -> 25374.2 | J27: =I27/$I$63 -> 0.015524765 | K27: =IFERROR(__xludf.DUMMYFUNCTION("GOOGLEFINANCE(C27,""changepct"")/100"),-0.009899999999999999) -> -0.0099 | L27: =IFERROR(__xludf.DUMMYFUNCTION("SPARKLINE(GoogleFinance(C27, ""price"", TODAY()-30,TODAY()))"),"") | M27: =IFERROR(__xludf.DUMMYFUNCTION("SPARKLINE(GoogleFinance(C27, ""price"", TODAY()-180,TODAY()))"),"") | N27: =(I27)-(H27*E27) -> 7896.5 | O27: =(G27-F27)/F27 -> 0.39092349 | P27: =((G27*E27)-(H27*E27))/(H27*E27) -> 0.4518043
B28: =IFERROR(__xludf.DUMMYFUNCTION("GOOGLEFINANCE(C28,B$3)"),"FedEx Corp") -> FedEx Corp | C28: FDX | D28: Industrials | E28: 60 | F28: =IFERROR(__xludf.DUMMYFUNCTION("INDEX(GOOGLEFINANCE(C28,""close"",F$2),2,2)"),274.28) -> 274.28 | G28: =IFERROR(__xludf.DUMMYFUNCTION("GOOGLEFINANCE(C28)"),386.56) -> 386.56 | H28: 278.57 | I28: =E28*G28 -> 23193.6 | J28: =I28/$I$63 -> 0.014190603 | K28: =IFERROR(__xludf.DUMMYFUNCTION("GOOGLEFINANCE(C28,""changepct"")/100"),0.0074) -> 0.0074 | L28: =IFERROR(__xludf.DUMMYFUNCTION("SPARKLINE(GoogleFinance(C28, ""price"", TODAY()-30,TODAY()))"),"") | M28: =IFERROR(__xludf.DUMMYFUNCTION("SPARKLINE(GoogleFinance(C28, ""price"", TODAY()-180,TODAY()))"),"") | N28: =(I28)-(H28*E28) -> 6479.4 | O28: =(G28-F28)/F28 -> 0.4093627 | P28: =((G28*E28)-(H28*E28))/(H28*E28) -> 0.3876584
B29: =IFERROR(__xludf.DUMMYFUNCTION("GOOGLEFINANCE(C29,B$3)"),"Ferrari NV") -> Ferrari NV | C29: RACE | D29: Consumer Discretionary | E29: 40 | F29: =IFERROR(__xludf.DUMMYFUNCTION("INDEX(GOOGLEFINANCE(C29,""close"",F$2),2,2)"),416.42) -> 416.42 | G29: =IFERROR(__xludf.DUMMYFUNCTION("GOOGLEFINANCE(C29)"),373.92) -> 373.92 | H29: 345.92 | I29: =E29*G29 -> 14956.8 | J29: =I29/$I$63 -> 0.0091510592 | K29: =IFERROR(__xludf.DUMMYFUNCTION("GOOGLEFINANCE(C29,""changepct"")/100"),0.0432) -> 0.0432 | L29: =IFERROR(__xludf.DUMMYFUNCTION("SPARKLINE(GoogleFinance(C29, ""price"", TODAY()-30,TODAY()))"),"") | M29: =IFERROR(__xludf.DUMMYFUNCTION("SPARKLINE(GoogleFinance(C29, ""price"", TODAY()-180,TODAY()))"),"") | N29: =(I29)-(H29*E29) -> 1120 | O29: =(G29-F29)/F29 -> -0.10206042 | P29: =((G29*E29)-(H29*E29))/(H29*E29) -> 0.080943571
B30: =IFERROR(__xludf.DUMMYFUNCTION("GOOGLEFINANCE(C30,B$3)"),"General Dynamics Corp") -> General Dynamics Corp | C30: GD | D30: Industrials | E30: 45 | F30: =IFERROR(__xludf.DUMMYFUNCTION("INDEX(GOOGLEFINANCE(C30,""close"",F$2),2,2)"),261.01) -> 261.01 | G30: =IFERROR(__xludf.DUMMYFUNCTION("GOOGLEFINANCE(C30)"),351.18) -> 351.18 | H30: 226.68 | I30: =E30*G30 -> 15803.1 | J30: =I30/$I$63 -> 0.0096688532 | K30: =IFERROR(__xludf.DUMMYFUNCTION("GOOGLEFINANCE(C30,""changepct"")/100"),0.0063) -> 0.0063 | L30: =IFERROR(__xludf.DUMMYFUNCTION("SPARKLINE(GoogleFinance(C30, ""price"", TODAY()-30,TODAY()))"),"") | M30: =IFERROR(__xludf.DUMMYFUNCTION("SPARKLINE(GoogleFinance(C30, ""price"", TODAY()-180,TODAY()))"),"") | N30: =(I30)-(H30*E30) -> 5602.5 | O30: =(G30-F30)/F30 -> 0.34546569 | P30: =((G30*E30)-(H30*E30))/(H30*E30) -> 0.5492324
B31: =IFERROR(__xludf.DUMMYFUNCTION("GOOGLEFINANCE(C31,B$3)"),"Gilead Sciences Inc") -> Gilead Sciences Inc | C31: GILD | D31: Health Care | E31: 205 | F31: =IFERROR(__xludf.DUMMYFUNCTION("INDEX(GOOGLEFINANCE(C31,""close"",F$2),2,2)"),91.88) -> 91.88 | G31: =IFERROR(__xludf.DUMMYFUNCTION("GOOGLEFINANCE(C31)"),147.64) -> 147.64 | H31: 23.03 | I31: =E31*G31 -> 30266.2 | J31: =I31/$I$63 -> 0.018517851 | K31: =IFERROR(__xludf.DUMMYFUNCTION("GOOGLEFINANCE(C31,""changepct"")/100"),-0.0146) -> -0.0146 | L31: =IFERROR(__xludf.DUMMYFUNCTION("SPARKLINE(GoogleFinance(C31, ""price"", TODAY()-30,TODAY()))"),"") | M31: =IFERROR(__xludf.DUMMYFUNCTION("SPARKLINE(GoogleFinance(C31, ""price"", TODAY()-180,TODAY()))"),"") | N31: =(I31)-(H31*E31) -> 25545.05 | O31: =(G31-F31)/F31 -> 0.60687854 | P31: =((G31*E31)-(H31*E31))/(H31*E31) -> 5.4107686
B32: =IFERROR(__xludf.DUMMYFUNCTION("GOOGLEFINANCE(C32,B$3)"),"Goldman Sachs Group Inc") -> Goldman Sachs Group Inc | C32: GS | D32: Financials | E32: 60 | F32: =IFERROR(__xludf.DUMMYFUNCTION("INDEX(GOOGLEFINANCE(C32,""close"",F$2),2,2)"),574.97) -> 574.97 | G32: =IFERROR(__xludf.DUMMYFUNCTION("GOOGLEFINANCE(C32)"),902.27) -> 902.27 | H32: 195.29 | I32: =E32*G32 -> 54136.2 | J32: =I32/$I$63 -> 0.033122297 | K32: =IFERROR(__xludf.DUMMYFUNCTION("GOOGLEFINANCE(C32,""changepct"")/100"),0.011200000000000002) -> 0.0112 | L32: =IFERROR(__xludf.DUMMYFUNCTION("SPARKLINE(GoogleFinance(C32, ""price"", TODAY()-30,TODAY()))"),"") | M32: =IFERROR(__xludf.DUMMYFUNCTION("SPARKLINE(GoogleFinance(C32, ""price"", TODAY()-180,TODAY()))"),"") | N32: =(I32)-(H32*E32) -> 42418.8 | O32: =(G32-F32)/F32 -> 0.56924709 | P32: =((G32*E32)-(H32*E32))/(H32*E32) -> 3.6201546
B33: =IFERROR(__xludf.DUMMYFUNCTION("GOOGLEFINANCE(C33,B$3)"),"Home Depot Inc") -> Home Depot Inc | C33: HD | D33: Consumer Discretionary | E33: 100 | F33: =IFERROR(__xludf.DUMMYFUNCTION("INDEX(GOOGLEFINANCE(C33,""close"",F$2),2,2)"),388.46) -> 388.46 | G33: =IFERROR(__xludf.DUMMYFUNCTION("GOOGLEFINANCE(C33)"),384.48) -> 384.48 | H33: 73.51 | I33: =E33*G33 -> 38448 | J33: =I33/$I$63 -> 0.023523743 | K33: =IFERROR(__xludf.DUMMYFUNCTION("GOOGLEFINANCE(C33,""changepct"")/100"),0.0199) -> 0.0199 | L33: =IFERROR(__xludf.DUMMYFUNCTION("SPARKLINE(GoogleFinance(C33, ""price"", TODAY()-30,TODAY()))"),"") | M33: =IFERROR(__xludf.DUMMYFUNCTION("SPARKLINE(GoogleFinance(C33, ""price"", TODAY()-180,TODAY()))"),"") | N33: =(I33)-(H33*E33) -> 31097 | O33: =(G33-F33)/F33 -> -0.010245585 | P33: =((G33*E33)-(H33*E33))/(H33*E33) -> 4.2303088
B34: =IFERROR(__xludf.DUMMYFUNCTION("GOOGLEFINANCE(C34,B$3)"),"Huron Consulting Group Inc") -> Huron Consulting Group Inc | C34: HURN | D34: Industrials | E34: 175 | F34: =IFERROR(__xludf.DUMMYFUNCTION("INDEX(GOOGLEFINANCE(C34,""close"",F$2),2,2)"),123.31) -> 123.31 | G34: =IFERROR(__xludf.DUMMYFUNCTION("GOOGLEFINANCE(C34)"),126.36) -> 126.36 | H34: 67.56 | I34: =E34*G34 -> 22113 | J34: =I34/$I$63 -> 0.013529456 | K34: =IFERROR(__xludf.DUMMYFUNCTION("GOOGLEFINANCE(C34,""changepct"")/100"),-0.0063) -> -0.0063 | L34: =IFERROR(__xludf.DUMMYFUNCTION("SPARKLINE(GoogleFinance(C34, ""price"", TODAY()-30,TODAY()))"),"") | M34: =IFERROR(__xludf.DUMMYFUNCTION("SPARKLINE(GoogleFinance(C34, ""price"", TODAY()-180,TODAY()))"),"") | N34: =(I34)-(H34*E34) -> 10290 | O34: =(G34-F34)/F34 -> 0.024734409 | P34: =((G34*E34)-(H34*E34))/(H34*E34) -> 0.87033748
B35: =IFERROR(__xludf.DUMMYFUNCTION("GOOGLEFINANCE(C35,B$3)"),"Intercontinental Exchange Inc") -> Intercontinental Exchange Inc | C35: ICE | D35: Financials | E35: 130 | F35: =IFERROR(__xludf.DUMMYFUNCTION("INDEX(GOOGLEFINANCE(C35,""close"",F$2),2,2)"),149.34) -> 149.34 | G35: =IFERROR(__xludf.DUMMYFUNCTION("GOOGLEFINANCE(C35)"),155.36) -> 155.36 | H35: 91.59 | I35: =E35*G35 -> 20196.8 | J35: =I35/$I$63 -> 0.012357062 | K35: =IFERROR(__xludf.DUMMYFUNCTION("GOOGLEFINANCE(C35,""changepct"")/100"),0.008199999999999999) -> 0.0082 | L35: =IFERROR(__xludf.DUMMYFUNCTION("SPARKLINE(GoogleFinance(C35, ""price"", TODAY()-30,TODAY()))"),"") | M35: =IFERROR(__xludf.DUMMYFUNCTION("SPARKLINE(GoogleFinance(C35, ""price"", TODAY()-180,TODAY()))"),"") | N35: =(I35)-(H35*E35) -> 8290.1 | O35: =(G35-F35)/F35 -> 0.0403107 | P35: =((G35*E35)-(H35*E35))/(H35*E35) -> 0.69625505
B36: =IFERROR(__xludf.DUMMYFUNCTION("GOOGLEFINANCE(C36,B$3)"),"Intuitive Surgical Inc") -> Intuitive Surgical Inc | C36: ISRG | D36: Health Care | E36: 47 | F36: =IFERROR(__xludf.DUMMYFUNCTION("INDEX(GOOGLEFINANCE(C36,""close"",F$2),2,2)"),524.03) -> 524.03 | G36: =IFERROR(__xludf.DUMMYFUNCTION("GOOGLEFINANCE(C36)"),494.02) -> 494.02 | H36: 533.21 | I36: =E36*G36 -> 23218.94 | J36: =I36/$I$63 -> 0.014206107 | K36: =IFERROR(__xludf.DUMMYFUNCTION("GOOGLEFINANCE(C36,""changepct"")/100"),0.0039000000000000003) -> 0.0039 | L36: =IFERROR(__xludf.DUMMYFUNCTION("SPARKLINE(GoogleFinance(C36, ""price"", TODAY()-30,TODAY()))"),"") | M36: =IFERROR(__xludf.DUMMYFUNCTION("SPARKLINE(GoogleFinance(C36, ""price"", TODAY()-180,TODAY()))"),"") | N36: =(I36)-(H36*E36) -> -1841.93 | O36: =(G36-F36)/F36 -> -0.057267714 | P36: =((G36*E36)-(H36*E36))/(H36*E36) -> -0.073498246
B37: =IFERROR(__xludf.DUMMYFUNCTION("GOOGLEFINANCE(C37,B$3)"),"JPMorgan Chase & Co") -> JPMorgan Chase & Co | C37: JPM | D37: Financials | E37: 160 | F37: =IFERROR(__xludf.DUMMYFUNCTION("INDEX(GOOGLEFINANCE(C37,""close"",F$2),2,2)"),240.0) -> 240 | G37: =IFERROR(__xludf.DUMMYFUNCTION("GOOGLEFINANCE(C37)"),297.3) -> 297.3 | H37: 39.94 | I37: =E37*G37 -> 47568 | J37: =I37/$I$63 -> 0.029103657 | K37: =IFERROR(__xludf.DUMMYFUNCTION("GOOGLEFINANCE(C37,""changepct"")/100"),-0.0012) -> -0.0012 | L37: =IFERROR(__xludf.DUMMYFUNCTION("SPARKLINE(GoogleFinance(C37, ""price"", TODAY()-30,TODAY()))"),"") | M37: =IFERROR(__xludf.DUMMYFUNCTION("SPARKLINE(GoogleFinance(C37, ""price"", TODAY()-180,TODAY()))"),"") | N37: =(I37)-(H37*E37) -> 41177.6 | O37: =(G37-F37)/F37 -> 0.23875 | P37: =((G37*E37)-(H37*E37))/(H37*E37) -> 6.4436655
B38: =IFERROR(__xludf.DUMMYFUNCTION("GOOGLEFINANCE(C38,B$3)"),"Lockheed Martin Corp") -> Lockheed Martin Corp | C38: LMT | D38: Industrials | E38: 70 | F38: =IFERROR(__xludf.DUMMYFUNCTION("INDEX(GOOGLEFINANCE(C38,""close"",F$2),2,2)"),482.25) -> 482.25 | G38: =IFERROR(__xludf.DUMMYFUNCTION("GOOGLEFINANCE(C38)"),664.43) -> 664.43 | H38: 430 | I38: =E38*G38 -> 46510.1 | J38: =I38/$I$63 -> 0.0284564 | K38: =IFERROR(__xludf.DUMMYFUNCTION("GOOGLEFINANCE(C38,""changepct"")/100"),0.0058) -> 0.0058 | L38: =IFERROR(__xludf.DUMMYFUNCTION("SPARKLINE(GoogleFinance(C38, ""price"", TODAY()-30,TODAY()))"),"") | M38: =IFERROR(__xludf.DUMMYFUNCTION("SPARKLINE(GoogleFinance(C38, ""price"", TODAY()-180,TODAY()))"),"") | N38: =(I38)-(H38*E38) -> 16410.1 | O38: =(G38-F38)/F38 -> 0.37777087 | P38: =((G38*E38)-(H38*E38))/(H38*E38) -> 0.54518605
B39: =IFERROR(__xludf.DUMMYFUNCTION("GOOGLEFINANCE(C39,B$3)"),"Manulife Financial Corp") -> Manulife Financial Corp | C39: MFC | D39: Financials | E39: 854 | F39: =IFERROR(__xludf.DUMMYFUNCTION("INDEX(GOOGLEFINANCE(C39,""close"",F$2),2,2)"),30.52) -> 30.52 | G39: =IFERROR(__xludf.DUMMYFUNCTION("GOOGLEFINANCE(C39)"),35.79) -> 35.79 | H39: 20.03 | I39: =E39*G39 -> 30564.66 | J39: =I39/$I$63 -> 0.018700458 | K39: =IFERROR(__xludf.DUMMYFUNCTION("GOOGLEFINANCE(C39,""changepct"")/100"),-0.004) -> -0.004 | L39: =IFERROR(__xludf.DUMMYFUNCTION("SPARKLINE(GoogleFinance(C39, ""price"", TODAY()-30,TODAY()))"),"") | M39: =IFERROR(__xludf.DUMMYFUNCTION("SPARKLINE(GoogleFinance(C39, ""price"", TODAY()-180,TODAY()))"),"") | N39: =(I39)-(H39*E39) -> 13459.04 | O39: =(G39-F39)/F39 -> 0.17267366 | P39: =((G39*E39)-(H39*E39))/(H39*E39) -> 0.78681977
B40: =IFERROR(__xludf.DUMMYFUNCTION("GOOGLEFINANCE(C40,B$3)"),"Medtronic PLC") -> Medtronic PLC | C40: MDT | D40: Health Care | E40: 250 | F40: =IFERROR(__xludf.DUMMYFUNCTION("INDEX(GOOGLEFINANCE(C40,""close"",F$2),2,2)"),80.22) -> 80.22 | G40: =IFERROR(__xludf.DUMMYFUNCTION("GOOGLEFINANCE(C40)"),96.75) -> 96.75 | H40: 87.54 | I40: =E40*G40 -> 24187.5 | J40: =I40/$I$63 -> 0.014798703 | K40: =IFERROR(__xludf.DUMMYFUNCTION("GOOGLEFINANCE(C40,""changepct"")/100"),-0.0189) -> -0.0189 | L40: =IFERROR(__xludf.DUMMYFUNCTION("SPARKLINE(GoogleFinance(C40, ""price"", TODAY()-30,TODAY()))"),"") | M40: =IFERROR(__xludf.DUMMYFUNCTION("SPARKLINE(GoogleFinance(C40, ""price"", TODAY()-180,TODAY()))"),"") | N40: =(I40)-(H40*E40) -> 2302.5 | O40: =(G40-F40)/F40 -> 0.20605834 | P40: =((G40*E40)-(H40*E40))/(H40*E40) -> 0.10520905
B41: =IFERROR(__xludf.DUMMYFUNCTION("GOOGLEFINANCE(C41,B$3)"),"Metlife Inc") -> Metlife Inc | C41: MET | D41: Financials | E41: 220 | F41: =IFERROR(__xludf.DUMMYFUNCTION("INDEX(GOOGLEFINANCE(C41,""close"",F$2),2,2)"),81.78) -> 81.78 | G41: =IFERROR(__xludf.DUMMYFUNCTION("GOOGLEFINANCE(C41)"),75.34) -> 75.34 | H41: 46.42 | I41: =E41*G41 -> 16574.8 | J41: =I41/$I$63 -> 0.010141004 | K41: =IFERROR(__xludf.DUMMYFUNCTION("GOOGLEFINANCE(C41,""changepct"")/100"),0.0013) -> 0.0013 | L41: =IFERROR(__xludf.DUMMYFUNCTION("SPARKLINE(GoogleFinance(C41, ""price"", TODAY()-30,TODAY()))"),"") | M41: =IFERROR(__xludf.DUMMYFUNCTION("SPARKLINE(GoogleFinance(C41, ""price"", TODAY()-180,TODAY()))"),"") | N41: =(I41)-(H41*E41) -> 6362.4 | O41: =(G41-F41)/F41 -> -0.07874786 | P41: =((G41*E41)-(H41*E41))/(H41*E41) -> 0.62300732
B42: =IFERROR(__xludf.DUMMYFUNCTION("GOOGLEFINANCE(C42,B$3)"),"Microsoft Corp") -> Microsoft Corp | C42: MSFT | D42: Information Technology | E42: 120 | F42: =IFERROR(__xludf.DUMMYFUNCTION("INDEX(GOOGLEFINANCE(C42,""close"",F$2),2,2)"),418.58) -> 418.58 | G42: =IFERROR(__xludf.DUMMYFUNCTION("GOOGLEFINANCE(C42)"),389.0) -> 389 | H42: 397.58 | I42: =E42*G42 -> 46680 | J42: =I42/$I$63 -> 0.02856035 | K42: =IFERROR(__xludf.DUMMYFUNCTION("GOOGLEFINANCE(C42,""changepct"")/100"),0.0118) -> 0.0118 | L42: =IFERROR(__xludf.DUMMYFUNCTION("SPARKLINE(GoogleFinance(C42, ""price"", TODAY()-30,TODAY()))"),"") | M42: =IFERROR(__xludf.DUMMYFUNCTION("SPARKLINE(GoogleFinance(C42, ""price"", TODAY()-180,TODAY()))"),"") | N42: =(I42)-(H42*E42) -> -1029.6 | O42: =(G42-F42)/F42 -> -0.070667495 | P42: =((G42*E42)-(H42*E42))/(H42*E42) -> -0.021580562
B43: =IFERROR(__xludf.DUMMYFUNCTION("GOOGLEFINANCE(C43,B$3)"),"Mp Materials Corp") -> Mp Materials Corp | C43: MP | D43: Materials | E43: 223 | F43: =IFERROR(__xludf.DUMMYFUNCTION("INDEX(GOOGLEFINANCE(C43,""close"",F$2),2,2)"),16.39) -> 16.39 | G43: =IFERROR(__xludf.DUMMYFUNCTION("GOOGLEFINANCE(C43)"),58.44) -> 58.44 | H43: 22.63 | I43: =E43*G43 -> 13032.12 | J43: =I43/$I$63 -> 0.0079734771 | K43: =IFERROR(__xludf.DUMMYFUNCTION("GOOGLEFINANCE(C43,""changepct"")/100"),0.0492) -> 0.0492 | L43: =IFERROR(__xludf.DUMMYFUNCTION("SPARKLINE(GoogleFinance(C43, ""price"", TODAY()-30,TODAY()))"),"") | M43: =IFERROR(__xludf.DUMMYFUNCTION("SPARKLINE(GoogleFinance(C43, ""price"", TODAY()-180,TODAY()))"),"") | N43: =(I43)-(H43*E43) -> 7985.63 | O43: =(G43-F43)/F43 -> 2.5655888 | P43: =((G43*E43)-(H43*E43))/(H43*E43) -> 1.5824127
B44: =IFERROR(__xludf.DUMMYFUNCTION("GOOGLEFINANCE(C44,B$3)"),"NextEra Energy Inc") -> NextEra Energy Inc | C44: NEE | D44: Utilities | E44: 384 | F44: =IFERROR(__xludf.DUMMYFUNCTION("INDEX(GOOGLEFINANCE(C44,""close"",F$2),2,2)"),71.61) -> 71.61 | G44: =IFERROR(__xludf.DUMMYFUNCTION("GOOGLEFINANCE(C44)"),95.68) -> 95.68 | H44: 73.52 | I44: =E44*G44 -> 36741.12 | J44: =I44/$I$63 -> 0.022479418 | K44: =IFERROR(__xludf.DUMMYFUNCTION("GOOGLEFINANCE(C44,""changepct"")/100"),0.0172) -> 0.0172 | L44: =IFERROR(__xludf.DUMMYFUNCTION("SPARKLINE(GoogleFinance(C44, ""price"", TODAY()-30,TODAY()))"),"") | M44: =IFERROR(__xludf.DUMMYFUNCTION("SPARKLINE(GoogleFinance(C44, ""price"", TODAY()-180,TODAY()))"),"") | N44: =(I44)-(H44*E44) -> 8509.44 | O44: =(G44-F44)/F44 -> 0.33612624 | P44: =((G44*E44)-(H44*E44))/(H44*E44) -> 0.30141458
B45: =IFERROR(__xludf.DUMMYFUNCTION("GOOGLEFINANCE(C45,B$3)"),"NRG Energy Inc") -> NRG Energy Inc | C45: NRG | D45: Utilities | E45: 114 | F45: =IFERROR(__xludf.DUMMYFUNCTION("INDEX(GOOGLEFINANCE(C45,""close"",F$2),2,2)"),92.75) -> 92.75 | G45: =IFERROR(__xludf.DUMMYFUNCTION("GOOGLEFINANCE(C45)"),184.03) -> 184.03 | H45: 173.16 | I45: =E45*G45 -> 20979.42 | J45: =I45/$I$63 -> 0.012835895 | K45: =IFERROR(__xludf.DUMMYFUNCTION("GOOGLEFINANCE(C45,""changepct"")/100"),0.0425) -> 0.0425 | L45: =IFERROR(__xludf.DUMMYFUNCTION("SPARKLINE(GoogleFinance(C45, ""price"", TODAY()-30,TODAY()))"),"") | M45: =IFERROR(__xludf.DUMMYFUNCTION("SPARKLINE(GoogleFinance(C45, ""price"", TODAY()-180,TODAY()))"),"") | N45: =(I45)-(H45*E45) -> 1239.18 | O45: =(G45-F45)/F45 -> 0.98415094 | P45: =((G45*E45)-(H45*E45))/(H45*E45) -> 0.062774313
B46: =IFERROR(__xludf.DUMMYFUNCTION("GOOGLEFINANCE(C46,B$3)"),"NVIDIA Corp") -> NVIDIA Corp | C46: NVDA | D46: Information Technology | E46: 142 | F46: =IFERROR(__xludf.DUMMYFUNCTION("INDEX(GOOGLEFINANCE(C46,""close"",F$2),2,2)"),138.31) -> 138.31 | G46: =IFERROR(__xludf.DUMMYFUNCTION("GOOGLEFINANCE(C46)"),192.85) -> 192.85 | H46: 20.56 | I46: =E46*G46 -> 27384.7 | J46: =I46/$I$63 -> 0.016754855 | K46: =IFERROR(__xludf.DUMMYFUNCTION("GOOGLEFINANCE(C46,""changepct"")/100"),0.0068000000000000005) -> 0.0068 | L46: =IFERROR(__xludf.DUMMYFUNCTION("SPARKLINE(GoogleFinance(C46, ""price"", TODAY()-30,TODAY()))"),"") | M46: =IFERROR(__xludf.DUMMYFUNCTION("SPARKLINE(GoogleFinance(C46, ""price"", TODAY()-180,TODAY()))"),"") | N46: =(I46)-(H46*E46) -> 24465.18 | O46: =(G46-F46)/F46 -> 0.39433157 | P46: =((G46*E46)-(H46*E46))/(H46*E46) -> 8.3798638
B47: =IFERROR(__xludf.DUMMYFUNCTION("GOOGLEFINANCE(C47,B$3)"),"Otis Worldwide Corp") -> Otis Worldwide Corp | C47: OTIS | D47: Industrials | E47: 40 | F47: =IFERROR(__xludf.DUMMYFUNCTION("INDEX(GOOGLEFINANCE(C47,""close"",F$2),2,2)"),92.24) -> 92.24 | G47: =IFERROR(__xludf.DUMMYFUNCTION("GOOGLEFINANCE(C47)"),89.91) -> 89.91 | H47: 51.54 | I47: =E47*G47 -> 3596.4 | J47: =I47/$I$63 -> 0.0022003951 | K47: =IFERROR(__xludf.DUMMYFUNCTION("GOOGLEFINANCE(C47,""changepct"")/100"),-0.0070999999999999995) -> -0.0071 | L47: =IFERROR(__xludf.DUMMYFUNCTION("SPARKLINE(GoogleFinance(C47, ""price"", TODAY()-30,TODAY()))"),"") | M47: =IFERROR(__xludf.DUMMYFUNCTION("SPARKLINE(GoogleFinance(C47, ""price"", TODAY()-180,TODAY()))"),"") | N47: =(I47)-(H47*E47) -> 1534.8 | O47: =(G47-F47)/F47 -> -0.025260191 | P47: =((G47*E47)-(H47*E47))/(H47*E47) -> 0.74447031
B48: =IFERROR(__xludf.DUMMYFUNCTION("GOOGLEFINANCE(C48,B$3)"),"Palantir Technologies Inc") -> Palantir Technologies Inc | C48: PLTR | D48: Information Technology | E48: 225 | F48: =IFERROR(__xludf.DUMMYFUNCTION("INDEX(GOOGLEFINANCE(C48,""close"",F$2),2,2)"),75.19) -> 75.19 | G48: =IFERROR(__xludf.DUMMYFUNCTION("GOOGLEFINANCE(C48)"),128.84) -> 128.84 | H48: 37.275 | I48: =E48*G48 -> 28989 | J48: =I48/$I$63 -> 0.017736418 | K48: =IFERROR(__xludf.DUMMYFUNCTION("GOOGLEFINANCE(C48,""changepct"")/100"),-0.013500000000000002) -> -0.0135 | L48: =IFERROR(__xludf.DUMMYFUNCTION("SPARKLINE(GoogleFinance(C48, ""price"", TODAY()-30,TODAY()))"),"") | M48: =IFERROR(__xludf.DUMMYFUNCTION("SPARKLINE(GoogleFinance(C48, ""price"", TODAY()-180,TODAY()))"),"") | N48: =(I48)-(H48*E48) -> 20602.125 | O48: =(G48-F48)/F48 -> 0.71352573 | P48: =((G48*E48)-(H48*E48))/(H48*E48) -> 2.4564722
B49: =IFERROR(__xludf.DUMMYFUNCTION("GOOGLEFINANCE(C49,B$3)"),"Pfizer Inc") -> Pfizer Inc | C49: PFE | D49: Health Care | E49: 190 | F49: =IFERROR(__xludf.DUMMYFUNCTION("INDEX(GOOGLEFINANCE(C49,""close"",F$2),2,2)"),26.61) -> 26.61 | G49: =IFERROR(__xludf.DUMMYFUNCTION("GOOGLEFINANCE(C49)"),27.14) -> 27.14 | H49: 27.08 | I49: =E49*G49 -> 5156.6 | J49: =I49/$I$63 -> 0.0031549765 | K49: =IFERROR(__xludf.DUMMYFUNCTION("GOOGLEFINANCE(C49,""changepct"")/100"),0.003) -> 0.003 | L49: =IFERROR(__xludf.DUMMYFUNCTION("SPARKLINE(GoogleFinance(C49, ""price"", TODAY()-30,TODAY()))"),"") | M49: =IFERROR(__xludf.DUMMYFUNCTION("SPARKLINE(GoogleFinance(C49, ""price"", TODAY()-180,TODAY()))"),"") | N49: =(I49)-(H49*E49) -> 11.4 | O49: =(G49-F49)/F49 -> 0.019917324 | P49: =((G49*E49)-(H49*E49))/(H49*E49) -> 0.0022156573
B50: =IFERROR(__xludf.DUMMYFUNCTION("GOOGLEFINANCE(C50,B$3)"),"Revolution Medicines Inc") -> Revolution Medicines Inc | C50: RVMD | D50: Health Care | E50: 328 | F50: =IFERROR(__xludf.DUMMYFUNCTION("INDEX(GOOGLEFINANCE(C50,""close"",F$2),2,2)"),44.0) -> 44 | G50: =IFERROR(__xludf.DUMMYFUNCTION("GOOGLEFINANCE(C50)"),104.83) -> 104.83 | H50: 39.615 | I50: =E50*G50 -> 34384.24 | J50: =I50/$I$63 -> 0.021037402 | K50: =IFERROR(__xludf.DUMMYFUNCTION("GOOGLEFINANCE(C50,""changepct"")/100"),0.011000000000000001) -> 0.011 | L50: =IFERROR(__xludf.DUMMYFUNCTION("SPARKLINE(GoogleFinance(C50, ""price"", TODAY()-30,TODAY()))"),"") | M50: =IFERROR(__xludf.DUMMYFUNCTION("SPARKLINE(GoogleFinance(C50, ""price"", TODAY()-180,TODAY()))"),"") | N50: =(I50)-(H50*E50) -> 21390.52 | O50: =(G50-F50)/F50 -> 1.3825 | P50: =((G50*E50)-(H50*E50))/(H50*E50) -> 1.6462199
B51: =IFERROR(__xludf.DUMMYFUNCTION("GOOGLEFINANCE(C51,B$3)"),"Rtx Corp") -> Rtx Corp | C51: RTX | D51: Industrials | E51: 80 | F51: =IFERROR(__xludf.DUMMYFUNCTION("INDEX(GOOGLEFINANCE(C51,""close"",F$2),2,2)"),116.01) -> 116.01 | G51: =IFERROR(__xludf.DUMMYFUNCTION("GOOGLEFINANCE(C51)"),198.46) -> 198.46 | H51: 57.34 | I51: =E51*G51 -> 15876.8 | J51: =I51/$I$63 -> 0.0097139453 | K51: =IFERROR(__xludf.DUMMYFUNCTION("GOOGLEFINANCE(C51,""changepct"")/100"),-0.0171) -> -0.0171 | L51: =IFERROR(__xludf.DUMMYFUNCTION("SPARKLINE(GoogleFinance(C51, ""price"", TODAY()-30,TODAY()))"),"") | M51: =IFERROR(__xludf.DUMMYFUNCTION("SPARKLINE(GoogleFinance(C51, ""price"", TODAY()-180,TODAY()))"),"") | N51: =(I51)-(H51*E51) -> 11289.6 | O51: =(G51-F51)/F51 -> 0.71071459 | P51: =((G51*E51)-(H51*E51))/(H51*E51) -> 2.4611092
B52: =IFERROR(__xludf.DUMMYFUNCTION("GOOGLEFINANCE(C52,B$3)"),"T-Mobile Us Inc") -> T-Mobile Us Inc | C52: TMUS | D52: Communication Services | E52: 213 | F52: =IFERROR(__xludf.DUMMYFUNCTION("INDEX(GOOGLEFINANCE(C52,""close"",F$2),2,2)"),219.53) -> 219.53 | G52: =IFERROR(__xludf.DUMMYFUNCTION("GOOGLEFINANCE(C52)"),221.98) -> 221.98 | H52: 140.92 | I52: =E52*G52 -> 47281.74 | J52: =I52/$I$63 -> 0.028928514 | K52: =IFERROR(__xludf.DUMMYFUNCTION("GOOGLEFINANCE(C52,""changepct"")/100"),0.0092) -> 0.0092 | L52: =IFERROR(__xludf.DUMMYFUNCTION("SPARKLINE(GoogleFinance(C52, ""price"", TODAY()-30,TODAY()))"),"") | M52: =IFERROR(__xludf.DUMMYFUNCTION("SPARKLINE(GoogleFinance(C52, ""price"", TODAY()-180,TODAY()))"),"") | N52: =(I52)-(H52*E52) -> 17265.78 | O52: =(G52-F52)/F52 -> 0.011160206 | P52: =((G52*E52)-(H52*E52))/(H52*E52) -> 0.57521998
B53: =IFERROR(__xludf.DUMMYFUNCTION("GOOGLEFINANCE(C53,B$3)"),"Thermo Fisher Scientific Inc") -> Thermo Fisher Scientific Inc | C53: TMO | D53: Health Care | E53: 23 | F53: =IFERROR(__xludf.DUMMYFUNCTION("INDEX(GOOGLEFINANCE(C53,""close"",F$2),2,2)"),522.57) -> 522.57 | G53: =IFERROR(__xludf.DUMMYFUNCTION("GOOGLEFINANCE(C53)"),515.6) -> 515.6 | H53: 259.18 | I53: =E53*G53 -> 11858.8 | J53: =I53/$I$63 -> 0.0072556015 | K53: =IFERROR(__xludf.DUMMYFUNCTION("GOOGLEFINANCE(C53,""changepct"")/100"),-0.0016) -> -0.0016 | L53: =IFERROR(__xludf.DUMMYFUNCTION("SPARKLINE(GoogleFinance(C53, ""price"", TODAY()-30,TODAY()))"),"") | M53: =IFERROR(__xludf.DUMMYFUNCTION("SPARKLINE(GoogleFinance(C53, ""price"", TODAY()-180,TODAY()))"),"") | N53: =(I53)-(H53*E53) -> 5897.66 | O53: =(G53-F53)/F53 -> -0.013337926 | P53: =((G53*E53)-(H53*E53))/(H53*E53) -> 0.98935103
B54: =IFERROR(__xludf.DUMMYFUNCTION("GOOGLEFINANCE(C54,B$3)"),"Toyota Motor Corp") -> Toyota Motor Corp | C54: TM | D54: Consumer Discretionary | E54: 40 | F54: =IFERROR(__xludf.DUMMYFUNCTION("INDEX(GOOGLEFINANCE(C54,""close"",F$2),2,2)"),193.12) -> 193.12 | G54: =IFERROR(__xludf.DUMMYFUNCTION("GOOGLEFINANCE(C54)"),238.64) -> 238.64 | H54: 121.51 | I54: =E54*G54 -> 9545.6 | J54: =I54/$I$63 -> 0.0058403101 | K54: =IFERROR(__xludf.DUMMYFUNCTION("GOOGLEFINANCE(C54,""changepct"")/100"),0.0026) -> 0.0026 | L54: =IFERROR(__xludf.DUMMYFUNCTION("SPARKLINE(GoogleFinance(C54, ""price"", TODAY()-30,TODAY()))"),"") | M54: =IFERROR(__xludf.DUMMYFUNCTION("SPARKLINE(GoogleFinance(C54, ""price"", TODAY()-180,TODAY()))"),"") | N54: =(I54)-(H54*E54) -> 4685.2 | O54: =(G54-F54)/F54 -> 0.23570837 | P54: =((G54*E54)-(H54*E54))/(H54*E54) -> 0.96395358
B55: =IFERROR(__xludf.DUMMYFUNCTION("GOOGLEFINANCE(C55,B$3)"),"TransMedics Group Inc") -> TransMedics Group Inc | C55: TMDX | D55: Health Care | E55: 278 | F55: =IFERROR(__xludf.DUMMYFUNCTION("INDEX(GOOGLEFINANCE(C55,""close"",F$2),2,2)"),66.5) -> 66.5 | G55: =IFERROR(__xludf.DUMMYFUNCTION("GOOGLEFINANCE(C55)"),137.78) -> 137.78 | H55: 84 | I55: =E55*G55 -> 38302.84 | J55: =I55/$I$63 -> 0.02343493 | K55: =IFERROR(__xludf.DUMMYFUNCTION("GOOGLEFINANCE(C55,""changepct"")/100"),0.0232) -> 0.0232 | L55: =IFERROR(__xludf.DUMMYFUNCTION("SPARKLINE(GoogleFinance(C55, ""price"", TODAY()-30,TODAY()))"),"") | M55: =IFERROR(__xludf.DUMMYFUNCTION("SPARKLINE(GoogleFinance(C55, ""price"", TODAY()-180,TODAY()))"),"") | N55: =(I55)-(H55*E55) -> 14950.84 | O55: =(G55-F55)/F55 -> 1.0718797 | P55: =((G55*E55)-(H55*E55))/(H55*E55) -> 0.6402381
B56: =IFERROR(__xludf.DUMMYFUNCTION("GOOGLEFINANCE(C56,B$3)"),"Union Pacific Corp") -> Union Pacific Corp | C56: UNP | D56: Industrials | E56: 160 | F56: =IFERROR(__xludf.DUMMYFUNCTION("INDEX(GOOGLEFINANCE(C56,""close"",F$2),2,2)"),229.12) -> 229.12 | G56: =IFERROR(__xludf.DUMMYFUNCTION("GOOGLEFINANCE(C56)"),266.66) -> 266.66 | H56: 47.08 | I56: =E56*G56 -> 42665.6 | J56: =I56/$I$63 -> 0.026104209 | K56: =IFERROR(__xludf.DUMMYFUNCTION("GOOGLEFINANCE(C56,""changepct"")/100"),0.011000000000000001) -> 0.011 | L56: =IFERROR(__xludf.DUMMYFUNCTION("SPARKLINE(GoogleFinance(C56, ""price"", TODAY()-30,TODAY()))"),"") | M56: =IFERROR(__xludf.DUMMYFUNCTION("SPARKLINE(GoogleFinance(C56, ""price"", TODAY()-180,TODAY()))"),"") | N56: =(I56)-(H56*E56) -> 35132.8 | O56: =(G56-F56)/F56 -> 0.16384427 | P56: =((G56*E56)-(H56*E56))/(H56*E56) -> 4.6639762
B57: =IFERROR(__xludf.DUMMYFUNCTION("GOOGLEFINANCE(C57,B$3)"),"UnitedHealth Group Inc") -> UnitedHealth Group Inc | C57: UNH | D57: Health Care | E57: 75 | F57: =IFERROR(__xludf.DUMMYFUNCTION("INDEX(GOOGLEFINANCE(C57,""close"",F$2),2,2)"),504.51) -> 504.51 | G57: =IFERROR(__xludf.DUMMYFUNCTION("GOOGLEFINANCE(C57)"),273.95) -> 273.95 | H57: 67.65 | I57: =E57*G57 -> 20546.25 | J57: =I57/$I$63 -> 0.012570867 | K57: =IFERROR(__xludf.DUMMYFUNCTION("GOOGLEFINANCE(C57,""changepct"")/100"),-0.0297) -> -0.0297 | L57: =IFERROR(__xludf.DUMMYFUNCTION("SPARKLINE(GoogleFinance(C57, ""price"", TODAY()-30,TODAY()))"),"") | M57: =IFERROR(__xludf.DUMMYFUNCTION("SPARKLINE(GoogleFinance(C57, ""price"", TODAY()-180,TODAY()))"),"") | N57: =(I57)-(H57*E57) -> 15472.5 | O57: =(G57-F57)/F57 -> -0.45699788 | P57: =((G57*E57)-(H57*E57))/(H57*E57) -> 3.0495196
B58: =IFERROR(__xludf.DUMMYFUNCTION("GOOGLEFINANCE(C58,B$3)"),"Vanguard Sht-Term Inflation-Protected Sec Idx ETF") -> Vanguard Sht-Term Inflation-Protected Sec Idx ETF | C58: VTIP | D58: Cash and Cash Equivalents | E58: 1802 | F58: =IFERROR(__xludf.DUMMYFUNCTION("INDEX(GOOGLEFINANCE(C58,""close"",F$2),2,2)"),48.45) -> 48.45 | G58: =IFERROR(__xludf.DUMMYFUNCTION("GOOGLEFINANCE(C58)"),49.76) -> 49.76 | H58: 47.83 | I58: =E58*G58 -> 89667.52 | J58: =I58/$I$63 -> 0.05486152 | K58: =IFERROR(__xludf.DUMMYFUNCTION("GOOGLEFINANCE(C58,""changepct"")/100"),-2.0E-4) -> -0.0002 | L58: =IFERROR(__xludf.DUMMYFUNCTION("SPARKLINE(GoogleFinance(C58, ""price"", TODAY()-30,TODAY()))"),"") | M58: =IFERROR(__xludf.DUMMYFUNCTION("SPARKLINE(GoogleFinance(C58, ""price"", TODAY()-180,TODAY()))"),"") | N58: =(I58)-(H58*E58) -> 3477.86 | O58: =(G58-F58)/F58 -> 0.027038184 | P58: =((G58*E58)-(H58*E58))/(H58*E58) -> 0.040351244
B59: =IFERROR(__xludf.DUMMYFUNCTION("GOOGLEFINANCE(C59,B$3)"),"Viatris Inc") -> Viatris Inc | C59: VTRS | D59: Health Care | E59: 47 | F59: =IFERROR(__xludf.DUMMYFUNCTION("INDEX(GOOGLEFINANCE(C59,""close"",F$2),2,2)"),12.42) -> 12.42 | G59: =IFERROR(__xludf.DUMMYFUNCTION("GOOGLEFINANCE(C59)"),16.07) -> 16.07 | H59: 11.77 | I59: =E59*G59 -> 755.29 | J59: =I59/$I$63 -> 0.00046211111 | K59: =IFERROR(__xludf.DUMMYFUNCTION("GOOGLEFINANCE(C59,""changepct"")/100"),0.0072) -> 0.0072 | L59: =IFERROR(__xludf.DUMMYFUNCTION("SPARKLINE(GoogleFinance(C59, ""price"", TODAY()-30,TODAY()))"),"") | M59: =IFERROR(__xludf.DUMMYFUNCTION("SPARKLINE(GoogleFinance(C59, ""price"", TODAY()-180,TODAY()))"),"") | N59: =(I59)-(H59*E59) -> 202.1 | O59: =(G59-F59)/F59 -> 0.29388084 | P59: =((G59*E59)-(H59*E59))/(H59*E59) -> 0.3653356
B60: =IFERROR(__xludf.DUMMYFUNCTION("GOOGLEFINANCE(C60,B$3)"),"Walt Disney Co") -> Walt Disney Co | C60: DIS | D60: Communication Services | E60: 188 | F60: =IFERROR(__xludf.DUMMYFUNCTION("INDEX(GOOGLEFINANCE(C60,""close"",F$2),2,2)"),110.82) -> 110.82 | G60: =IFERROR(__xludf.DUMMYFUNCTION("GOOGLEFINANCE(C60)"),106.05) -> 106.05 | H60: 79.18 | I60: =E60*G60 -> 19937.4 | J60: =I60/$I$63 -> 0.012198353 | K60: =IFERROR(__xludf.DUMMYFUNCTION("GOOGLEFINANCE(C60,""changepct"")/100"),0.015700000000000002) -> 0.0157 | L60: =IFERROR(__xludf.DUMMYFUNCTION("SPARKLINE(GoogleFinance(C60, ""price"", TODAY()-30,TODAY()))"),"") | M60: =IFERROR(__xludf.DUMMYFUNCTION("SPARKLINE(GoogleFinance(C60, ""price"", TODAY()-180,TODAY()))"),"") | N60: =(I60)-(H60*E60) -> 5051.56 | O60: =(G60-F60)/F60 -> -0.043042772 | P60: =((G60*E60)-(H60*E60))/(H60*E60) -> 0.33935337
B61: =IFERROR(__xludf.DUMMYFUNCTION("GOOGLEFINANCE(C61,B$3)"),"Waste Management Inc") -> Waste Management Inc | C61: WM | D61: Industrials | E61: 48 | F61: =IFERROR(__xludf.DUMMYFUNCTION("INDEX(GOOGLEFINANCE(C61,""close"",F$2),2,2)"),200.54) -> 200.54 | G61: =IFERROR(__xludf.DUMMYFUNCTION("GOOGLEFINANCE(C61)"),229.58) -> 229.58 | H61: 206.28 | I61: =E61*G61 -> 11019.84 | J61: =I61/$I$63 -> 0.0067422984 | K61: =IFERROR(__xludf.DUMMYFUNCTION("GOOGLEFINANCE(C61,""changepct"")/100"),-0.0043) -> -0.0043 | L61: =IFERROR(__xludf.DUMMYFUNCTION("SPARKLINE(GoogleFinance(C61, ""price"", TODAY()-30,TODAY()))"),"") | M61: =IFERROR(__xludf.DUMMYFUNCTION("SPARKLINE(GoogleFinance(C61, ""price"", TODAY()-180,TODAY()))"),"") | N61: =(I61)-(H61*E61) -> 1118.4 | O61: =(G61-F61)/F61 -> 0.14480902 | P61: =((G61*E61)-(H61*E61))/(H61*E61) -> 0.11295327
H63: Total Portfolio Value: | I63: =sum(I4:I61) -> 1634433.8

Sheet PRACTICE Equity Price Data
B1: .INX | C1: .IXIC | D1: .DJI | E1: RUT | F1: ADBE | G1: AMZN | H1: AWK | I1: AAPL | J1: AMAT | K1: BK | L1: BCS | M1: BRK.B | N1: BHP | O1: BIIB | P1: CARR | Q1: CAT | R1: CCJ | S1: CHKP | T1: CVX | U1: CI | V1: CFG | W1: KO | X1: ED | Y1: DLR | Z1: DLTR | AA1: DPZ | AB1: EBAY | AC1: XOM | AD1: FDX | AE1: RACE | AF1: GD | AG1: GM | AH1: GILD | AI1: GS | AJ1: HD | AK1: HURN | AL1: ICE | AM1: ISRG | AN1: JPM | AO1: LMT | AP1: LULU | AQ1: MFC | AR1: MDT | AS1: MET | AT1: MSFT | AU1: NEE | AV1: NVDA | AW1: OTIS | AX1: ONON | AY1: PLTR | AZ1: PYPL | BA1: PFE | BB1: RTX | BC1: TMUS | BD1: TMO | BE1: TM | BF1: TMDX | BG1: UAA | BH1: UNP | BI1: UNH | BJ1: VTIP | BK1: VTRS | BL1: WM | BM1: DIS | BN1: CASH
A2: =IFERROR(__xludf.DUMMYFUNCTION("INDEX(GOOGLEFINANCE(F$1, ""price"", DATE(2024,5,13), TODAY(), ""DAILY""), ,1)"),"#REF!") -> #REF! | B2: =IFERROR(__xludf.DUMMYFUNCTION("INDEX(GOOGLEFINANCE(B$1, ""price"", DATE(2024,5,13), TODAY(), ""DAILY""), ,2)"),"Close") -> Close | C2: =IFERROR(__xludf.DUMMYFUNCTION("INDEX(GOOGLEFINANCE(C$1, ""price"", DATE(2024,5,13), TODAY(), ""DAILY""), ,2)"),"Close") -> Close | D2: =IFERROR(__xludf.DUMMYFUNCTION("INDEX(GOOGLEFINANCE(D$1, ""price"", DATE(2024,5,13), TODAY(), ""DAILY""), ,2)"),"Close") -> Close | E2: =IFERROR(__xludf.DUMMYFUNCTION("INDEX(GOOGLEFINANCE(E$1, ""price"", DATE(2024,5,13), TODAY(), ""DAILY""), ,2)"),"Close") -> Close | F2: =IFERROR(__xludf.DUMMYFUNCTION("INDEX(GOOGLEFINANCE(F$1, ""price"", DATE(2024,5,13), TODAY(), ""DAILY""), ,2)"),"Close") -> Close | G2: =IFERROR(__xludf.DUMMYFUNCTION("INDEX(GOOGLEFINANCE(G$1, ""price"", DATE(2024,5,13), TODAY(), ""DAILY""), ,2)"),"Close") -> Close | H2: =IFERROR(__xludf.DUMMYFUNCTION("INDEX(GOOGLEFINANCE(H$1, ""price"", DATE(2024,5,13), TODAY(), ""DAILY""), ,2)"),"Close") -> Close | I2: =IFERROR(__xludf.DUMMYFUNCTION("INDEX(GOOGLEFINANCE(I$1, ""price"", DATE(2024,5,13), TODAY(), ""DAILY""), ,2)"),"Close") -> Close | J2: =IFERROR(__xludf.DUMMYFUNCTION("INDEX(GOOGLEFINANCE(J$1, ""price"", DATE(2024,5,13), TODAY(), ""DAILY""), ,2)"),"Close") -> Close | K2: =IFERROR(__xludf.DUMMYFUNCTION("INDEX(GOOGLEFINANCE(K$1, ""price"", DATE(2024,5,13), TODAY(), ""DAILY""), ,2)"),"Close") -> Close | L2: =IFERROR(__xludf.DUMMYFUNCTION("INDEX(GOOGLEFINANCE(L$1, ""price"", DATE(2024,5,13), TODAY(), ""DAILY""), ,2)"),"Close") -> Close | M2: =IFERROR(__xludf.DUMMYFUNCTION("INDEX(GOOGLEFINANCE(M$1, ""price"", DATE(2024,5,13), TODAY(), ""DAILY""), ,2)"),"Close") -> Close | N2: =IFERROR(__xludf.DUMMYFUNCTION("INDEX(GOOGLEFINANCE(N$1, ""price"", DATE(2024,5,13), TODAY(), ""DAILY""), ,2)"),"Close") -> Close | O2: =IFERROR(__xludf.DUMMYFUNCTION("INDEX(GOOGLEFINANCE(O$1, ""price"", DATE(2024,5,13), TODAY(), ""DAILY""), ,2)"),"Close") -> Close | P2: =IFERROR(__xludf.DUMMYFUNCTION("INDEX(GOOGLEFINANCE(P$1, ""price"", DATE(2024,5,13), TODAY(), ""DAILY""), ,2)"),"Close") -> Close | Q2: =IFERROR(__xludf.DUMMYFUNCTION("INDEX(GOOGLEFINANCE(Q$1, ""price"", DATE(2024,5,13), TODAY(), ""DAILY""), ,2)"),"Close") -> Close | R2: =IFERROR(__xludf.DUMMYFUNCTION("INDEX(GOOGLEFINANCE(R$1, ""price"", DATE(2024,5,13), TODAY(), ""DAILY""), ,2)"),"Close") -> Close | S2: =IFERROR(__xludf.DUMMYFUNCTION("INDEX(GOOGLEFINANCE(S$1, ""price"", DATE(2024,5,13), TODAY(), ""DAILY""), ,2)"),"Close") -> Close | T2: =IFERROR(__xludf.DUMMYFUNCTION("INDEX(GOOGLEFINANCE(T$1, ""price"", DATE(2024,5,13), TODAY(), ""DAILY""), ,2)"),"Close") -> Close | U2: =IFERROR(__xludf.DUMMYFUNCTION("INDEX(GOOGLEFINANCE(U$1, ""price"", DATE(2024,5,13), TODAY(), ""DAILY""), ,2)"),"Close") -> Close | V2: =IFERROR(__xludf.DUMMYFUNCTION("INDEX(GOOGLEFINANCE(V$1, ""price"", DATE(2024,5,13), TODAY(), ""DAILY""), ,2)"),"Close") -> Close | W2: =IFERROR(__xludf.DUMMYFUNCTION("INDEX(GOOGLEFINANCE(W$1, ""price"", DATE(2024,5,13), TODAY(), ""DAILY""), ,2)"),"Close") -> Close | X2: =IFERROR(__xludf.DUMMYFUNCTION("INDEX(GOOGLEFINANCE(X$1, ""price"", DATE(2024,5,13), TODAY(), ""DAILY""), ,2)"),"Close") -> Close | Y2: =IFERROR(__xludf.DUMMYFUNCTION("INDEX(GOOGLEFINANCE(Y$1, ""price"", DATE(2024,5,13), TODAY(), ""DAILY""), ,2)"),"Close") -> Close | Z2: =IFERROR(__xludf.DUMMYFUNCTION("INDEX(GOOGLEFINANCE(Z$1, ""price"", DATE(2024,5,13), TODAY(), ""DAILY""), ,2)"),"Close") -> Close | AA2: =IFERROR(__xludf.DUMMYFUNCTION("INDEX(GOOGLEFINANCE(AA$1, ""price"", DATE(2024,5,13), TODAY(), ""DAILY""), ,2)"),"Close") -> Close | AB2: =IFERROR(__xludf.DUMMYFUNCTION("INDEX(GOOGLEFINANCE(AB$1, ""price"", DATE(2024,5,13), TODAY(), ""DAILY""), ,2)"),"Close") -> Close | AC2: =IFERROR(__xludf.DUMMYFUNCTION("INDEX(GOOGLEFINANCE(AC$1, ""price"", DATE(2024,5,13), TODAY(), ""DAILY""), ,2)"),"Close") -> Close | AD2: =IFERROR(__xludf.DUMMYFUNCTION("INDEX(GOOGLEFINANCE(AD$1, ""price"", DATE(2024,5,13), TODAY(), ""DAILY""), ,2)"),"Close") -> Close | AE2: =IFERROR(__xludf.DUMMYFUNCTION("INDEX(GOOGLEFINANCE(AE$1, ""price"", DATE(2024,5,13), TODAY(), ""DAILY""), ,2)"),"Close") -> Close | AF2: =IFERROR(__xludf.DUMMYFUNCTION("INDEX(GOOGLEFINANCE(AF$1, ""price"", DATE(2024,5,13), TODAY(), ""DAILY""), ,2)"),"Close") -> Close | AG2: =IFERROR(__xludf.DUMMYFUNCTION("INDEX(GOOGLEFINANCE(AG$1, ""price"", DATE(2024,5,13), TODAY(), ""DAILY""), ,2)"),"Close") -> Close | AH2: =IFERROR(__xludf.DUMMYFUNCTION("INDEX(GOOGLEFINANCE(AH$1, ""price"", DATE(2024,5,13), TODAY(), ""DAILY""), ,2)"),"Close") -> Close | AI2: =IFERROR(__xludf.DUMMYFUNCTION("INDEX(GOOGLEFINANCE(AI$1, ""price"", DATE(2024,5,13), TODAY(), ""DAILY""), ,2)"),"Close") -> Close | AJ2: =IFERROR(__xludf.DUMMYFUNCTION("INDEX(GOOGLEFINANCE(AJ$1, ""price"", DATE(2024,5,13), TODAY(), ""DAILY""), ,2)"),"Close") -> Close | AK2: =IFERROR(__xludf.DUMMYFUNCTION("INDEX(GOOGLEFINANCE(AK$1, ""price"", DATE(2024,5,13), TODAY(), ""DAILY""), ,2)"),"Close") -> Close | AL2: =IFERROR(__xludf.DUMMYFUNCTION("INDEX(GOOGLEFINANCE(AL$1, ""price"", DATE(2024,5,13), TODAY(), ""DAILY""), ,2)"),"Close") -> Close | AM2: =IFERROR(__xludf.DUMMYFUNCTION("INDEX(GOOGLEFINANCE(AM$1, ""price"", DATE(2024,5,13), TODAY(), ""DAILY""), ,2)"),"Close") -> Close | AN2: =IFERROR(__xludf.DUMMYFUNCTION("INDEX(GOOGLEFINANCE(AN$1, ""price"", DATE(2024,5,13), TODAY(), ""DAILY""), ,2)"),"Close") -> Close | AO2: =IFERROR(__xludf.DUMMYFUNCTION("INDEX(GOOGLEFINANCE(AO$1, ""price"", DATE(2024,5,13), TODAY(), ""DAILY""), ,2)"),"Close") -> Close | AP2: =IFERROR(__xludf.DUMMYFUNCTION("INDEX(GOOGLEFINANCE(AP$1, ""price"", DATE(2024,5,13), TODAY(), ""DAILY""), ,2)"),"Close") -> Close | AQ2: =IFERROR(__xludf.DUMMYFUNCTION("INDEX(GOOGLEFINANCE(AQ$1, ""price"", DATE(2024,5,13), TODAY(), ""DAILY""), ,2)"),"Close") -> Close | AR2: =IFERROR(__xludf.DUMMYFUNCTION("INDEX(GOOGLEFINANCE(AR$1, ""price"", DATE(2024,5,13), TODAY(), ""DAILY""), ,2)"),"Close") -> Close | AS2: =IFERROR(__xludf.DUMMYFUNCTION("INDEX(GOOGLEFINANCE(AS$1, ""price"", DATE(2024,5,13), TODAY(), ""DAILY""), ,2)"),"Close") -> Close | AT2: =IFERROR(__xludf.DUMMYFUNCTION("INDEX(GOOGLEFINANCE(AT$1, ""price"", DATE(2024,5,13), TODAY(), ""DAILY""), ,2)"),"Close") -> Close | AU2: =IFERROR(__xludf.DUMMYFUNCTION("INDEX(GOOGLEFINANCE(AU$1, ""price"", DATE(2024,5,13), TODAY(), ""DAILY""), ,2)"),"Close") -> Close | AV2: =IFERROR(__xludf.DUMMYFUNCTION("INDEX(GOOGLEFINANCE(AV$1, ""price"", DATE(2024,5,13), TODAY(), ""DAILY""), ,2)"),"Close") -> Close | AW2: =IFERROR(__xludf.DUMMYFUNCTION("INDEX(GOOGLEFINANCE(AW$1, ""price"", DATE(2024,5,13), TODAY(), ""DAILY""), ,2)"),"Close") -> Close | AX2: =IFERROR(__xludf.DUMMYFUNCTION("INDEX(GOOGLEFINANCE(AX$1, ""price"", DATE(2024,5,13), TODAY(), ""DAILY""), ,2)"),"Close") -> Close | AY2: =IFERROR(__xludf.DUMMYFUNCTION("INDEX(GOOGLEFINANCE(AY$1, ""price"", DATE(2024,5,13), TODAY(), ""DAILY""), ,2)"),"Close") -> Close | AZ2: =IFERROR(__xludf.DUMMYFUNCTION("INDEX(GOOGLEFINANCE(AZ$1, ""price"", DATE(2024,5,13), TODAY(), ""DAILY""), ,2)"),"Close") -> Close | BA2: =IFERROR(__xludf.DUMMYFUNCTION("INDEX(GOOGLEFINANCE(BA$1, ""price"", DATE(2024,5,13), TODAY(), ""DAILY""), ,2)"),"Close") -> Close | BB2: =IFERROR(__xludf.DUMMYFUNCTION("INDEX(GOOGLEFINANCE(BB$1, ""price"", DATE(2024,5,13), TODAY(), ""DAILY""), ,2)"),"Close") -> Close | BC2: =IFERROR(__xludf.DUMMYFUNCTION("INDEX(GOOGLEFINANCE(BC$1, ""price"", DATE(2024,5,13), TODAY(), ""DAILY""), ,2)"),"Close") -> Close | BD2: =IFERROR(__xludf.DUMMYFUNCTION("INDEX(GOOGLEFINANCE(BD$1, ""price"", DATE(2024,5,13), TODAY(), ""DAILY""), ,2)"),"Close") -> Close | BE2: =IFERROR(__xludf.DUMMYFUNCTION("INDEX(GOOGLEFINANCE(BE$1, ""price"", DATE(2024,5,13), TODAY(), ""DAILY""), ,2)"),"Close") -> Close | BF2: =IFERROR(__xludf.DUMMYFUNCTION("INDEX(GOOGLEFINANCE(BF$1, ""price"", DATE(2024,5,13), TODAY(), ""DAILY""), ,2)"),"Close") -> Close | BG2: =IFERROR(__xludf.DUMMYFUNCTION("INDEX(GOOGLEFINANCE(BG$1, ""price"", DATE(2024,5,13), TODAY(), ""DAILY""), ,2)"),"Close") -> Close | BH2: =IFERROR(__xludf.DUMMYFUNCTION("INDEX(GOOGLEFINANCE(BH$1, ""price"", DATE(2024,5,13), TODAY(), ""DAILY""), ,2)"),"Close") -> Close | BI2: =IFERROR(__xludf.DUMMYFUNCTION("INDEX(GOOGLEFINANCE(BI$1, ""price"", DATE(2024,5,13), TODAY(), ""DAILY""), ,2)"),"Close") -> Close | BJ2: =IFERROR(__xludf.DUMMYFUNCTION("INDEX(GOOGLEFINANCE(BJ$1, ""price"", DATE(2024,5,13), TODAY(), ""DAILY""), ,2)"),"Close") -> Close | BK2: =IFERROR(__xludf.DUMMYFUNCTION("INDEX(GOOGLEFINANCE(BK$1, ""price"", DATE(2024,5,13), TODAY(), ""DAILY""), ,2)"),"Close") -> Close | BL2: =IFERROR(__xludf.DUMMYFUNCTION("INDEX(GOOGLEFINANCE(BL$1, ""price"", DATE(2024,5,13), TODAY(), ""DAILY""), ,2)"),"Close") -> Close | BM2: =IFERROR(__xludf.DUMMYFUNCTION("INDEX(GOOGLEFINANCE(BM$1, ""price"", DATE(2024,5,13), TODAY(), ""DAILY""), ,2)"),"Close") -> Close | BN2: Close
A3: 45425.667 | B3: =IFERROR(__xludf.DUMMYFUNCTION("""COMPUTED_VALUE"""),5221.42) -> 5221.42 | C3: =IFERROR(__xludf.DUMMYFUNCTION("""COMPUTED_VALUE"""),16388.24) -> 16388.24 | D3: =IFERROR(__xludf.DUMMYFUNCTION("""COMPUTED_VALUE"""),39431.51) -> 39431.51 | E3: =IFERROR(__xludf.DUMMYFUNCTION("""COMPUTED_VALUE"""),2062.12) -> 2062.12 | F3: =IFERROR(__xludf.DUMMYFUNCTION("""COMPUTED_VALUE"""),483.11) -> 483.11 | G3: =IFERROR(__xludf.DUMMYFUNCTION("""COMPUTED_VALUE"""),186.57) -> 186.57 | H3: =IFERROR(__xludf.DUMMYFUNCTION("""COMPUTED_VALUE"""),133.78) -> 133.78 | I3: =IFERROR(__xludf.DUMMYFUNCTION("""COMPUTED_VALUE"""),186.28) -> 186.28 | J3: =IFERROR(__xludf.DUMMYFUNCTION("""COMPUTED_VALUE"""),206.63) -> 206.63 | K3: =IFERROR(__xludf.DUMMYFUNCTION("""COMPUTED_VALUE"""),57.85) -> 57.85 | L3: =IFERROR(__xludf.DUMMYFUNCTION("""COMPUTED_VALUE"""),10.84) -> 10.84 | M3: =IFERROR(__xludf.DUMMYFUNCTION("""COMPUTED_VALUE"""),411.22) -> 411.22 | N3: =IFERROR(__xludf.DUMMYFUNCTION("""COMPUTED_VALUE"""),57.18) -> 57.18 | O3: =IFERROR(__xludf.DUMMYFUNCTION("""COMPUTED_VALUE"""),225.34) -> 225.34 | P3: =IFERROR(__xludf.DUMMYFUNCTION("""COMPUTED_VALUE"""),64.33) -> 64.33 | Q3: =IFERROR(__xludf.DUMMYFUNCTION("""COMPUTED_VALUE"""),356.68) -> 356.68 | R3: =IFERROR(__xludf.DUMMYFUNCTION("""COMPUTED_VALUE"""),48.98) -> 48.98 | S3: =IFERROR(__xludf.DUMMYFUNCTION("""COMPUTED_VALUE"""),150.03) -> 150.03 | T3: =IFERROR(__xludf.DUMMYFUNCTION("""COMPUTED_VALUE"""),164.53) -> 164.53 | U3: =IFERROR(__xludf.DUMMYFUNCTION("""COMPUTED_VALUE"""),349.14) -> 349.14 | V3: =IFERROR(__xludf.DUMMYFUNCTION("""COMPUTED_VALUE"""),35.94) -> 35.94 | W3: =IFERROR(__xludf.DUMMYFUNCTION("""COMPUTED_VALUE"""),63.58) -> 63.58 | X3: =IFERROR(__xludf.DUMMYFUNCTION("""COMPUTED_VALUE"""),97.64) -> 97.64 | Y3: =IFERROR(__xludf.DUMMYFUNCTION("""COMPUTED_VALUE"""),143.09) -> 143.09 | Z3: =IFERROR(__xludf.DUMMYFUNCTION("""COMPUTED_VALUE"""),120.2) -> 120.2 | AA3: =IFERROR(__xludf.DUMMYFUNCTION("""COMPUTED_VALUE"""),510.24) -> 510.24 | AB3: =IFERROR(__xludf.DUMMYFUNCTION("""COMPUTED_VALUE"""),51.99) -> 51.99 | AC3: =IFERROR(__xludf.DUMMYFUNCTION("""COMPUTED_VALUE"""),117.91) -> 117.91 | AD3: =IFERROR(__xludf.DUMMYFUNCTION("""COMPUTED_VALUE"""),266.89) -> 266.89 | AE3: =IFERROR(__xludf.DUMMYFUNCTION("""COMPUTED_VALUE"""),405.73) -> 405.73 | AF3: =IFERROR(__xludf.DUMMYFUNCTION("""COMPUTED_VALUE"""),293.53) -> 293.53 | AG3: =IFERROR(__xludf.DUMMYFUNCTION("""COMPUTED_VALUE"""),45.17) -> 45.17 | AH3: =IFERROR(__xludf.DUMMYFUNCTION("""COMPUTED_VALUE"""),67.54) -> 67.54 | AI3: =IFERROR(__xludf.DUMMYFUNCTION("""COMPUTED_VALUE"""),453.56) -> 453.56 | AJ3: =IFERROR(__xludf.DUMMYFUNCTION("""COMPUTED_VALUE"""),340.96) -> 340.96 | AK3: =IFERROR(__xludf.DUMMYFUNCTION("""COMPUTED_VALUE"""),87.33) -> 87.33 | AL3: =IFERROR(__xludf.DUMMYFUNCTION("""COMPUTED_VALUE"""),133.74) -> 133.74 | AM3: =IFERROR(__xludf.DUMMYFUNCTION("""COMPUTED_VALUE"""),380.88) -> 380.88 | AN3: =IFERROR(__xludf.DUMMYFUNCTION("""COMPUTED_VALUE"""),198.73) -> 198.73 | AO3: =IFERROR(__xludf.DUMMYFUNCTION("""COMPUTED_VALUE"""),470.56) -> 470.56 | AP3: =IFERROR(__xludf.DUMMYFUNCTION("""COMPUTED_VALUE"""),347.16) -> 347.16 | AQ3: =IFERROR(__xludf.DUMMYFUNCTION("""COMPUTED_VALUE"""),25.69) -> 25.69 | AR3: =IFERROR(__xludf.DUMMYFUNCTION("""COMPUTED_VALUE"""),83.52) -> 83.52 | AS3: =IFERROR(__xludf.DUMMYFUNCTION("""COMPUTED_VALUE"""),72.41) -> 72.41 | AT3: =IFERROR(__xludf.DUMMYFUNCTION("""COMPUTED_VALUE"""),413.72) -> 413.72 | AU3: =IFERROR(__xludf.DUMMYFUNCTION("""COMPUTED_VALUE"""),74.58) -> 74.58 | AV3: =IFERROR(__xludf.DUMMYFUNCTION("""COMPUTED_VALUE"""),90.4) -> 90.4 | AW3: =IFERROR(__xludf.DUMMYFUNCTION("""COMPUTED_VALUE"""),96.59) -> 96.59 | AX3: =IFERROR(__xludf.DUMMYFUNCTION("""COMPUTED_VALUE"""),30.69) -> 30.69 | AY3: =IFERROR(__xludf.DUMMYFUNCTION("""COMPUTED_VALUE"""),20.94) -> 20.94 | AZ3: =IFERROR(__xludf.DUMMYFUNCTION("""COMPUTED_VALUE"""),63.95) -> 63.95 | BA3: =IFERROR(__xludf.DUMMYFUNCTION("""COMPUTED_VALUE"""),28.44) -> 28.44 | BB3: =IFERROR(__xludf.DUMMYFUNCTION("""COMPUTED_VALUE"""),105.8) -> 105.8 | BC3: =IFERROR(__xludf.DUMMYFUNCTION("""COMPUTED_VALUE"""),163.35) -> 163.35 | BD3: =IFERROR(__xludf.DUMMYFUNCTION("""COMPUTED_VALUE"""),590.7) -> 590.7 | BE3: =IFERROR(__xludf.DUMMYFUNCTION("""COMPUTED_VALUE"""),215.64) -> 215.64 | BF3: =IFERROR(__xludf.DUMMYFUNCTION("""COMPUTED_VALUE"""),132.04) -> 132.04 | BG3: =IFERROR(__xludf.DUMMYFUNCTION("""COMPUTED_VALUE"""),6.78) -> 6.78 | BH3: =IFERROR(__xludf.DUMMYFUNCTION("""COMPUTED_VALUE"""),245.68) -> 245.68 | BI3: =IFERROR(__xludf.DUMMYFUNCTION("""COMPUTED_VALUE"""),511.74) -> 511.74 | BJ3: =IFERROR(__xludf.DUMMYFUNCTION("""COMPUTED_VALUE"""),48.05) -> 48.05 | BK3: =IFERROR(__xludf.DUMMYFUNCTION("""COMPUTED_VALUE"""),11.36) -> 11.36 | BL3: =IFERROR(__xludf.DUMMYFUNCTION("""COMPUTED_VALUE"""),210.82) -> 210.82 | BM3: =IFERROR(__xludf.DUMMYFUNCTION("""COMPUTED_VALUE"""),105.83) -> 105.83
A4: 45426.667 | B4: =IFERROR(__xludf.DUMMYFUNCTION("""COMPUTED_VALUE"""),5246.68) -> 5246.68 | C4: =IFERROR(__xludf.DUMMYFUNCTION("""COMPUTED_VALUE"""),16511.18) -> 16511.18 | D4: =IFERROR(__xludf.DUMMYFUNCTION("""COMPUTED_VALUE"""),39558.11) -> 39558.11 | E4: =IFERROR(__xludf.DUMMYFUNCTION("""COMPUTED_VALUE"""),2085.69) -> 2085.69 | F4: =IFERROR(__xludf.DUMMYFUNCTION("""COMPUTED_VALUE"""),475.95) -> 475.95 | G4: =IFERROR(__xludf.DUMMYFUNCTION("""COMPUTED_VALUE"""),187.07) -> 187.07 | H4: =IFERROR(__xludf.DUMMYFUNCTION("""COMPUTED_VALUE"""),133.13) -> 133.13 | I4: =IFERROR(__xludf.DUMMYFUNCTION("""COMPUTED_VALUE"""),187.43) -> 187.43 | J4: =IFERROR(__xludf.DUMMYFUNCTION("""COMPUTED_VALUE"""),209.82) -> 209.82 | K4: =IFERROR(__xludf.DUMMYFUNCTION("""COMPUTED_VALUE"""),58.35) -> 58.35 | L4: =IFERROR(__xludf.DUMMYFUNCTION("""COMPUTED_VALUE"""),11.04) -> 11.04 | M4: =IFERROR(__xludf.DUMMYFUNCTION("""COMPUTED_VALUE"""),410.24) -> 410.24 | N4: =IFERROR(__xludf.DUMMYFUNCTION("""COMPUTED_VALUE"""),58.79) -> 58.79 | O4: =IFERROR(__xludf.DUMMYFUNCTION("""COMPUTED_VALUE"""),226.88) -> 226.88 | P4: =IFERROR(__xludf.DUMMYFUNCTION("""COMPUTED_VALUE"""),64.96) -> 64.96 | Q4: =IFERROR(__xludf.DUMMYFUNCTION("""COMPUTED_VALUE"""),358.18) -> 358.18 | R4: =IFERROR(__xludf.DUMMYFUNCTION("""COMPUTED_VALUE"""),49.98) -> 49.98 | S4: =IFERROR(__xludf.DUMMYFUNCTION("""COMPUTED_VALUE"""),148.91) -> 148.91 | T4: =IFERROR(__xludf.DUMMYFUNCTION("""COMPUTED_VALUE"""),163.61) -> 163.61 | U4: =IFERROR(__xludf.DUMMYFUNCTION("""COMPUTED_VALUE"""),346.42) -> 346.42 | V4: =IFERROR(__xludf.DUMMYFUNCTION("""COMPUTED_VALUE"""),36.43) -> 36.43 | W4: =IFERROR(__xludf.DUMMYFUNCTION("""COMPUTED_VALUE"""),63.1) -> 63.1 | X4: =IFERROR(__xludf.DUMMYFUNCTION("""COMPUTED_VALUE"""),96.64) -> 96.64 | Y4: =IFERROR(__xludf.DUMMYFUNCTION("""COMPUTED_VALUE"""),141.86) -> 141.86 | Z4: =IFERROR(__xludf.DUMMYFUNCTION("""COMPUTED_VALUE"""),118.88) -> 118.88 | AA4: =IFERROR(__xludf.DUMMYFUNCTION("""COMPUTED_VALUE"""),510.71) -> 510.71 | AB4: =IFERROR(__xludf.DUMMYFUNCTION("""COMPUTED_VALUE"""),52.1) -> 52.1 | AC4: =IFERROR(__xludf.DUMMYFUNCTION("""COMPUTED_VALUE"""),117.67) -> 117.67 | AD4: =IFERROR(__xludf.DUMMYFUNCTION("""COMPUTED_VALUE"""),259.04) -> 259.04 | AE4: =IFERROR(__xludf.DUMMYFUNCTION("""COMPUTED_VALUE"""),411.02) -> 411.02 | AF4: =IFERROR(__xludf.DUMMYFUNCTION("""COMPUTED_VALUE"""),294.06) -> 294.06 | AG4: =IFERROR(__xludf.DUMMYFUNCTION("""COMPUTED_VALUE"""),45.03) -> 45.03 | AH4: =IFERROR(__xludf.DUMMYFUNCTION("""COMPUTED_VALUE"""),67.65) -> 67.65 | AI4: =IFERROR(__xludf.DUMMYFUNCTION("""COMPUTED_VALUE"""),458.47) -> 458.47 | AJ4: =IFERROR(__xludf.DUMMYFUNCTION("""COMPUTED_VALUE"""),340.5) -> 340.5 | AK4: =IFERROR(__xludf.DUMMYFUNCTION("""COMPUTED_VALUE"""),87.12) -> 87.12 | AL4: =IFERROR(__xludf.DUMMYFUNCTION("""COMPUTED_VALUE"""),134.39) -> 134.39 | AM4: =IFERROR(__xludf.DUMMYFUNCTION("""COMPUTED_VALUE"""),384.19) -> 384.19 | AN4: =IFERROR(__xludf.DUMMYFUNCTION("""COMPUTED_VALUE"""),201.51) -> 201.51 | AO4: =IFERROR(__xludf.DUMMYFUNCTION("""COMPUTED_VALUE"""),467.18) -> 467.18 | AP4: =IFERROR(__xludf.DUMMYFUNCTION("""COMPUTED_VALUE"""),352.35) -> 352.35 | AQ4: =IFERROR(__xludf.DUMMYFUNCTION("""COMPUTED_VALUE"""),26.01) -> 26.01 | AR4: =IFERROR(__xludf.DUMMYFUNCTION("""COMPUTED_VALUE"""),84.3) -> 84.3 | AS4: =IFERROR(__xludf.DUMMYFUNCTION("""COMPUTED_VALUE"""),73.31) -> 73.31 | AT4: =IFERROR(__xludf.DUMMYFUNCTION("""COMPUTED_VALUE"""),416.56) -> 416.56 | AU4: =IFERROR(__xludf.DUMMYFUNCTION("""COMPUTED_VALUE"""),75.42) -> 75.42 | AV4: =IFERROR(__xludf.DUMMYFUNCTION("""COMPUTED_VALUE"""),91.36) -> 91.36 | AW4: =IFERROR(__xludf.DUMMYFUNCTION("""COMPUTED_VALUE"""),97.07) -> 97.07 | AX4: =IFERROR(__xludf.DUMMYFUNCTION("""COMPUTED_VALUE"""),36.3) -> 36.3 | AY4: =IFERROR(__xludf.DUMMYFUNCTION("""COMPUTED_VALUE"""),21.44) -> 21.44 | AZ4: =IFERROR(__xludf.DUMMYFUNCTION("""COMPUTED_VALUE"""),64.58) -> 64.58 | BA4: =IFERROR(__xludf.DUMMYFUNCTION("""COMPUTED_VALUE"""),28.38) -> 28.38 | BB4: =IFERROR(__xludf.DUMMYFUNCTION("""COMPUTED_VALUE"""),105.7) -> 105.7 | BC4: =IFERROR(__xludf.DUMMYFUNCTION("""COMPUTED_VALUE"""),162.41) -> 162.41 | BD4: =IFERROR(__xludf.DUMMYFUNCTION("""COMPUTED_VALUE"""),594.8) -> 594.8 | BE4: =IFERROR(__xludf.DUMMYFUNCTION("""COMPUTED_VALUE"""),217.12) -> 217.12 | BF4: =IFERROR(__xludf.DUMMYFUNCTION("""COMPUTED_VALUE"""),132.44) -> 132.44 | BG4: =IFERROR(__xludf.DUMMYFUNCTION("""COMPUTED_VALUE"""),6.83) -> 6.83 | BH4: =IFERROR(__xludf.DUMMYFUNCTION("""COMPUTED_VALUE"""),244.94) -> 244.94 | BI4: =IFERROR(__xludf.DUMMYFUNCTION("""COMPUTED_VALUE"""),513.88) -> 513.88 | BJ4: =IFERROR(__xludf.DUMMYFUNCTION("""COMPUTED_VALUE"""),48.09) -> 48.09 | BK4: =IFERROR(__xludf.DUMMYFUNCTION("""COMPUTED_VALUE"""),11.14) -> 11.14 | BL4: =IFERROR(__xludf.DUMMYFUNCTION("""COMPUTED_VALUE"""),209.86) -> 209.86 | BM4: =IFERROR(__xludf.DUMMYFUNCTION("""COMPUTED_VALUE"""),105.35) -> 105.35
A5: 45427.667 | B5: =IFERROR(__xludf.DUMMYFUNCTION("""COMPUTED_VALUE"""),5308.15) -> 5308.15 | C5: =IFERROR(__xludf.DUMMYFUNCTION("""COMPUTED_VALUE"""),16742.39) -> 16742.39 | D5: =IFERROR(__xludf.DUMMYFUNCTION("""COMPUTED_VALUE"""),39908.0) -> 39908 | E5: =IFERROR(__xludf.DUMMYFUNCTION("""COMPUTED_VALUE"""),2109.46) -> 2109.46 | F5: =IFERROR(__xludf.DUMMYFUNCTION("""COMPUTED_VALUE"""),485.35) -> 485.35 | G5: =IFERROR(__xludf.DUMMYFUNCTION("""COMPUTED_VALUE"""),185.99) -> 185.99 | H5: =IFERROR(__xludf.DUMMYFUNCTION("""COMPUTED_VALUE"""),133.75) -> 133.75 | I5: =IFERROR(__xludf.DUMMYFUNCTION("""COMPUTED_VALUE"""),189.72) -> 189.72 | J5: =IFERROR(__xludf.DUMMYFUNCTION("""COMPUTED_VALUE"""),217.49) -> 217.49 | K5: =IFERROR(__xludf.DUMMYFUNCTION("""COMPUTED_VALUE"""),58.8) -> 58.8 | L5: =IFERROR(__xludf.DUMMYFUNCTION("""COMPUTED_VALUE"""),10.94) -> 10.94 | M5: =IFERROR(__xludf.DUMMYFUNCTION("""COMPUTED_VALUE"""),412.76) -> 412.76 | N5: =IFERROR(__xludf.DUMMYFUNCTION("""COMPUTED_VALUE"""),59.27) -> 59.27 | O5: =IFERROR(__xludf.DUMMYFUNCTION("""COMPUTED_VALUE"""),235.32) -> 235.32 | P5: =IFERROR(__xludf.DUMMYFUNCTION("""COMPUTED_VALUE"""),65.8) -> 65.8 | Q5: =IFERROR(__xludf.DUMMYFUNCTION("""COMPUTED_VALUE"""),360.04) -> 360.04 | R5: =IFERROR(__xludf.DUMMYFUNCTION("""COMPUTED_VALUE"""),49.97) -> 49.97 | S5: =IFERROR(__xludf.DUMMYFUNCTION("""COMPUTED_VALUE"""),149.0) -> 149 | T5: =IFERROR(__xludf.DUMMYFUNCTION("""COMPUTED_VALUE"""),163.05) -> 163.05 | U5: =IFERROR(__xludf.DUMMYFUNCTION("""COMPUTED_VALUE"""),343.28) -> 343.28 | V5: =IFERROR(__xludf.DUMMYFUNCTION("""COMPUTED_VALUE"""),36.84) -> 36.84 | W5: =IFERROR(__xludf.DUMMYFUNCTION("""COMPUTED_VALUE"""),63.13) -> 63.13 | X5: =IFERROR(__xludf.DUMMYFUNCTION("""COMPUTED_VALUE"""),96.91) -> 96.91 | Y5: =IFERROR(__xludf.DUMMYFUNCTION("""COMPUTED_VALUE"""),144.64) -> 144.64 | Z5: =IFERROR(__xludf.DUMMYFUNCTION("""COMPUTED_VALUE"""),118.8) -> 118.8 | AA5: =IFERROR(__xludf.DUMMYFUNCTION("""COMPUTED_VALUE"""),517.68) -> 517.68 | AB5: =IFERROR(__xludf.DUMMYFUNCTION("""COMPUTED_VALUE"""),52.42) -> 52.42 | AC5: =IFERROR(__xludf.DUMMYFUNCTION("""COMPUTED_VALUE"""),118.58) -> 118.58 | AD5: =IFERROR(__xludf.DUMMYFUNCTION("""COMPUTED_VALUE"""),259.32) -> 259.32 | AE5: =IFERROR(__xludf.DUMMYFUNCTION("""COMPUTED_VALUE"""),417.21) -> 417.21 | AF5: =IFERROR(__xludf.DUMMYFUNCTION("""COMPUTED_VALUE"""),294.59) -> 294.59 | AG5: =IFERROR(__xludf.DUMMYFUNCTION("""COMPUTED_VALUE"""),45.49) -> 45.49 | AH5: =IFERROR(__xludf.DUMMYFUNCTION("""COMPUTED_VALUE"""),67.01) -> 67.01 | AI5: =IFERROR(__xludf.DUMMYFUNCTION("""COMPUTED_VALUE"""),466.09) -> 466.09 | AJ5: =IFERROR(__xludf.DUMMYFUNCTION("""COMPUTED_VALUE"""),348.67) -> 348.67 | AK5: =IFERROR(__xludf.DUMMYFUNCTION("""COMPUTED_VALUE"""),86.6) -> 86.6 | AL5: =IFERROR(__xludf.DUMMYFUNCTION("""COMPUTED_VALUE"""),137.87) -> 137.87 | AM5: =IFERROR(__xludf.DUMMYFUNCTION("""COMPUTED_VALUE"""),399.39) -> 399.39 | AN5: =IFERROR(__xludf.DUMMYFUNCTION("""COMPUTED_VALUE"""),202.11) -> 202.11 | AO5: =IFERROR(__xludf.DUMMYFUNCTION("""COMPUTED_VALUE"""),464.08) -> 464.08 | AP5: =IFERROR(__xludf.DUMMYFUNCTION("""COMPUTED_VALUE"""),346.85) -> 346.85 | AQ5: =IFERROR(__xludf.DUMMYFUNCTION("""COMPUTED_VALUE"""),26.15) -> 26.15 | AR5: =IFERROR(__xludf.DUMMYFUNCTION("""COMPUTED_VALUE"""),84.72) -> 84.72 | AS5: =IFERROR(__xludf.DUMMYFUNCTION("""COMPUTED_VALUE"""),73.13) -> 73.13 | AT5: =IFERROR(__xludf.DUMMYFUNCTION("""COMPUTED_VALUE"""),423.08) -> 423.08 | AU5: =IFERROR(__xludf.DUMMYFUNCTION("""COMPUTED_VALUE"""),77.05) -> 77.05 | AV5: =IFERROR(__xludf.DUMMYFUNCTION("""COMPUTED_VALUE"""),94.63) -> 94.63 | AW5: =IFERROR(__xludf.DUMMYFUNCTION("""COMPUTED_VALUE"""),97.27) -> 97.27 | AX5: =IFERROR(__xludf.DUMMYFUNCTION("""COMPUTED_VALUE"""),36.42) -> 36.42 | AY5: =IFERROR(__xludf.DUMMYFUNCTION("""COMPUTED_VALUE"""),21.67) -> 21.67 | AZ5: =IFERROR(__xludf.DUMMYFUNCTION("""COMPUTED_VALUE"""),63.9) -> 63.9 | BA5: =IFERROR(__xludf.DUMMYFUNCTION("""COMPUTED_VALUE"""),28.82) -> 28.82 | BB5: =IFERROR(__xludf.DUMMYFUNCTION("""COMPUTED_VALUE"""),105.35) -> 105.35 | BC5: =IFERROR(__xludf.DUMMYFUNCTION("""COMPUTED_VALUE"""),162.68) -> 162.68 | BD5: =IFERROR(__xludf.DUMMYFUNCTION("""COMPUTED_VALUE"""),599.02) -> 599.02 | BE5: =IFERROR(__xludf.DUMMYFUNCTION("""COMPUTED_VALUE"""),219.55) -> 219.55 | BF5: =IFERROR(__xludf.DUMMYFUNCTION("""COMPUTED_VALUE"""),136.14) -> 136.14 | BG5: =IFERROR(__xludf.DUMMYFUNCTION("""COMPUTED_VALUE"""),6.8) -> 6.8 | BH5: =IFERROR(__xludf.DUMMYFUNCTION("""COMPUTED_VALUE"""),246.54) -> 246.54 | BI5: =IFERROR(__xludf.DUMMYFUNCTION("""COMPUTED_VALUE"""),517.55) -> 517.55 | BJ5: =IFERROR(__xludf.DUMMYFUNCTION("""COMPUTED_VALUE"""),48.16) -> 48.16 | BK5: =IFERROR(__xludf.DUMMYFUNCTION("""COMPUTED_VALUE"""),11.07) -> 11.07 | BL5: =IFERROR(__xludf.DUMMYFUNCTION("""COMPUTED_VALUE"""),209.0) -> 209 | BM5: =IFERROR(__xludf.DUMMYFUNCTION("""COMPUTED_VALUE"""),102.77) -> 102.77
A6: 45428.667 | B6: =IFERROR(__xludf.DUMMYFUNCTION("""COMPUTED_VALUE"""),5297.1) -> 5297.1 | C6: =IFERROR(__xludf.DUMMYFUNCTION("""COMPUTED_VALUE"""),16698.32) -> 16698.32 | D6: =IFERROR(__xludf.DUMMYFUNCTION("""COMPUTED_VALUE"""),39869.38) -> 39869.38 | E6: =IFERROR(__xludf.DUMMYFUNCTION("""COMPUTED_VALUE"""),2096.25) -> 2096.25 | F6: =IFERROR(__xludf.DUMMYFUNCTION("""COMPUTED_VALUE"""),482.88) -> 482.88 | G6: =IFERROR(__xludf.DUMMYFUNCTION("""COMPUTED_VALUE"""),183.63) -> 183.63 | H6: =IFERROR(__xludf.DUMMYFUNCTION("""COMPUTED_VALUE"""),134.27) -> 134.27 | I6: =IFERROR(__xludf.DUMMYFUNCTION("""COMPUTED_VALUE"""),189.84) -> 189.84 | J6: =IFERROR(__xludf.DUMMYFUNCTION("""COMPUTED_VALUE"""),214.03) -> 214.03 | K6: =IFERROR(__xludf.DUMMYFUNCTION("""COMPUTED_VALUE"""),58.77) -> 58.77 | L6: =IFERROR(__xludf.DUMMYFUNCTION("""COMPUTED_VALUE"""),10.94) -> 10.94 | M6: =IFERROR(__xludf.DUMMYFUNCTION("""COMPUTED_VALUE"""),413.12) -> 413.12 | N6: =IFERROR(__xludf.DUMMYFUNCTION("""COMPUTED_VALUE"""),60.02) -> 60.02 | O6: =IFERROR(__xludf.DUMMYFUNCTION("""COMPUTED_VALUE"""),230.04) -> 230.04 | P6: =IFERROR(__xludf.DUMMYFUNCTION("""COMPUTED_VALUE"""),65.0) -> 65 | Q6: =IFERROR(__xludf.DUMMYFUNCTION("""COMPUTED_VALUE"""),350.72) -> 350.72 | R6: =IFERROR(__xludf.DUMMYFUNCTION("""COMPUTED_VALUE"""),49.83) -> 49.83 | S6: =IFERROR(__xludf.DUMMYFUNCTION("""COMPUTED_VALUE"""),151.1) -> 151.1 | T6: =IFERROR(__xludf.DUMMYFUNCTION("""COMPUTED_VALUE"""),161.09) -> 161.09 | U6: =IFERROR(__xludf.DUMMYFUNCTION("""COMPUTED_VALUE"""),339.26) -> 339.26 | V6: =IFERROR(__xludf.DUMMYFUNCTION("""COMPUTED_VALUE"""),36.52) -> 36.52 | W6: =IFERROR(__xludf.DUMMYFUNCTION("""COMPUTED_VALUE"""),63.32) -> 63.32 | X6: =IFERROR(__xludf.DUMMYFUNCTION("""COMPUTED_VALUE"""),96.91) -> 96.91 | Y6: =IFERROR(__xludf.DUMMYFUNCTION("""COMPUTED_VALUE"""),144.94) -> 144.94 | Z6: =IFERROR(__xludf.DUMMYFUNCTION("""COMPUTED_VALUE"""),121.3) -> 121.3 | AA6: =IFERROR(__xludf.DUMMYFUNCTION("""COMPUTED_VALUE"""),513.3) -> 513.3 | AB6: =IFERROR(__xludf.DUMMYFUNCTION("""COMPUTED_VALUE"""),52.7) -> 52.7 | AC6: =IFERROR(__xludf.DUMMYFUNCTION("""COMPUTED_VALUE"""),117.87) -> 117.87 | AD6: =IFERROR(__xludf.DUMMYFUNCTION("""COMPUTED_VALUE"""),258.78) -> 258.78 | AE6: =IFERROR(__xludf.DUMMYFUNCTION("""COMPUTED_VALUE"""),419.57) -> 419.57 | AF6: =IFERROR(__xludf.DUMMYFUNCTION("""COMPUTED_VALUE"""),295.75) -> 295.75 | AG6: =IFERROR(__xludf.DUMMYFUNCTION("""COMPUTED_VALUE"""),45.87) -> 45.87 | AH6: =IFERROR(__xludf.DUMMYFUNCTION("""COMPUTED_VALUE"""),67.86) -> 67.86 | AI6: =IFERROR(__xludf.DUMMYFUNCTION("""COMPUTED_VALUE"""),464.52) -> 464.52 | AJ6: =IFERROR(__xludf.DUMMYFUNCTION("""COMPUTED_VALUE"""),342.73) -> 342.73 | AK6: =IFERROR(__xludf.DUMMYFUNCTION("""COMPUTED_VALUE"""),87.72) -> 87.72 | AL6: =IFERROR(__xludf.DUMMYFUNCTION("""COMPUTED_VALUE"""),137.11) -> 137.11 | AM6: =IFERROR(__xludf.DUMMYFUNCTION("""COMPUTED_VALUE"""),396.43) -> 396.43 | AN6: =IFERROR(__xludf.DUMMYFUNCTION("""COMPUTED_VALUE"""),202.47) -> 202.47 | AO6: =IFERROR(__xludf.DUMMYFUNCTION("""COMPUTED_VALUE"""),464.83) -> 464.83 | AP6: =IFERROR(__xludf.DUMMYFUNCTION("""COMPUTED_VALUE"""),338.28) -> 338.28 | AQ6: =IFERROR(__xludf.DUMMYFUNCTION("""COMPUTED_VALUE"""),26.39) -> 26.39 | AR6: =IFERROR(__xludf.DUMMYFUNCTION("""COMPUTED_VALUE"""),85.64) -> 85.64 | AS6: =IFERROR(__xludf.DUMMYFUNCTION("""COMPUTED_VALUE"""),73.47) -> 73.47 | AT6: =IFERROR(__xludf.DUMMYFUNCTION("""COMPUTED_VALUE"""),420.99) -> 420.99 | AU6: =IFERROR(__xludf.DUMMYFUNCTION("""COMPUTED_VALUE"""),76.41) -> 76.41 | AV6: =IFERROR(__xludf.DUMMYFUNCTION("""COMPUTED_VALUE"""),94.36) -> 94.36 | AW6: =IFERROR(__xludf.DUMMYFUNCTION("""COMPUTED_VALUE"""),96.56) -> 96.56 | AX6: =IFERROR(__xludf.DUMMYFUNCTION("""COMPUTED_VALUE"""),36.64) -> 36.64 | AY6: =IFERROR(__xludf.DUMMYFUNCTION("""COMPUTED_VALUE"""),21.65) -> 21.65 | AZ6: =IFERROR(__xludf.DUMMYFUNCTION("""COMPUTED_VALUE"""),64.1) -> 64.1 | BA6: =IFERROR(__xludf.DUMMYFUNCTION("""COMPUTED_VALUE"""),28.92) -> 28.92 | BB6: =IFERROR(__xludf.DUMMYFUNCTION("""COMPUTED_VALUE"""),104.24) -> 104.24 | BC6: =IFERROR(__xludf.DUMMYFUNCTION("""COMPUTED_VALUE"""),163.58) -> 163.58 | BD6: =IFERROR(__xludf.DUMMYFUNCTION("""COMPUTED_VALUE"""),597.15) -> 597.15 | BE6: =IFERROR(__xludf.DUMMYFUNCTION("""COMPUTED_VALUE"""),215.63) -> 215.63 | BF6: =IFERROR(__xludf.DUMMYFUNCTION("""COMPUTED_VALUE"""),134.93) -> 134.93 | BG6: =IFERROR(__xludf.DUMMYFUNCTION("""COMPUTED_VALUE"""),6.71) -> 6.71 | BH6: =IFERROR(__xludf.DUMMYFUNCTION("""COMPUTED_VALUE"""),245.9) -> 245.9 | BI6: =IFERROR(__xludf.DUMMYFUNCTION("""COMPUTED_VALUE"""),521.27) -> 521.27 | BJ6: =IFERROR(__xludf.DUMMYFUNCTION("""COMPUTED_VALUE"""),48.16) -> 48.16 | BK6: =IFERROR(__xludf.DUMMYFUNCTION("""COMPUTED_VALUE"""),11.02) -> 11.02 | BL6: =IFERROR(__xludf.DUMMYFUNCTION("""COMPUTED_VALUE"""),212.2) -> 212.2 | BM6: =IFERROR(__xludf.DUMMYFUNCTION("""COMPUTED_VALUE"""),103.37) -> 103.37
A7: 45429.667 | B7: =IFERROR(__xludf.DUMMYFUNCTION("""COMPUTED_VALUE"""),5303.27) -> 5303.27 | C7: =IFERROR(__xludf.DUMMYFUNCTION("""COMPUTED_VALUE"""),16685.97) -> 16685.97 | D7: =IFERROR(__xludf.DUMMYFUNCTION("""COMPUTED_VALUE"""),40003.59) -> 40003.59 | E7: =IFERROR(__xludf.DUMMYFUNCTION("""COMPUTED_VALUE"""),2095.72) -> 2095.72 | F7: =IFERROR(__xludf.DUMMYFUNCTION("""COMPUTED_VALUE"""),483.43) -> 483.43 | G7: =IFERROR(__xludf.DUMMYFUNCTION("""COMPUTED_VALUE"""),184.7) -> 184.7 | H7: =IFERROR(__xludf.DUMMYFUNCTION("""COMPUTED_VALUE"""),133.76) -> 133.76 | I7: =IFERROR(__xludf.DUMMYFUNCTION("""COMPUTED_VALUE"""),189.87) -> 189.87 | J7: =IFERROR(__xludf.DUMMYFUNCTION("""COMPUTED_VALUE"""),212.08) -> 212.08 | K7: =IFERROR(__xludf.DUMMYFUNCTION("""COMPUTED_VALUE"""),59.5) -> 59.5 | L7: =IFERROR(__xludf.DUMMYFUNCTION("""COMPUTED_VALUE"""),11.12) -> 11.12 | M7: =IFERROR(__xludf.DUMMYFUNCTION("""COMPUTED_VALUE"""),416.94) -> 416.94 | N7: =IFERROR(__xludf.DUMMYFUNCTION("""COMPUTED_VALUE"""),61.47) -> 61.47 | O7: =IFERROR(__xludf.DUMMYFUNCTION("""COMPUTED_VALUE"""),230.57) -> 230.57 | P7: =IFERROR(__xludf.DUMMYFUNCTION("""COMPUTED_VALUE"""),65.23) -> 65.23 | Q7: =IFERROR(__xludf.DUMMYFUNCTION("""COMPUTED_VALUE"""),356.27) -> 356.27 | R7: =IFERROR(__xludf.DUMMYFUNCTION("""COMPUTED_VALUE"""),53.05) -> 53.05 | S7: =IFERROR(__xludf.DUMMYFUNCTION("""COMPUTED_VALUE"""),151.13) -> 151.13 | T7: =IFERROR(__xludf.DUMMYFUNCTION("""COMPUTED_VALUE"""),162.67) -> 162.67 | U7: =IFERROR(__xludf.DUMMYFUNCTION("""COMPUTED_VALUE"""),338.71) -> 338.71 | V7: =IFERROR(__xludf.DUMMYFUNCTION("""COMPUTED_VALUE"""),37.16) -> 37.16 | W7: =IFERROR(__xludf.DUMMYFUNCTION("""COMPUTED_VALUE"""),63.03) -> 63.03 | X7: =IFERROR(__xludf.DUMMYFUNCTION("""COMPUTED_VALUE"""),97.1) -> 97.1 | Y7: =IFERROR(__xludf.DUMMYFUNCTION("""COMPUTED_VALUE"""),143.83) -> 143.83 | Z7: =IFERROR(__xludf.DUMMYFUNCTION("""COMPUTED_VALUE"""),117.31) -> 117.31 | AA7: =IFERROR(__xludf.DUMMYFUNCTION("""COMPUTED_VALUE"""),513.03) -> 513.03 | AB7: =IFERROR(__xludf.DUMMYFUNCTION("""COMPUTED_VALUE"""),51.48) -> 51.48 | AC7: =IFERROR(__xludf.DUMMYFUNCTION("""COMPUTED_VALUE"""),119.64) -> 119.64 | AD7: =IFERROR(__xludf.DUMMYFUNCTION("""COMPUTED_VALUE"""),257.25) -> 257.25 | AE7: =IFERROR(__xludf.DUMMYFUNCTION("""COMPUTED_VALUE"""),422.3) -> 422.3 | AF7: =IFERROR(__xludf.DUMMYFUNCTION("""COMPUTED_VALUE"""),299.02) -> 299.02 | AG7: =IFERROR(__xludf.DUMMYFUNCTION("""COMPUTED_VALUE"""),45.76) -> 45.76 | AH7: =IFERROR(__xludf.DUMMYFUNCTION("""COMPUTED_VALUE"""),67.72) -> 67.72 | AI7: =IFERROR(__xludf.DUMMYFUNCTION("""COMPUTED_VALUE"""),467.72) -> 467.72 | AJ7: =IFERROR(__xludf.DUMMYFUNCTION("""COMPUTED_VALUE"""),344.21) -> 344.21 | AK7: =IFERROR(__xludf.DUMMYFUNCTION("""COMPUTED_VALUE"""),87.66) -> 87.66 | AL7: =IFERROR(__xludf.DUMMYFUNCTION("""COMPUTED_VALUE"""),138.4) -> 138.4 | AM7: =IFERROR(__xludf.DUMMYFUNCTION("""COMPUTED_VALUE"""),398.82) -> 398.82 | AN7: =IFERROR(__xludf.DUMMYFUNCTION("""COMPUTED_VALUE"""),204.79) -> 204.79 | AO7: =IFERROR(__xludf.DUMMYFUNCTION("""COMPUTED_VALUE"""),466.2) -> 466.2 | AP7: =IFERROR(__xludf.DUMMYFUNCTION("""COMPUTED_VALUE"""),334.95) -> 334.95 | AQ7: =IFERROR(__xludf.DUMMYFUNCTION("""COMPUTED_VALUE"""),26.69) -> 26.69 | AR7: =IFERROR(__xludf.DUMMYFUNCTION("""COMPUTED_VALUE"""),85.92) -> 85.92 | AS7: =IFERROR(__xludf.DUMMYFUNCTION("""COMPUTED_VALUE"""),74.22) -> 74.22 | AT7: =IFERROR(__xludf.DUMMYFUNCTION("""COMPUTED_VALUE"""),420.21) -> 420.21 | AU7: =IFERROR(__xludf.DUMMYFUNCTION("""COMPUTED_VALUE"""),76.09) -> 76.09 | AV7: =IFERROR(__xludf.DUMMYFUNCTION("""COMPUTED_VALUE"""),92.48) -> 92.48 | AW7: =IFERROR(__xludf.DUMMYFUNCTION("""COMPUTED_VALUE"""),96.79) -> 96.79 | AX7: =IFERROR(__xludf.DUMMYFUNCTION("""COMPUTED_VALUE"""),38.12) -> 38.12 | AY7: =IFERROR(__xludf.DUMMYFUNCTION("""COMPUTED_VALUE"""),21.76) -> 21.76 | AZ7: =IFERROR(__xludf.DUMMYFUNCTION("""COMPUTED_VALUE"""),64.48) -> 64.48 | BA7: =IFERROR(__xludf.DUMMYFUNCTION("""COMPUTED_VALUE"""),28.64) -> 28.64 | BB7: =IFERROR(__xludf.DUMMYFUNCTION("""COMPUTED_VALUE"""),104.18) -> 104.18 | BC7: =IFERROR(__xludf.DUMMYFUNCTION("""COMPUTED_VALUE"""),164.0) -> 164 | BD7: =IFERROR(__xludf.DUMMYFUNCTION("""COMPUTED_VALUE"""),595.3) -> 595.3 | BE7: =IFERROR(__xludf.DUMMYFUNCTION("""COMPUTED_VALUE"""),219.76) -> 219.76 | BF7: =IFERROR(__xludf.DUMMYFUNCTION("""COMPUTED_VALUE"""),137.98) -> 137.98 | BG7: =IFERROR(__xludf.DUMMYFUNCTION("""COMPUTED_VALUE"""),6.78) -> 6.78 | BH7: =IFERROR(__xludf.DUMMYFUNCTION("""COMPUTED_VALUE"""),244.97) -> 244.97 | BI7: =IFERROR(__xludf.DUMMYFUNCTION("""COMPUTED_VALUE"""),524.63) -> 524.63 | BJ7: =IFERROR(__xludf.DUMMYFUNCTION("""COMPUTED_VALUE"""),48.16) -> 48.16 | BK7: =IFERROR(__xludf.DUMMYFUNCTION("""COMPUTED_VALUE"""),10.98) -> 10.98 | BL7: =IFERROR(__xludf.DUMMYFUNCTION("""COMPUTED_VALUE"""),210.44) -> 210.44 | BM7: =IFERROR(__xludf.DUMMYFUNCTION("""COMPUTED_VALUE"""),103.25) -> 103.25
A8: 45432.667 | B8: =IFERROR(__xludf.DUMMYFUNCTION("""COMPUTED_VALUE"""),5308.13) -> 5308.13 | C8: =IFERROR(__xludf.DUMMYFUNCTION("""COMPUTED_VALUE"""),16794.87) -> 16794.87 | D8: =IFERROR(__xludf.DUMMYFUNCTION("""COMPUTED_VALUE"""),39806.77) -> 39806.77 | E8: =IFERROR(__xludf.DUMMYFUNCTION("""COMPUTED_VALUE"""),2102.5) -> 2102.5 | F8: =IFERROR(__xludf.DUMMYFUNCTION("""COMPUTED_VALUE"""),484.69) -> 484.69 | G8: =IFERROR(__xludf.DUMMYFUNCTION("""COMPUTED_VALUE"""),183.54) -> 183.54 | H8: =IFERROR(__xludf.DUMMYFUNCTION("""COMPUTED_VALUE"""),133.57) -> 133.57 | I8: =IFERROR(__xludf.DUMMYFUNCTION("""COMPUTED_VALUE"""),191.04) -> 191.04 | J8: =IFERROR(__xludf.DUMMYFUNCTION("""COMPUTED_VALUE"""),219.95) -> 219.95 | K8: =IFERROR(__xludf.DUMMYFUNCTION("""COMPUTED_VALUE"""),58.95) -> 58.95 | L8: =IFERROR(__xludf.DUMMYFUNCTION("""COMPUTED_VALUE"""),11.02) -> 11.02 | M8: =IFERROR(__xludf.DUMMYFUNCTION("""COMPUTED_VALUE"""),413.0) -> 413 | N8: =IFERROR(__xludf.DUMMYFUNCTION("""COMPUTED_VALUE"""),61.58) -> 61.58 | O8: =IFERROR(__xludf.DUMMYFUNCTION("""COMPUTED_VALUE"""),231.58) -> 231.58 | P8: =IFERROR(__xludf.DUMMYFUNCTION("""COMPUTED_VALUE"""),65.98) -> 65.98 | Q8: =IFERROR(__xludf.DUMMYFUNCTION("""COMPUTED_VALUE"""),362.75) -> 362.75 | R8: =IFERROR(__xludf.DUMMYFUNCTION("""COMPUTED_VALUE"""),54.0) -> 54 | S8: =IFERROR(__xludf.DUMMYFUNCTION("""COMPUTED_VALUE"""),151.86) -> 151.86 | T8: =IFERROR(__xludf.DUMMYFUNCTION("""COMPUTED_VALUE"""),161.14) -> 161.14 | U8: =IFERROR(__xludf.DUMMYFUNCTION("""COMPUTED_VALUE"""),333.37) -> 333.37 | V8: =IFERROR(__xludf.DUMMYFUNCTION("""COMPUTED_VALUE"""),36.49) -> 36.49 | W8: =IFERROR(__xludf.DUMMYFUNCTION("""COMPUTED_VALUE"""),62.57) -> 62.57 | X8: =IFERROR(__xludf.DUMMYFUNCTION("""COMPUTED_VALUE"""),96.51) -> 96.51 | Y8: =IFERROR(__xludf.DUMMYFUNCTION("""COMPUTED_VALUE"""),143.35) -> 143.35 | Z8: =IFERROR(__xludf.DUMMYFUNCTION("""COMPUTED_VALUE"""),113.48) -> 113.48 | AA8: =IFERROR(__xludf.DUMMYFUNCTION("""COMPUTED_VALUE"""),516.08) -> 516.08 | AB8: =IFERROR(__xludf.DUMMYFUNCTION("""COMPUTED_VALUE"""),51.24) -> 51.24 | AC8: =IFERROR(__xludf.DUMMYFUNCTION("""COMPUTED_VALUE"""),118.67) -> 118.67 | AD8: =IFERROR(__xludf.DUMMYFUNCTION("""COMPUTED_VALUE"""),254.71) -> 254.71 | AE8: =IFERROR(__xludf.DUMMYFUNCTION("""COMPUTED_VALUE"""),416.65) -> 416.65 | AF8: =IFERROR(__xludf.DUMMYFUNCTION("""COMPUTED_VALUE"""),300.23) -> 300.23 | AG8: =IFERROR(__xludf.DUMMYFUNCTION("""COMPUTED_VALUE"""),45.11) -> 45.11 | AH8: =IFERROR(__xludf.DUMMYFUNCTION("""COMPUTED_VALUE"""),67.9) -> 67.9 | AI8: =IFERROR(__xludf.DUMMYFUNCTION("""COMPUTED_VALUE"""),462.94) -> 462.94 | AJ8: =IFERROR(__xludf.DUMMYFUNCTION("""COMPUTED_VALUE"""),337.82) -> 337.82 | AK8: =IFERROR(__xludf.DUMMYFUNCTION("""COMPUTED_VALUE"""),86.71) -> 86.71 | AL8: =IFERROR(__xludf.DUMMYFUNCTION("""COMPUTED_VALUE"""),136.95) -> 136.95 | AM8: =IFERROR(__xludf.DUMMYFUNCTION("""COMPUTED_VALUE"""),400.03) -> 400.03 | AN8: =IFERROR(__xludf.DUMMYFUNCTION("""COMPUTED_VALUE"""),195.58) -> 195.58 | AO8: =IFERROR(__xludf.DUMMYFUNCTION("""COMPUTED_VALUE"""),467.08) -> 467.08 | AP8: =IFERROR(__xludf.DUMMYFUNCTION("""COMPUTED_VALUE"""),327.07) -> 327.07 | AQ8: =IFERROR(__xludf.DUMMYFUNCTION("""COMPUTED_VALUE"""),26.45) -> 26.45 | AR8: =IFERROR(__xludf.DUMMYFUNCTION("""COMPUTED_VALUE"""),84.51) -> 84.51 | AS8: =IFERROR(__xludf.DUMMYFUNCTION("""COMPUTED_VALUE"""),72.89) -> 72.89 | AT8: =IFERROR(__xludf.DUMMYFUNCTION("""COMPUTED_VALUE"""),425.34) -> 425.34 | AU8: =IFERROR(__xludf.DUMMYFUNCTION("""COMPUTED_VALUE"""),75.87) -> 75.87 | AV8: =IFERROR(__xludf.DUMMYFUNCTION("""COMPUTED_VALUE"""),94.78) -> 94.78 | AW8: =IFERROR(__xludf.DUMMYFUNCTION("""COMPUTED_VALUE"""),97.08) -> 97.08 | AX8: =IFERROR(__xludf.DUMMYFUNCTION("""COMPUTED_VALUE"""),38.36) -> 38.36 | AY8: =IFERROR(__xludf.DUMMYFUNCTION("""COMPUTED_VALUE"""),21.62) -> 21.62 | AZ8: =IFERROR(__xludf.DUMMYFUNCTION("""COMPUTED_VALUE"""),64.77) -> 64.77 | BA8: =IFERROR(__xludf.DUMMYFUNCTION("""COMPUTED_VALUE"""),28.53) -> 28.53 | BB8: =IFERROR(__xludf.DUMMYFUNCTION("""COMPUTED_VALUE"""),105.02) -> 105.02 | BC8: =IFERROR(__xludf.DUMMYFUNCTION("""COMPUTED_VALUE"""),163.9) -> 163.9 | BD8: =IFERROR(__xludf.DUMMYFUNCTION("""COMPUTED_VALUE"""),594.01) -> 594.01 | BE8: =IFERROR(__xludf.DUMMYFUNCTION("""COMPUTED_VALUE"""),220.5) -> 220.5 | BF8: =IFERROR(__xludf.DUMMYFUNCTION("""COMPUTED_VALUE"""),138.62) -> 138.62 | BG8: =IFERROR(__xludf.DUMMYFUNCTION("""COMPUTED_VALUE"""),6.7) -> 6.7 | BH8: =IFERROR(__xludf.DUMMYFUNCTION("""COMPUTED_VALUE"""),243.63) -> 243.63 | BI8: =IFERROR(__xludf.DUMMYFUNCTION("""COMPUTED_VALUE"""),517.23) -> 517.23 | BJ8: =IFERROR(__xludf.DUMMYFUNCTION("""COMPUTED_VALUE"""),48.15) -> 48.15 | BK8: =IFERROR(__xludf.DUMMYFUNCTION("""COMPUTED_VALUE"""),11.07) -> 11.07 | BL8: =IFERROR(__xludf.DUMMYFUNCTION("""COMPUTED_VALUE"""),208.47) -> 208.47 | BM8: =IFERROR(__xludf.DUMMYFUNCTION("""COMPUTED_VALUE"""),102.9) -> 102.9
A9: 45433.667 | B9: =IFERROR(__xludf.DUMMYFUNCTION("""COMPUTED_VALUE"""),5321.41) -> 5321.41 | C9: =IFERROR(__xludf.DUMMYFUNCTION("""COMPUTED_VALUE"""),16832.62) -> 16832.62 | D9: =IFERROR(__xludf.DUMMYFUNCTION("""COMPUTED_VALUE"""),39872.99) -> 39872.99 | E9: =IFERROR(__xludf.DUMMYFUNCTION("""COMPUTED_VALUE"""),2098.36) -> 2098.36 | F9: =IFERROR(__xludf.DUMMYFUNCTION("""COMPUTED_VALUE"""),481.85) -> 481.85 | G9: =IFERROR(__xludf.DUMMYFUNCTION("""COMPUTED_VALUE"""),183.15) -> 183.15 | H9: =IFERROR(__xludf.DUMMYFUNCTION("""COMPUTED_VALUE"""),134.36) -> 134.36 | I9: =IFERROR(__xludf.DUMMYFUNCTION("""COMPUTED_VALUE"""),192.35) -> 192.35 | J9: =IFERROR(__xludf.DUMMYFUNCTION("""COMPUTED_VALUE"""),219.8) -> 219.8 | K9: =IFERROR(__xludf.DUMMYFUNCTION("""COMPUTED_VALUE"""),59.08) -> 59.08 | L9: =IFERROR(__xludf.DUMMYFUNCTION("""COMPUTED_VALUE"""),11.17) -> 11.17 | M9: =IFERROR(__xludf.DUMMYFUNCTION("""COMPUTED_VALUE"""),414.37) -> 414.37 | N9: =IFERROR(__xludf.DUMMYFUNCTION("""COMPUTED_VALUE"""),61.63) -> 61.63 | O9: =IFERROR(__xludf.DUMMYFUNCTION("""COMPUTED_VALUE"""),227.69) -> 227.69 | P9: =IFERROR(__xludf.DUMMYFUNCTION("""COMPUTED_VALUE"""),66.22) -> 66.22 | Q9: =IFERROR(__xludf.DUMMYFUNCTION("""COMPUTED_VALUE"""),359.07) -> 359.07 | R9: =IFERROR(__xludf.DUMMYFUNCTION("""COMPUTED_VALUE"""),53.73) -> 53.73 | S9: =IFERROR(__xludf.DUMMYFUNCTION("""COMPUTED_VALUE"""),151.58) -> 151.58 | T9: =IFERROR(__xludf.DUMMYFUNCTION("""COMPUTED_VALUE"""),159.97) -> 159.97 | U9: =IFERROR(__xludf.DUMMYFUNCTION("""COMPUTED_VALUE"""),336.38) -> 336.38 | V9: =IFERROR(__xludf.DUMMYFUNCTION("""COMPUTED_VALUE"""),36.57) -> 36.57 | W9: =IFERROR(__xludf.DUMMYFUNCTION("""COMPUTED_VALUE"""),62.91) -> 62.91 | X9: =IFERROR(__xludf.DUMMYFUNCTION("""COMPUTED_VALUE"""),96.34) -> 96.34 | Y9: =IFERROR(__xludf.DUMMYFUNCTION("""COMPUTED_VALUE"""),144.26) -> 144.26 | Z9: =IFERROR(__xludf.DUMMYFUNCTION("""COMPUTED_VALUE"""),114.7) -> 114.7 | AA9: =IFERROR(__xludf.DUMMYFUNCTION("""COMPUTED_VALUE"""),513.72) -> 513.72 | AB9: =IFERROR(__xludf.DUMMYFUNCTION("""COMPUTED_VALUE"""),52.17) -> 52.17 | AC9: =IFERROR(__xludf.DUMMYFUNCTION("""COMPUTED_VALUE"""),117.85) -> 117.85 | AD9: =IFERROR(__xludf.DUMMYFUNCTION("""COMPUTED_VALUE"""),252.33) -> 252.33 | AE9: =IFERROR(__xludf.DUMMYFUNCTION("""COMPUTED_VALUE"""),418.37) -> 418.37 | AF9: =IFERROR(__xludf.DUMMYFUNCTION("""COMPUTED_VALUE"""),297.06) -> 297.06 | AG9: =IFERROR(__xludf.DUMMYFUNCTION("""COMPUTED_VALUE"""),44.92) -> 44.92 | AH9: =IFERROR(__xludf.DUMMYFUNCTION("""COMPUTED_VALUE"""),67.29) -> 67.29 | AI9: =IFERROR(__xludf.DUMMYFUNCTION("""COMPUTED_VALUE"""),470.41) -> 470.41 | AJ9: =IFERROR(__xludf.DUMMYFUNCTION("""COMPUTED_VALUE"""),336.15) -> 336.15 | AK9: =IFERROR(__xludf.DUMMYFUNCTION("""COMPUTED_VALUE"""),85.42) -> 85.42 | AL9: =IFERROR(__xludf.DUMMYFUNCTION("""COMPUTED_VALUE"""),137.27) -> 137.27 | AM9: =IFERROR(__xludf.DUMMYFUNCTION("""COMPUTED_VALUE"""),402.11) -> 402.11 | AN9: =IFERROR(__xludf.DUMMYFUNCTION("""COMPUTED_VALUE"""),199.52) -> 199.52 | AO9: =IFERROR(__xludf.DUMMYFUNCTION("""COMPUTED_VALUE"""),468.31) -> 468.31 | AP9: =IFERROR(__xludf.DUMMYFUNCTION("""COMPUTED_VALUE"""),322.98) -> 322.98 | AQ9: =IFERROR(__xludf.DUMMYFUNCTION("""COMPUTED_VALUE"""),26.37) -> 26.37 | AR9: =IFERROR(__xludf.DUMMYFUNCTION("""COMPUTED_VALUE"""),85.17) -> 85.17 | AS9: =IFERROR(__xludf.DUMMYFUNCTION("""COMPUTED_VALUE"""),72.59) -> 72.59 | AT9: =IFERROR(__xludf.DUMMYFUNCTION("""COMPUTED_VALUE"""),429.04) -> 429.04 | AU9: =IFERROR(__xludf.DUMMYFUNCTION("""COMPUTED_VALUE"""),76.95) -> 76.95 | AV9: =IFERROR(__xludf.DUMMYFUNCTION("""COMPUTED_VALUE"""),95.39) -> 95.39 | AW9: =IFERROR(__xludf.DUMMYFUNCTION("""COMPUTED_VALUE"""),98.15) -> 98.15 | AX9: =IFERROR(__xludf.DUMMYFUNCTION("""COMPUTED_VALUE"""),37.31) -> 37.31 | AY9: =IFERROR(__xludf.DUMMYFUNCTION("""COMPUTED_VALUE"""),21.24) -> 21.24 | AZ9: =IFERROR(__xludf.DUMMYFUNCTION("""COMPUTED_VALUE"""),64.1) -> 64.1 | BA9: =IFERROR(__xludf.DUMMYFUNCTION("""COMPUTED_VALUE"""),28.56) -> 28.56 | BB9: =IFERROR(__xludf.DUMMYFUNCTION("""COMPUTED_VALUE"""),105.43) -> 105.43 | BC9: =IFERROR(__xludf.DUMMYFUNCTION("""COMPUTED_VALUE"""),164.36) -> 164.36 | BD9: =IFERROR(__xludf.DUMMYFUNCTION("""COMPUTED_VALUE"""),590.12) -> 590.12 | BE9: =IFERROR(__xludf.DUMMYFUNCTION("""COMPUTED_VALUE"""),219.36) -> 219.36 | BF9: =IFERROR(__xludf.DUMMYFUNCTION("""COMPUTED_VALUE"""),138.42) -> 138.42 | BG9: =IFERROR(__xludf.DUMMYFUNCTION("""COMPUTED_VALUE"""),6.85) -> 6.85 | BH9: =IFERROR(__xludf.DUMMYFUNCTION("""COMPUTED_VALUE"""),234.96) -> 234.96 | BI9: =IFERROR(__xludf.DUMMYFUNCTION("""COMPUTED_VALUE"""),523.55) -> 523.55 | BJ9: =IFERROR(__xludf.DUMMYFUNCTION("""COMPUTED_VALUE"""),48.2) -> 48.2 | BK9: =IFERROR(__xludf.DUMMYFUNCTION("""COMPUTED_VALUE"""),10.96) -> 10.96 | BL9: =IFERROR(__xludf.DUMMYFUNCTION("""COMPUTED_VALUE"""),208.33) -> 208.33 | BM9: =IFERROR(__xludf.DUMMYFUNCTION("""COMPUTED_VALUE"""),103.01) -> 103.01
A10: 45434.667 | B10: =IFERROR(__xludf.DUMMYFUNCTION("""COMPUTED_VALUE"""),5307.01) -> 5307.01 | C10: =IFERROR(__xludf.DUMMYFUNCTION("""COMPUTED_VALUE"""),16801.54) -> 16801.54 | D10: =IFERROR(__xludf.DUMMYFUNCTION("""COMPUTED_VALUE"""),39671.04) -> 39671.04 | E10: =IFERROR(__xludf.DUMMYFUNCTION("""COMPUTED_VALUE"""),2081.71) -> 2081.71 | F10: =IFERROR(__xludf.DUMMYFUNCTION("""COMPUTED_VALUE"""),483.93) -> 483.93 | G10: =IFERROR(__xludf.DUMMYFUNCTION("""COMPUTED_VALUE"""),183.13) -> 183.13 | H10: =IFERROR(__xludf.DUMMYFUNCTION("""COMPUTED_VALUE"""),133.75) -> 133.75 | I10: =IFERROR(__xludf.DUMMYFUNCTION("""COMPUTED_VALUE"""),190.9) -> 190.9 | J10: =IFERROR(__xludf.DUMMYFUNCTION("""COMPUTED_VALUE"""),218.15) -> 218.15 | K10: =IFERROR(__xludf.DUMMYFUNCTION("""COMPUTED_VALUE"""),58.97) -> 58.97 | L10: =IFERROR(__xludf.DUMMYFUNCTION("""COMPUTED_VALUE"""),10.84) -> 10.84 | M10: =IFERROR(__xludf.DUMMYFUNCTION("""COMPUTED_VALUE"""),413.99) -> 413.99 | N10: =IFERROR(__xludf.DUMMYFUNCTION("""COMPUTED_VALUE"""),58.73) -> 58.73 | O10: =IFERROR(__xludf.DUMMYFUNCTION("""COMPUTED_VALUE"""),225.21) -> 225.21 | P10: =IFERROR(__xludf.DUMMYFUNCTION("""COMPUTED_VALUE"""),65.35) -> 65.35 | Q10: =IFERROR(__xludf.DUMMYFUNCTION("""COMPUTED_VALUE"""),355.94) -> 355.94 | R10: =IFERROR(__xludf.DUMMYFUNCTION("""COMPUTED_VALUE"""),52.14) -> 52.14 | S10: =IFERROR(__xludf.DUMMYFUNCTION("""COMPUTED_VALUE"""),153.52) -> 153.52 | T10: =IFERROR(__xludf.DUMMYFUNCTION("""COMPUTED_VALUE"""),157.57) -> 157.57 | U10: =IFERROR(__xludf.DUMMYFUNCTION("""COMPUTED_VALUE"""),336.47) -> 336.47 | V10: =IFERROR(__xludf.DUMMYFUNCTION("""COMPUTED_VALUE"""),35.91) -> 35.91 | W10: =IFERROR(__xludf.DUMMYFUNCTION("""COMPUTED_VALUE"""),63.0) -> 63 | X10: =IFERROR(__xludf.DUMMYFUNCTION("""COMPUTED_VALUE"""),96.13) -> 96.13 | Y10: =IFERROR(__xludf.DUMMYFUNCTION("""COMPUTED_VALUE"""),143.15) -> 143.15 | Z10: =IFERROR(__xludf.DUMMYFUNCTION("""COMPUTED_VALUE"""),113.77) -> 113.77 | AA10: =IFERROR(__xludf.DUMMYFUNCTION("""COMPUTED_VALUE"""),511.92) -> 511.92 | AB10: =IFERROR(__xludf.DUMMYFUNCTION("""COMPUTED_VALUE"""),52.8) -> 52.8 | AC10: =IFERROR(__xludf.DUMMYFUNCTION("""COMPUTED_VALUE"""),115.48) -> 115.48 | AD10: =IFERROR(__xludf.DUMMYFUNCTION("""COMPUTED_VALUE"""),252.07) -> 252.07 | AE10: =IFERROR(__xludf.DUMMYFUNCTION("""COMPUTED_VALUE"""),415.05) -> 415.05 | AF10: =IFERROR(__xludf.DUMMYFUNCTION("""COMPUTED_VALUE"""),298.01) -> 298.01 | AG10: =IFERROR(__xludf.DUMMYFUNCTION("""COMPUTED_VALUE"""),43.97) -> 43.97 | AH10: =IFERROR(__xludf.DUMMYFUNCTION("""COMPUTED_VALUE"""),67.8) -> 67.8 | AI10: =IFERROR(__xludf.DUMMYFUNCTION("""COMPUTED_VALUE"""),462.38) -> 462.38 | AJ10: =IFERROR(__xludf.DUMMYFUNCTION("""COMPUTED_VALUE"""),330.59) -> 330.59 | AK10: =IFERROR(__xludf.DUMMYFUNCTION("""COMPUTED_VALUE"""),85.22) -> 85.22 | AL10: =IFERROR(__xludf.DUMMYFUNCTION("""COMPUTED_VALUE"""),136.89) -> 136.89 | AM10: =IFERROR(__xludf.DUMMYFUNCTION("""COMPUTED_VALUE"""),400.9) -> 400.9 | AN10: =IFERROR(__xludf.DUMMYFUNCTION("""COMPUTED_VALUE"""),198.31) -> 198.31 | AO10: =IFERROR(__xludf.DUMMYFUNCTION("""COMPUTED_VALUE"""),469.71) -> 469.71 | AP10: =IFERROR(__xludf.DUMMYFUNCTION("""COMPUTED_VALUE"""),299.63) -> 299.63 | AQ10: =IFERROR(__xludf.DUMMYFUNCTION("""COMPUTED_VALUE"""),26.27) -> 26.27 | AR10: =IFERROR(__xludf.DUMMYFUNCTION("""COMPUTED_VALUE"""),85.76) -> 85.76 | AS10: =IFERROR(__xludf.DUMMYFUNCTION("""COMPUTED_VALUE"""),72.87) -> 72.87 | AT10: =IFERROR(__xludf.DUMMYFUNCTION("""COMPUTED_VALUE"""),430.52) -> 430.52 | AU10: =IFERROR(__xludf.DUMMYFUNCTION("""COMPUTED_VALUE"""),76.32) -> 76.32 | AV10: =IFERROR(__xludf.DUMMYFUNCTION("""COMPUTED_VALUE"""),94.95) -> 94.95 | AW10: =IFERROR(__xludf.DUMMYFUNCTION("""COMPUTED_VALUE"""),98.7) -> 98.7 | AX10: =IFERROR(__xludf.DUMMYFUNCTION("""COMPUTED_VALUE"""),37.59) -> 37.59 | AY10: =IFERROR(__xludf.DUMMYFUNCTION("""COMPUTED_VALUE"""),21.17) -> 21.17 | AZ10: =IFERROR(__xludf.DUMMYFUNCTION("""COMPUTED_VALUE"""),62.19) -> 62.19 | BA10: =IFERROR(__xludf.DUMMYFUNCTION("""COMPUTED_VALUE"""),29.6) -> 29.6 | BB10: =IFERROR(__xludf.DUMMYFUNCTION("""COMPUTED_VALUE"""),106.31) -> 106.31 | BC10: =IFERROR(__xludf.DUMMYFUNCTION("""COMPUTED_VALUE"""),165.5) -> 165.5 | BD10: =IFERROR(__xludf.DUMMYFUNCTION("""COMPUTED_VALUE"""),590.8) -> 590.8 | BE10: =IFERROR(__xludf.DUMMYFUNCTION("""COMPUTED_VALUE"""),216.63) -> 216.63 | BF10: =IFERROR(__xludf.DUMMYFUNCTION("""COMPUTED_VALUE"""),136.97) -> 136.97 | BG10: =IFERROR(__xludf.DUMMYFUNCTION("""COMPUTED_VALUE"""),6.95) -> 6.95 | BH10: =IFERROR(__xludf.DUMMYFUNCTION("""COMPUTED_VALUE"""),234.71) -> 234.71 | BI10: =IFERROR(__xludf.DUMMYFUNCTION("""COMPUTED_VALUE"""),521.35) -> 521.35 | BJ10: =IFERROR(__xludf.DUMMYFUNCTION("""COMPUTED_VALUE"""),48.17) -> 48.17 | BK10: =IFERROR(__xludf.DUMMYFUNCTION("""COMPUTED_VALUE"""),10.88) -> 10.88 | BL10: =IFERROR(__xludf.DUMMYFUNCTION("""COMPUTED_VALUE"""),209.92) -> 209.92 | BM10: =IFERROR(__xludf.DUMMYFUNCTION("""COMPUTED_VALUE"""),103.02) -> 103.02
A11: 45435.667 | B11: =IFERROR(__xludf.DUMMYFUNCTION("""COMPUTED_VALUE"""),5267.84) -> 5267.84 | C11: =IFERROR(__xludf.DUMMYFUNCTION("""COMPUTED_VALUE"""),16736.03) -> 16736.03 | D11: =IFERROR(__xludf.DUMMYFUNCTION("""COMPUTED_VALUE"""),39065.26) -> 39065.26 | E11: =IFERROR(__xludf.DUMMYFUNCTION("""COMPUTED_VALUE"""),2048.41) -> 2048.41 | F11: =IFERROR(__xludf.DUMMYFUNCTION("""COMPUTED_VALUE"""),483.31) -> 483.31 | G11: =IFERROR(__xludf.DUMMYFUNCTION("""COMPUTED_VALUE"""),181.05) -> 181.05 | H11: =IFERROR(__xludf.DUMMYFUNCTION("""COMPUTED_VALUE"""),128.6) -> 128.6 | I11: =IFERROR(__xludf.DUMMYFUNCTION("""COMPUTED_VALUE"""),186.88) -> 186.88 | J11: =IFERROR(__xludf.DUMMYFUNCTION("""COMPUTED_VALUE"""),217.95) -> 217.95 | K11: =IFERROR(__xludf.DUMMYFUNCTION("""COMPUTED_VALUE"""),58.33) -> 58.33 | L11: =IFERROR(__xludf.DUMMYFUNCTION("""COMPUTED_VALUE"""),10.91) -> 10.91 | M11: =IFERROR(__xludf.DUMMYFUNCTION("""COMPUTED_VALUE"""),405.88) -> 405.88 | N11: =IFERROR(__xludf.DUMMYFUNCTION("""COMPUTED_VALUE"""),58.75) -> 58.75 | O11: =IFERROR(__xludf.DUMMYFUNCTION("""COMPUTED_VALUE"""),218.06) -> 218.06 | P11: =IFERROR(__xludf.DUMMYFUNCTION("""COMPUTED_VALUE"""),64.35) -> 64.35 | Q11: =IFERROR(__xludf.DUMMYFUNCTION("""COMPUTED_VALUE"""),350.7) -> 350.7 | R11: =IFERROR(__xludf.DUMMYFUNCTION("""COMPUTED_VALUE"""),51.69) -> 51.69 | S11: =IFERROR(__xludf.DUMMYFUNCTION("""COMPUTED_VALUE"""),153.5) -> 153.5 | T11: =IFERROR(__xludf.DUMMYFUNCTION("""COMPUTED_VALUE"""),156.94) -> 156.94 | U11: =IFERROR(__xludf.DUMMYFUNCTION("""COMPUTED_VALUE"""),337.83) -> 337.83 | V11: =IFERROR(__xludf.DUMMYFUNCTION("""COMPUTED_VALUE"""),35.12) -> 35.12 | W11: =IFERROR(__xludf.DUMMYFUNCTION("""COMPUTED_VALUE"""),62.09) -> 62.09 | X11: =IFERROR(__xludf.DUMMYFUNCTION("""COMPUTED_VALUE"""),93.87) -> 93.87 | Y11: =IFERROR(__xludf.DUMMYFUNCTION("""COMPUTED_VALUE"""),142.25) -> 142.25 | Z11: =IFERROR(__xludf.DUMMYFUNCTION("""COMPUTED_VALUE"""),114.6) -> 114.6 | AA11: =IFERROR(__xludf.DUMMYFUNCTION("""COMPUTED_VALUE"""),502.13) -> 502.13 | AB11: =IFERROR(__xludf.DUMMYFUNCTION("""COMPUTED_VALUE"""),52.81) -> 52.81 | AC11: =IFERROR(__xludf.DUMMYFUNCTION("""COMPUTED_VALUE"""),113.51) -> 113.51 | AD11: =IFERROR(__xludf.DUMMYFUNCTION("""COMPUTED_VALUE"""),249.29) -> 249.29 | AE11: =IFERROR(__xludf.DUMMYFUNCTION("""COMPUTED_VALUE"""),413.53) -> 413.53 | AF11: =IFERROR(__xludf.DUMMYFUNCTION("""COMPUTED_VALUE"""),296.52) -> 296.52 | AG11: =IFERROR(__xludf.DUMMYFUNCTION("""COMPUTED_VALUE"""),43.73) -> 43.73 | AH11: =IFERROR(__xludf.DUMMYFUNCTION("""COMPUTED_VALUE"""),66.17) -> 66.17 | AI11: =IFERROR(__xludf.DUMMYFUNCTION("""COMPUTED_VALUE"""),458.15) -> 458.15 | AJ11: =IFERROR(__xludf.DUMMYFUNCTION("""COMPUTED_VALUE"""),326.89) -> 326.89 | AK11: =IFERROR(__xludf.DUMMYFUNCTION("""COMPUTED_VALUE"""),85.58) -> 85.58 | AL11: =IFERROR(__xludf.DUMMYFUNCTION("""COMPUTED_VALUE"""),135.4) -> 135.4 | AM11: =IFERROR(__xludf.DUMMYFUNCTION("""COMPUTED_VALUE"""),398.39) -> 398.39 | AN11: =IFERROR(__xludf.DUMMYFUNCTION("""COMPUTED_VALUE"""),196.92) -> 196.92 | AO11: =IFERROR(__xludf.DUMMYFUNCTION("""COMPUTED_VALUE"""),467.08) -> 467.08 | AP11: =IFERROR(__xludf.DUMMYFUNCTION("""COMPUTED_VALUE"""),299.74) -> 299.74 | AQ11: =IFERROR(__xludf.DUMMYFUNCTION("""COMPUTED_VALUE"""),26.14) -> 26.14 | AR11: =IFERROR(__xludf.DUMMYFUNCTION("""COMPUTED_VALUE"""),81.38) -> 81.38 | AS11: =IFERROR(__xludf.DUMMYFUNCTION("""COMPUTED_VALUE"""),71.65) -> 71.65 | AT11: =IFERROR(__xludf.DUMMYFUNCTION("""COMPUTED_VALUE"""),427.0) -> 427 | AU11: =IFERROR(__xludf.DUMMYFUNCTION("""COMPUTED_VALUE"""),75.32) -> 75.32 | AV11: =IFERROR(__xludf.DUMMYFUNCTION("""COMPUTED_VALUE"""),103.8) -> 103.8 | AW11: =IFERROR(__xludf.DUMMYFUNCTION("""COMPUTED_VALUE"""),97.13) -> 97.13 | AX11: =IFERROR(__xludf.DUMMYFUNCTION("""COMPUTED_VALUE"""),38.41) -> 38.41 | AY11: =IFERROR(__xludf.DUMMYFUNCTION("""COMPUTED_VALUE"""),20.72) -> 20.72 | AZ11: =IFERROR(__xludf.DUMMYFUNCTION("""COMPUTED_VALUE"""),61.58) -> 61.58 | BA11: =IFERROR(__xludf.DUMMYFUNCTION("""COMPUTED_VALUE"""),28.69) -> 28.69 | BB11: =IFERROR(__xludf.DUMMYFUNCTION("""COMPUTED_VALUE"""),105.41) -> 105.41 | BC11: =IFERROR(__xludf.DUMMYFUNCTION("""COMPUTED_VALUE"""),164.97) -> 164.97 | BD11: =IFERROR(__xludf.DUMMYFUNCTION("""COMPUTED_VALUE"""),585.03) -> 585.03 | BE11: =IFERROR(__xludf.DUMMYFUNCTION("""COMPUTED_VALUE"""),214.72) -> 214.72 | BF11: =IFERROR(__xludf.DUMMYFUNCTION("""COMPUTED_VALUE"""),137.53) -> 137.53 | BG11: =IFERROR(__xludf.DUMMYFUNCTION("""COMPUTED_VALUE"""),6.72) -> 6.72 | BH11: =IFERROR(__xludf.DUMMYFUNCTION("""COMPUTED_VALUE"""),232.71) -> 232.71 | BI11: =IFERROR(__xludf.DUMMYFUNCTION("""COMPUTED_VALUE"""),516.83) -> 516.83 | BJ11: =IFERROR(__xludf.DUMMYFUNCTION("""COMPUTED_VALUE"""),48.12) -> 48.12 | BK11: =IFERROR(__xludf.DUMMYFUNCTION("""COMPUTED_VALUE"""),10.53) -> 10.53 | BL11: =IFERROR(__xludf.DUMMYFUNCTION("""COMPUTED_VALUE"""),209.49) -> 209.49 | BM11: =IFERROR(__xludf.DUMMYFUNCTION("""COMPUTED_VALUE"""),100.66) -> 100.66
A12: 45436.667 | B12: =IFERROR(__xludf.DUMMYFUNCTION("""COMPUTED_VALUE"""),5304.72) -> 5304.72 | C12: =IFERROR(__xludf.DUMMYFUNCTION("""COMPUTED_VALUE"""),16920.79) -> 16920.79 | D12: =IFERROR(__xludf.DUMMYFUNCTION("""COMPUTED_VALUE"""),39069.59) -> 39069.59 | E12: =IFERROR(__xludf.DUMMYFUNCTION("""COMPUTED_VALUE"""),2069.67) -> 2069.67 | F12: =IFERROR(__xludf.DUMMYFUNCTION("""COMPUTED_VALUE"""),475.43) -> 475.43 | G12: =IFERROR(__xludf.DUMMYFUNCTION("""COMPUTED_VALUE"""),180.75) -> 180.75 | H12: =IFERROR(__xludf.DUMMYFUNCTION("""COMPUTED_VALUE"""),128.23) -> 128.23 | I12: =IFERROR(__xludf.DUMMYFUNCTION("""COMPUTED_VALUE"""),189.98) -> 189.98 | J12: =IFERROR(__xludf.DUMMYFUNCTION("""COMPUTED_VALUE"""),220.89) -> 220.89 | K12: =IFERROR(__xludf.DUMMYFUNCTION("""COMPUTED_VALUE"""),59.09) -> 59.09 | L12: =IFERROR(__xludf.DUMMYFUNCTION("""COMPUTED_VALUE"""),11.08) -> 11.08 | M12: =IFERROR(__xludf.DUMMYFUNCTION("""COMPUTED_VALUE"""),407.41) -> 407.41 | N12: =IFERROR(__xludf.DUMMYFUNCTION("""COMPUTED_VALUE"""),59.63) -> 59.63 | O12: =IFERROR(__xludf.DUMMYFUNCTION("""COMPUTED_VALUE"""),217.81) -> 217.81 | P12: =IFERROR(__xludf.DUMMYFUNCTION("""COMPUTED_VALUE"""),65.65) -> 65.65 | Q12: =IFERROR(__xludf.DUMMYFUNCTION("""COMPUTED_VALUE"""),348.9) -> 348.9 | R12: =IFERROR(__xludf.DUMMYFUNCTION("""COMPUTED_VALUE"""),52.99) -> 52.99 | S12: =IFERROR(__xludf.DUMMYFUNCTION("""COMPUTED_VALUE"""),154.42) -> 154.42 | T12: =IFERROR(__xludf.DUMMYFUNCTION("""COMPUTED_VALUE"""),157.75) -> 157.75 | U12: =IFERROR(__xludf.DUMMYFUNCTION("""COMPUTED_VALUE"""),332.61) -> 332.61 | V12: =IFERROR(__xludf.DUMMYFUNCTION("""COMPUTED_VALUE"""),35.35) -> 35.35 | W12: =IFERROR(__xludf.DUMMYFUNCTION("""COMPUTED_VALUE"""),62.0) -> 62 | X12: =IFERROR(__xludf.DUMMYFUNCTION("""COMPUTED_VALUE"""),94.43) -> 94.43 | Y12: =IFERROR(__xludf.DUMMYFUNCTION("""COMPUTED_VALUE"""),142.77) -> 142.77 | Z12: =IFERROR(__xludf.DUMMYFUNCTION("""COMPUTED_VALUE"""),115.37) -> 115.37 | AA12: =IFERROR(__xludf.DUMMYFUNCTION("""COMPUTED_VALUE"""),502.16) -> 502.16 | AB12: =IFERROR(__xludf.DUMMYFUNCTION("""COMPUTED_VALUE"""),54.41) -> 54.41 | AC12: =IFERROR(__xludf.DUMMYFUNCTION("""COMPUTED_VALUE"""),113.42) -> 113.42 | AD12: =IFERROR(__xludf.DUMMYFUNCTION("""COMPUTED_VALUE"""),247.59) -> 247.59 | AE12: =IFERROR(__xludf.DUMMYFUNCTION("""COMPUTED_VALUE"""),416.16) -> 416.16 | AF12: =IFERROR(__xludf.DUMMYFUNCTION("""COMPUTED_VALUE"""),299.62) -> 299.62 | AG12: =IFERROR(__xludf.DUMMYFUNCTION("""COMPUTED_VALUE"""),44.11) -> 44.11 | AH12: =IFERROR(__xludf.DUMMYFUNCTION("""COMPUTED_VALUE"""),65.68) -> 65.68 | AI12: =IFERROR(__xludf.DUMMYFUNCTION("""COMPUTED_VALUE"""),461.18) -> 461.18 | AJ12: =IFERROR(__xludf.DUMMYFUNCTION("""COMPUTED_VALUE"""),325.1) -> 325.1 | AK12: =IFERROR(__xludf.DUMMYFUNCTION("""COMPUTED_VALUE"""),87.17) -> 87.17 | AL12: =IFERROR(__xludf.DUMMYFUNCTION("""COMPUTED_VALUE"""),136.34) -> 136.34 | AM12: =IFERROR(__xludf.DUMMYFUNCTION("""COMPUTED_VALUE"""),404.85) -> 404.85 | AN12: =IFERROR(__xludf.DUMMYFUNCTION("""COMPUTED_VALUE"""),200.71) -> 200.71 | AO12: =IFERROR(__xludf.DUMMYFUNCTION("""COMPUTED_VALUE"""),467.35) -> 467.35 | AP12: =IFERROR(__xludf.DUMMYFUNCTION("""COMPUTED_VALUE"""),303.01) -> 303.01 | AQ12: =IFERROR(__xludf.DUMMYFUNCTION("""COMPUTED_VALUE"""),26.54) -> 26.54 | AR12: =IFERROR(__xludf.DUMMYFUNCTION("""COMPUTED_VALUE"""),82.29) -> 82.29 | AS12: =IFERROR(__xludf.DUMMYFUNCTION("""COMPUTED_VALUE"""),72.54) -> 72.54 | AT12: =IFERROR(__xludf.DUMMYFUNCTION("""COMPUTED_VALUE"""),430.16) -> 430.16 | AU12: =IFERROR(__xludf.DUMMYFUNCTION("""COMPUTED_VALUE"""),76.61) -> 76.61 | AV12: =IFERROR(__xludf.DUMMYFUNCTION("""COMPUTED_VALUE"""),106.47) -> 106.47 | AW12: =IFERROR(__xludf.DUMMYFUNCTION("""COMPUTED_VALUE"""),97.57) -> 97.57 | AX12: =IFERROR(__xludf.DUMMYFUNCTION("""COMPUTED_VALUE"""),40.23) -> 40.23 | AY12: =IFERROR(__xludf.DUMMYFUNCTION("""COMPUTED_VALUE"""),21.01) -> 21.01 | AZ12: =IFERROR(__xludf.DUMMYFUNCTION("""COMPUTED_VALUE"""),61.64) -> 61.64 | BA12: =IFERROR(__xludf.DUMMYFUNCTION("""COMPUTED_VALUE"""),28.88) -> 28.88 | BB12: =IFERROR(__xludf.DUMMYFUNCTION("""COMPUTED_VALUE"""),106.27) -> 106.27 | BC12: =IFERROR(__xludf.DUMMYFUNCTION("""COMPUTED_VALUE"""),166.0) -> 166 | BD12: =IFERROR(__xludf.DUMMYFUNCTION("""COMPUTED_VALUE"""),584.05) -> 584.05 | BE12: =IFERROR(__xludf.DUMMYFUNCTION("""COMPUTED_VALUE"""),216.84) -> 216.84 | BF12: =IFERROR(__xludf.DUMMYFUNCTION("""COMPUTED_VALUE"""),140.29) -> 140.29 | BG12: =IFERROR(__xludf.DUMMYFUNCTION("""COMPUTED_VALUE"""),6.65) -> 6.65 | BH12: =IFERROR(__xludf.DUMMYFUNCTION("""COMPUTED_VALUE"""),232.05) -> 232.05 | BI12: =IFERROR(__xludf.DUMMYFUNCTION("""COMPUTED_VALUE"""),508.17) -> 508.17 | BJ12: =IFERROR(__xludf.DUMMYFUNCTION("""COMPUTED_VALUE"""),48.15) -> 48.15 | BK12: =IFERROR(__xludf.DUMMYFUNCTION("""COMPUTED_VALUE"""),10.41) -> 10.41 | BL12: =IFERROR(__xludf.DUMMYFUNCTION("""COMPUTED_VALUE"""),208.81) -> 208.81 | BM12: =IFERROR(__xludf.DUMMYFUNCTION("""COMPUTED_VALUE"""),101.76) -> 101.76
A13: 45440.667 | B13: =IFERROR(__xludf.DUMMYFUNCTION("""COMPUTED_VALUE"""),5306.04) -> 5306.04 | C13: =IFERROR(__xludf.DUMMYFUNCTION("""COMPUTED_VALUE"""),17019.88) -> 17019.88 | D13: =IFERROR(__xludf.DUMMYFUNCTION("""COMPUTED_VALUE"""),38852.86) -> 38852.86 | E13: =IFERROR(__xludf.DUMMYFUNCTION("""COMPUTED_VALUE"""),2066.85) -> 2066.85 | F13: =IFERROR(__xludf.DUMMYFUNCTION("""COMPUTED_VALUE"""),478.43) -> 478.43 | G13: =IFERROR(__xludf.DUMMYFUNCTION("""COMPUTED_VALUE"""),182.15) -> 182.15 | H13: =IFERROR(__xludf.DUMMYFUNCTION("""COMPUTED_VALUE"""),126.24) -> 126.24 | I13: =IFERROR(__xludf.DUMMYFUNCTION("""COMPUTED_VALUE"""),189.99) -> 189.99 | J13: =IFERROR(__xludf.DUMMYFUNCTION("""COMPUTED_VALUE"""),221.32) -> 221.32 | K13: =IFERROR(__xludf.DUMMYFUNCTION("""COMPUTED_VALUE"""),58.24) -> 58.24 | L13: =IFERROR(__xludf.DUMMYFUNCTION("""COMPUTED_VALUE"""),11.25) -> 11.25 | M13: =IFERROR(__xludf.DUMMYFUNCTION("""COMPUTED_VALUE"""),403.9) -> 403.9 | N13: =IFERROR(__xludf.DUMMYFUNCTION("""COMPUTED_VALUE"""),59.6) -> 59.6 | O13: =IFERROR(__xludf.DUMMYFUNCTION("""COMPUTED_VALUE"""),218.73) -> 218.73 | P13: =IFERROR(__xludf.DUMMYFUNCTION("""COMPUTED_VALUE"""),64.67) -> 64.67 | Q13: =IFERROR(__xludf.DUMMYFUNCTION("""COMPUTED_VALUE"""),346.47) -> 346.47 | R13: =IFERROR(__xludf.DUMMYFUNCTION("""COMPUTED_VALUE"""),54.13) -> 54.13 | S13: =IFERROR(__xludf.DUMMYFUNCTION("""COMPUTED_VALUE"""),149.71) -> 149.71 | T13: =IFERROR(__xludf.DUMMYFUNCTION("""COMPUTED_VALUE"""),159.04) -> 159.04 | U13: =IFERROR(__xludf.DUMMYFUNCTION("""COMPUTED_VALUE"""),333.21) -> 333.21 | V13: =IFERROR(__xludf.DUMMYFUNCTION("""COMPUTED_VALUE"""),34.66) -> 34.66 | W13: =IFERROR(__xludf.DUMMYFUNCTION("""COMPUTED_VALUE"""),61.82) -> 61.82 | X13: =IFERROR(__xludf.DUMMYFUNCTION("""COMPUTED_VALUE"""),93.21) -> 93.21 | Y13: =IFERROR(__xludf.DUMMYFUNCTION("""COMPUTED_VALUE"""),143.77) -> 143.77 | Z13: =IFERROR(__xludf.DUMMYFUNCTION("""COMPUTED_VALUE"""),113.02) -> 113.02 | AA13: =IFERROR(__xludf.DUMMYFUNCTION("""COMPUTED_VALUE"""),509.08) -> 509.08 | AB13: =IFERROR(__xludf.DUMMYFUNCTION("""COMPUTED_VALUE"""),52.9) -> 52.9 | AC13: =IFERROR(__xludf.DUMMYFUNCTION("""COMPUTED_VALUE"""),114.86) -> 114.86 | AD13: =IFERROR(__xludf.DUMMYFUNCTION("""COMPUTED_VALUE"""),248.04) -> 248.04 | AE13: =IFERROR(__xludf.DUMMYFUNCTION("""COMPUTED_VALUE"""),412.14) -> 412.14 | AF13: =IFERROR(__xludf.DUMMYFUNCTION("""COMPUTED_VALUE"""),297.34) -> 297.34 | AG13: =IFERROR(__xludf.DUMMYFUNCTION("""COMPUTED_VALUE"""),43.09) -> 43.09 | AH13: =IFERROR(__xludf.DUMMYFUNCTION("""COMPUTED_VALUE"""),63.94) -> 63.94 | AI13: =IFERROR(__xludf.DUMMYFUNCTION("""COMPUTED_VALUE"""),459.81) -> 459.81 | AJ13: =IFERROR(__xludf.DUMMYFUNCTION("""COMPUTED_VALUE"""),328.7) -> 328.7 | AK13: =IFERROR(__xludf.DUMMYFUNCTION("""COMPUTED_VALUE"""),88.06) -> 88.06 | AL13: =IFERROR(__xludf.DUMMYFUNCTION("""COMPUTED_VALUE"""),133.68) -> 133.68 | AM13: =IFERROR(__xludf.DUMMYFUNCTION("""COMPUTED_VALUE"""),401.03) -> 401.03 | AN13: =IFERROR(__xludf.DUMMYFUNCTION("""COMPUTED_VALUE"""),199.5) -> 199.5 | AO13: =IFERROR(__xludf.DUMMYFUNCTION("""COMPUTED_VALUE"""),458.48) -> 458.48 | AP13: =IFERROR(__xludf.DUMMYFUNCTION("""COMPUTED_VALUE"""),295.25) -> 295.25 | AQ13: =IFERROR(__xludf.DUMMYFUNCTION("""COMPUTED_VALUE"""),26.2) -> 26.2 | AR13: =IFERROR(__xludf.DUMMYFUNCTION("""COMPUTED_VALUE"""),82.0) -> 82 | AS13: =IFERROR(__xludf.DUMMYFUNCTION("""COMPUTED_VALUE"""),70.98) -> 70.98 | AT13: =IFERROR(__xludf.DUMMYFUNCTION("""COMPUTED_VALUE"""),430.32) -> 430.32 | AU13: =IFERROR(__xludf.DUMMYFUNCTION("""COMPUTED_VALUE"""),77.53) -> 77.53 | AV13: =IFERROR(__xludf.DUMMYFUNCTION("""COMPUTED_VALUE"""),113.9) -> 113.9 | AW13: =IFERROR(__xludf.DUMMYFUNCTION("""COMPUTED_VALUE"""),95.25) -> 95.25 | AX13: =IFERROR(__xludf.DUMMYFUNCTION("""COMPUTED_VALUE"""),41.82) -> 41.82 | AY13: =IFERROR(__xludf.DUMMYFUNCTION("""COMPUTED_VALUE"""),21.05) -> 21.05 | AZ13: =IFERROR(__xludf.DUMMYFUNCTION("""COMPUTED_VALUE"""),62.17) -> 62.17 | BA13: =IFERROR(__xludf.DUMMYFUNCTION("""COMPUTED_VALUE"""),28.3) -> 28.3 | BB13: =IFERROR(__xludf.DUMMYFUNCTION("""COMPUTED_VALUE"""),105.52) -> 105.52 | BC13: =IFERROR(__xludf.DUMMYFUNCTION("""COMPUTED_VALUE"""),167.31) -> 167.31 | BD13: =IFERROR(__xludf.DUMMYFUNCTION("""COMPUTED_VALUE"""),572.57) -> 572.57 | BE13: =IFERROR(__xludf.DUMMYFUNCTION("""COMPUTED_VALUE"""),218.72) -> 218.72 | BF13: =IFERROR(__xludf.DUMMYFUNCTION("""COMPUTED_VALUE"""),142.86) -> 142.86 | BG13: =IFERROR(__xludf.DUMMYFUNCTION("""COMPUTED_VALUE"""),6.84) -> 6.84 | BH13: =IFERROR(__xludf.DUMMYFUNCTION("""COMPUTED_VALUE"""),229.01) -> 229.01 | BI13: =IFERROR(__xludf.DUMMYFUNCTION("""COMPUTED_VALUE"""),503.68) -> 503.68 | BJ13: =IFERROR(__xludf.DUMMYFUNCTION("""COMPUTED_VALUE"""),48.16) -> 48.16 | BK13: =IFERROR(__xludf.DUMMYFUNCTION("""COMPUTED_VALUE"""),10.39) -> 10.39 | BL13: =IFERROR(__xludf.DUMMYFUNCTION("""COMPUTED_VALUE"""),206.46) -> 206.46 | BM13: =IFERROR(__xludf.DUMMYFUNCTION("""COMPUTED_VALUE"""),102.44) -> 102.44
A14: 45441.667 | B14: =IFERROR(__xludf.DUMMYFUNCTION("""COMPUTED_VALUE"""),5266.95) -> 5266.95 | C14: =IFERROR(__xludf.DUMMYFUNCTION("""COMPUTED_VALUE"""),16920.58) -> 16920.58 | D14: =IFERROR(__xludf.DUMMYFUNCTION("""COMPUTED_VALUE"""),38441.54) -> 38441.54 | E14: =IFERROR(__xludf.DUMMYFUNCTION("""COMPUTED_VALUE"""),2036.19) -> 2036.19 | F14: =IFERROR(__xludf.DUMMYFUNCTION("""COMPUTED_VALUE"""),477.6) -> 477.6 | G14: =IFERROR(__xludf.DUMMYFUNCTION("""COMPUTED_VALUE"""),182.02) -> 182.02 | H14: =IFERROR(__xludf.DUMMYFUNCTION("""COMPUTED_VALUE"""),124.11) -> 124.11 | I14: =IFERROR(__xludf.DUMMYFUNCTION("""COMPUTED_VALUE"""),190.29) -> 190.29 | J14: =IFERROR(__xludf.DUMMYFUNCTION("""COMPUTED_VALUE"""),219.05) -> 219.05 | K14: =IFERROR(__xludf.DUMMYFUNCTION("""COMPUTED_VALUE"""),57.76) -> 57.76 | L14: =IFERROR(__xludf.DUMMYFUNCTION("""COMPUTED_VALUE"""),10.98) -> 10.98 | M14: =IFERROR(__xludf.DUMMYFUNCTION("""COMPUTED_VALUE"""),404.09) -> 404.09 | N14: =IFERROR(__xludf.DUMMYFUNCTION("""COMPUTED_VALUE"""),59.45) -> 59.45 | O14: =IFERROR(__xludf.DUMMYFUNCTION("""COMPUTED_VALUE"""),214.41) -> 214.41 | P14: =IFERROR(__xludf.DUMMYFUNCTION("""COMPUTED_VALUE"""),63.07) -> 63.07 | Q14: =IFERROR(__xludf.DUMMYFUNCTION("""COMPUTED_VALUE"""),338.11) -> 338.11 | R14: =IFERROR(__xludf.DUMMYFUNCTION("""COMPUTED_VALUE"""),54.34) -> 54.34 | S14: =IFERROR(__xludf.DUMMYFUNCTION("""COMPUTED_VALUE"""),149.05) -> 149.05 | T14: =IFERROR(__xludf.DUMMYFUNCTION("""COMPUTED_VALUE"""),156.9) -> 156.9 | U14: =IFERROR(__xludf.DUMMYFUNCTION("""COMPUTED_VALUE"""),332.92) -> 332.92 | V14: =IFERROR(__xludf.DUMMYFUNCTION("""COMPUTED_VALUE"""),34.2) -> 34.2 | W14: =IFERROR(__xludf.DUMMYFUNCTION("""COMPUTED_VALUE"""),61.7) -> 61.7 | X14: =IFERROR(__xludf.DUMMYFUNCTION("""COMPUTED_VALUE"""),91.91) -> 91.91 | Y14: =IFERROR(__xludf.DUMMYFUNCTION("""COMPUTED_VALUE"""),141.43) -> 141.43 | Z14: =IFERROR(__xludf.DUMMYFUNCTION("""COMPUTED_VALUE"""),113.83) -> 113.83 | AA14: =IFERROR(__xludf.DUMMYFUNCTION("""COMPUTED_VALUE"""),510.01) -> 510.01 | AB14: =IFERROR(__xludf.DUMMYFUNCTION("""COMPUTED_VALUE"""),52.09) -> 52.09 | AC14: =IFERROR(__xludf.DUMMYFUNCTION("""COMPUTED_VALUE"""),113.63) -> 113.63 | AD14: =IFERROR(__xludf.DUMMYFUNCTION("""COMPUTED_VALUE"""),245.11) -> 245.11 | AE14: =IFERROR(__xludf.DUMMYFUNCTION("""COMPUTED_VALUE"""),406.19) -> 406.19 | AF14: =IFERROR(__xludf.DUMMYFUNCTION("""COMPUTED_VALUE"""),293.48) -> 293.48 | AG14: =IFERROR(__xludf.DUMMYFUNCTION("""COMPUTED_VALUE"""),42.64) -> 42.64 | AH14: =IFERROR(__xludf.DUMMYFUNCTION("""COMPUTED_VALUE"""),63.5) -> 63.5 | AI14: =IFERROR(__xludf.DUMMYFUNCTION("""COMPUTED_VALUE"""),457.17) -> 457.17 | AJ14: =IFERROR(__xludf.DUMMYFUNCTION("""COMPUTED_VALUE"""),325.91) -> 325.91 | AK14: =IFERROR(__xludf.DUMMYFUNCTION("""COMPUTED_VALUE"""),86.1) -> 86.1 | AL14: =IFERROR(__xludf.DUMMYFUNCTION("""COMPUTED_VALUE"""),131.95) -> 131.95 | AM14: =IFERROR(__xludf.DUMMYFUNCTION("""COMPUTED_VALUE"""),398.4) -> 398.4 | AN14: =IFERROR(__xludf.DUMMYFUNCTION("""COMPUTED_VALUE"""),198.11) -> 198.11 | AO14: =IFERROR(__xludf.DUMMYFUNCTION("""COMPUTED_VALUE"""),452.72) -> 452.72 | AP14: =IFERROR(__xludf.DUMMYFUNCTION("""COMPUTED_VALUE"""),298.54) -> 298.54 | AQ14: =IFERROR(__xludf.DUMMYFUNCTION("""COMPUTED_VALUE"""),25.63) -> 25.63 | AR14: =IFERROR(__xludf.DUMMYFUNCTION("""COMPUTED_VALUE"""),81.49) -> 81.49 | AS14: =IFERROR(__xludf.DUMMYFUNCTION("""COMPUTED_VALUE"""),70.44) -> 70.44 | AT14: =IFERROR(__xludf.DUMMYFUNCTION("""COMPUTED_VALUE"""),429.17) -> 429.17 | AU14: =IFERROR(__xludf.DUMMYFUNCTION("""COMPUTED_VALUE"""),76.68) -> 76.68 | AV14: =IFERROR(__xludf.DUMMYFUNCTION("""COMPUTED_VALUE"""),114.83) -> 114.83 | AW14: =IFERROR(__xludf.DUMMYFUNCTION("""COMPUTED_VALUE"""),94.79) -> 94.79 | AX14: =IFERROR(__xludf.DUMMYFUNCTION("""COMPUTED_VALUE"""),42.65) -> 42.65 | AY14: =IFERROR(__xludf.DUMMYFUNCTION("""COMPUTED_VALUE"""),20.94) -> 20.94 | AZ14: =IFERROR(__xludf.DUMMYFUNCTION("""COMPUTED_VALUE"""),61.05) -> 61.05 | BA14: =IFERROR(__xludf.DUMMYFUNCTION("""COMPUTED_VALUE"""),27.82) -> 27.82 | BB14: =IFERROR(__xludf.DUMMYFUNCTION("""COMPUTED_VALUE"""),104.57) -> 104.57 | BC14: =IFERROR(__xludf.DUMMYFUNCTION("""COMPUTED_VALUE"""),168.88) -> 168.88 | BD14: =IFERROR(__xludf.DUMMYFUNCTION("""COMPUTED_VALUE"""),567.3) -> 567.3 | BE14: =IFERROR(__xludf.DUMMYFUNCTION("""COMPUTED_VALUE"""),213.95) -> 213.95 | BF14: =IFERROR(__xludf.DUMMYFUNCTION("""COMPUTED_VALUE"""),142.3) -> 142.3 | BG14: =IFERROR(__xludf.DUMMYFUNCTION("""COMPUTED_VALUE"""),6.94) -> 6.94 | BH14: =IFERROR(__xludf.DUMMYFUNCTION("""COMPUTED_VALUE"""),225.88) -> 225.88 | BI14: =IFERROR(__xludf.DUMMYFUNCTION("""COMPUTED_VALUE"""),484.72) -> 484.72 | BJ14: =IFERROR(__xludf.DUMMYFUNCTION("""COMPUTED_VALUE"""),48.11) -> 48.11 | BK14: =IFERROR(__xludf.DUMMYFUNCTION("""COMPUTED_VALUE"""),10.31) -> 10.31 | BL14: =IFERROR(__xludf.DUMMYFUNCTION("""COMPUTED_VALUE"""),204.16) -> 204.16 | BM14: =IFERROR(__xludf.DUMMYFUNCTION("""COMPUTED_VALUE"""),100.88) -> 100.88
A15: 45442.667 | B15: =IFERROR(__xludf.DUMMYFUNCTION("""COMPUTED_VALUE"""),5235.48) -> 5235.48 | C15: =IFERROR(__xludf.DUMMYFUNCTION("""COMPUTED_VALUE"""),16737.08) -> 16737.08 | D15: =IFERROR(__xludf.DUMMYFUNCTION("""COMPUTED_VALUE"""),38111.48) -> 38111.48 | E15: =IFERROR(__xludf.DUMMYFUNCTION("""COMPUTED_VALUE"""),2056.6) -> 2056.6 | F15: =IFERROR(__xludf.DUMMYFUNCTION("""COMPUTED_VALUE"""),445.87) -> 445.87 | G15: =IFERROR(__xludf.DUMMYFUNCTION("""COMPUTED_VALUE"""),179.32) -> 179.32 | H15: =IFERROR(__xludf.DUMMYFUNCTION("""COMPUTED_VALUE"""),126.28) -> 126.28 | I15: =IFERROR(__xludf.DUMMYFUNCTION("""COMPUTED_VALUE"""),191.29) -> 191.29 | J15: =IFERROR(__xludf.DUMMYFUNCTION("""COMPUTED_VALUE"""),216.54) -> 216.54 | K15: =IFERROR(__xludf.DUMMYFUNCTION("""COMPUTED_VALUE"""),58.42) -> 58.42 | L15: =IFERROR(__xludf.DUMMYFUNCTION("""COMPUTED_VALUE"""),11.26) -> 11.26 | M15: =IFERROR(__xludf.DUMMYFUNCTION("""COMPUTED_VALUE"""),408.61) -> 408.61 | N15: =IFERROR(__xludf.DUMMYFUNCTION("""COMPUTED_VALUE"""),58.66) -> 58.66 | O15: =IFERROR(__xludf.DUMMYFUNCTION("""COMPUTED_VALUE"""),220.07) -> 220.07 | P15: =IFERROR(__xludf.DUMMYFUNCTION("""COMPUTED_VALUE"""),63.34) -> 63.34 | Q15: =IFERROR(__xludf.DUMMYFUNCTION("""COMPUTED_VALUE"""),339.25) -> 339.25 | R15: =IFERROR(__xludf.DUMMYFUNCTION("""COMPUTED_VALUE"""),54.77) -> 54.77 | S15: =IFERROR(__xludf.DUMMYFUNCTION("""COMPUTED_VALUE"""),146.79) -> 146.79 | T15: =IFERROR(__xludf.DUMMYFUNCTION("""COMPUTED_VALUE"""),158.26) -> 158.26 | U15: =IFERROR(__xludf.DUMMYFUNCTION("""COMPUTED_VALUE"""),331.0) -> 331 | V15: =IFERROR(__xludf.DUMMYFUNCTION("""COMPUTED_VALUE"""),34.41) -> 34.41 | W15: =IFERROR(__xludf.DUMMYFUNCTION("""COMPUTED_VALUE"""),61.97) -> 61.97 | X15: =IFERROR(__xludf.DUMMYFUNCTION("""COMPUTED_VALUE"""),92.45) -> 92.45 | Y15: =IFERROR(__xludf.DUMMYFUNCTION("""COMPUTED_VALUE"""),144.04) -> 144.04 | Z15: =IFERROR(__xludf.DUMMYFUNCTION("""COMPUTED_VALUE"""),114.79) -> 114.79 | AA15: =IFERROR(__xludf.DUMMYFUNCTION("""COMPUTED_VALUE"""),509.1) -> 509.1 | AB15: =IFERROR(__xludf.DUMMYFUNCTION("""COMPUTED_VALUE"""),53.35) -> 53.35 | AC15: =IFERROR(__xludf.DUMMYFUNCTION("""COMPUTED_VALUE"""),113.99) -> 113.99 | AD15: =IFERROR(__xludf.DUMMYFUNCTION("""COMPUTED_VALUE"""),249.58) -> 249.58 | AE15: =IFERROR(__xludf.DUMMYFUNCTION("""COMPUTED_VALUE"""),408.98) -> 408.98 | AF15: =IFERROR(__xludf.DUMMYFUNCTION("""COMPUTED_VALUE"""),296.08) -> 296.08 | AG15: =IFERROR(__xludf.DUMMYFUNCTION("""COMPUTED_VALUE"""),43.41) -> 43.41 | AH15: =IFERROR(__xludf.DUMMYFUNCTION("""COMPUTED_VALUE"""),64.08) -> 64.08 | AI15: =IFERROR(__xludf.DUMMYFUNCTION("""COMPUTED_VALUE"""),450.23) -> 450.23 | AJ15: =IFERROR(__xludf.DUMMYFUNCTION("""COMPUTED_VALUE"""),329.18) -> 329.18 | AK15: =IFERROR(__xludf.DUMMYFUNCTION("""COMPUTED_VALUE"""),85.92) -> 85.92 | AL15: =IFERROR(__xludf.DUMMYFUNCTION("""COMPUTED_VALUE"""),133.24) -> 133.24 | AM15: =IFERROR(__xludf.DUMMYFUNCTION("""COMPUTED_VALUE"""),403.39) -> 403.39 | AN15: =IFERROR(__xludf.DUMMYFUNCTION("""COMPUTED_VALUE"""),199.33) -> 199.33 | AO15: =IFERROR(__xludf.DUMMYFUNCTION("""COMPUTED_VALUE"""),460.94) -> 460.94 | AP15: =IFERROR(__xludf.DUMMYFUNCTION("""COMPUTED_VALUE"""),302.9) -> 302.9 | AQ15: =IFERROR(__xludf.DUMMYFUNCTION("""COMPUTED_VALUE"""),25.66) -> 25.66 | AR15: =IFERROR(__xludf.DUMMYFUNCTION("""COMPUTED_VALUE"""),80.6) -> 80.6 | AS15: =IFERROR(__xludf.DUMMYFUNCTION("""COMPUTED_VALUE"""),71.11) -> 71.11 | AT15: =IFERROR(__xludf.DUMMYFUNCTION("""COMPUTED_VALUE"""),414.67) -> 414.67 | AU15: =IFERROR(__xludf.DUMMYFUNCTION("""COMPUTED_VALUE"""),78.19) -> 78.19 | AV15: =IFERROR(__xludf.DUMMYFUNCTION("""COMPUTED_VALUE"""),110.5) -> 110.5 | AW15: =IFERROR(__xludf.DUMMYFUNCTION("""COMPUTED_VALUE"""),96.39) -> 96.39 | AX15: =IFERROR(__xludf.DUMMYFUNCTION("""COMPUTED_VALUE"""),42.6) -> 42.6 | AY15: =IFERROR(__xludf.DUMMYFUNCTION("""COMPUTED_VALUE"""),21.73) -> 21.73 | AZ15: =IFERROR(__xludf.DUMMYFUNCTION("""COMPUTED_VALUE"""),62.51) -> 62.51 | BA15: =IFERROR(__xludf.DUMMYFUNCTION("""COMPUTED_VALUE"""),28.2) -> 28.2 | BB15: =IFERROR(__xludf.DUMMYFUNCTION("""COMPUTED_VALUE"""),105.72) -> 105.72 | BC15: =IFERROR(__xludf.DUMMYFUNCTION("""COMPUTED_VALUE"""),170.7) -> 170.7 | BD15: =IFERROR(__xludf.DUMMYFUNCTION("""COMPUTED_VALUE"""),562.76) -> 562.76 | BE15: =IFERROR(__xludf.DUMMYFUNCTION("""COMPUTED_VALUE"""),214.17) -> 214.17 | BF15: =IFERROR(__xludf.DUMMYFUNCTION("""COMPUTED_VALUE"""),136.42) -> 136.42 | BG15: =IFERROR(__xludf.DUMMYFUNCTION("""COMPUTED_VALUE"""),6.95) -> 6.95 | BH15: =IFERROR(__xludf.DUMMYFUNCTION("""COMPUTED_VALUE"""),229.24) -> 229.24 | BI15: =IFERROR(__xludf.DUMMYFUNCTION("""COMPUTED_VALUE"""),481.65) -> 481.65 | BJ15: =IFERROR(__xludf.DUMMYFUNCTION("""COMPUTED_VALUE"""),48.19) -> 48.19 | BK15: =IFERROR(__xludf.DUMMYFUNCTION("""COMPUTED_VALUE"""),10.48) -> 10.48 | BL15: =IFERROR(__xludf.DUMMYFUNCTION("""COMPUTED_VALUE"""),206.25) -> 206.25 | BM15: =IFERROR(__xludf.DUMMYFUNCTION("""COMPUTED_VALUE"""),101.7) -> 101.7
A16: 45443.667 | B16: =IFERROR(__xludf.DUMMYFUNCTION("""COMPUTED_VALUE"""),5277.51) -> 5277.51 | C16: =IFERROR(__xludf.DUMMYFUNCTION("""COMPUTED_VALUE"""),16735.02) -> 16735.02 | D16: =IFERROR(__xludf.DUMMYFUNCTION("""COMPUTED_VALUE"""),38686.32) -> 38686.32 | E16: =IFERROR(__xludf.DUMMYFUNCTION("""COMPUTED_VALUE"""),2070.13) -> 2070.13 | F16: =IFERROR(__xludf.DUMMYFUNCTION("""COMPUTED_VALUE"""),444.76) -> 444.76 | G16: =IFERROR(__xludf.DUMMYFUNCTION("""COMPUTED_VALUE"""),176.44) -> 176.44 | H16: =IFERROR(__xludf.DUMMYFUNCTION("""COMPUTED_VALUE"""),130.77) -> 130.77 | I16: =IFERROR(__xludf.DUMMYFUNCTION("""COMPUTED_VALUE"""),192.25) -> 192.25 | J16: =IFERROR(__xludf.DUMMYFUNCTION("""COMPUTED_VALUE"""),215.08) -> 215.08 | K16: =IFERROR(__xludf.DUMMYFUNCTION("""COMPUTED_VALUE"""),59.61) -> 59.61 | L16: =IFERROR(__xludf.DUMMYFUNCTION("""COMPUTED_VALUE"""),11.35) -> 11.35 | M16: =IFERROR(__xludf.DUMMYFUNCTION("""COMPUTED_VALUE"""),414.4) -> 414.4 | N16: =IFERROR(__xludf.DUMMYFUNCTION("""COMPUTED_VALUE"""),59.53) -> 59.53 | O16: =IFERROR(__xludf.DUMMYFUNCTION("""COMPUTED_VALUE"""),224.94) -> 224.94 | P16: =IFERROR(__xludf.DUMMYFUNCTION("""COMPUTED_VALUE"""),63.19) -> 63.19 | Q16: =IFERROR(__xludf.DUMMYFUNCTION("""COMPUTED_VALUE"""),338.52) -> 338.52 | R16: =IFERROR(__xludf.DUMMYFUNCTION("""COMPUTED_VALUE"""),55.51) -> 55.51 | S16: =IFERROR(__xludf.DUMMYFUNCTION("""COMPUTED_VALUE"""),150.5) -> 150.5 | T16: =IFERROR(__xludf.DUMMYFUNCTION("""COMPUTED_VALUE"""),162.3) -> 162.3 | U16: =IFERROR(__xludf.DUMMYFUNCTION("""COMPUTED_VALUE"""),344.62) -> 344.62 | V16: =IFERROR(__xludf.DUMMYFUNCTION("""COMPUTED_VALUE"""),35.29) -> 35.29 | W16: =IFERROR(__xludf.DUMMYFUNCTION("""COMPUTED_VALUE"""),62.93) -> 62.93 | X16: =IFERROR(__xludf.DUMMYFUNCTION("""COMPUTED_VALUE"""),94.55) -> 94.55 | Y16: =IFERROR(__xludf.DUMMYFUNCTION("""COMPUTED_VALUE"""),145.34) -> 145.34 | Z16: =IFERROR(__xludf.DUMMYFUNCTION("""COMPUTED_VALUE"""),117.95) -> 117.95 | AA16: =IFERROR(__xludf.DUMMYFUNCTION("""COMPUTED_VALUE"""),508.58) -> 508.58 | AB16: =IFERROR(__xludf.DUMMYFUNCTION("""COMPUTED_VALUE"""),54.22) -> 54.22 | AC16: =IFERROR(__xludf.DUMMYFUNCTION("""COMPUTED_VALUE"""),117.26) -> 117.26 | AD16: =IFERROR(__xludf.DUMMYFUNCTION("""COMPUTED_VALUE"""),253.96) -> 253.96 | AE16: =IFERROR(__xludf.DUMMYFUNCTION("""COMPUTED_VALUE"""),411.0) -> 411 | AF16: =IFERROR(__xludf.DUMMYFUNCTION("""COMPUTED_VALUE"""),299.77) -> 299.77 | AG16: =IFERROR(__xludf.DUMMYFUNCTION("""COMPUTED_VALUE"""),44.99) -> 44.99 | AH16: =IFERROR(__xludf.DUMMYFUNCTION("""COMPUTED_VALUE"""),64.27) -> 64.27 | AI16: =IFERROR(__xludf.DUMMYFUNCTION("""COMPUTED_VALUE"""),456.52) -> 456.52 | AJ16: =IFERROR(__xludf.DUMMYFUNCTION("""COMPUTED_VALUE"""),334.87) -> 334.87 | AK16: =IFERROR(__xludf.DUMMYFUNCTION("""COMPUTED_VALUE"""),88.31) -> 88.31 | AL16: =IFERROR(__xludf.DUMMYFUNCTION("""COMPUTED_VALUE"""),133.9) -> 133.9 | AM16: =IFERROR(__xludf.DUMMYFUNCTION("""COMPUTED_VALUE"""),402.12) -> 402.12 | AN16: =IFERROR(__xludf.DUMMYFUNCTION("""COMPUTED_VALUE"""),202.63) -> 202.63 | AO16: =IFERROR(__xludf.DUMMYFUNCTION("""COMPUTED_VALUE"""),470.34) -> 470.34 | AP16: =IFERROR(__xludf.DUMMYFUNCTION("""COMPUTED_VALUE"""),311.99) -> 311.99 | AQ16: =IFERROR(__xludf.DUMMYFUNCTION("""COMPUTED_VALUE"""),25.96) -> 25.96 | AR16: =IFERROR(__xludf.DUMMYFUNCTION("""COMPUTED_VALUE"""),81.37) -> 81.37 | AS16: =IFERROR(__xludf.DUMMYFUNCTION("""COMPUTED_VALUE"""),72.37) -> 72.37 | AT16: =IFERROR(__xludf.DUMMYFUNCTION("""COMPUTED_VALUE"""),415.13) -> 415.13 | AU16: =IFERROR(__xludf.DUMMYFUNCTION("""COMPUTED_VALUE"""),80.02) -> 80.02 | AV16: =IFERROR(__xludf.DUMMYFUNCTION("""COMPUTED_VALUE"""),109.63) -> 109.63 | AW16: =IFERROR(__xludf.DUMMYFUNCTION("""COMPUTED_VALUE"""),99.2) -> 99.2 | AX16: =IFERROR(__xludf.DUMMYFUNCTION("""COMPUTED_VALUE"""),42.54) -> 42.54 | AY16: =IFERROR(__xludf.DUMMYFUNCTION("""COMPUTED_VALUE"""),21.68) -> 21.68 | AZ16: =IFERROR(__xludf.DUMMYFUNCTION("""COMPUTED_VALUE"""),62.99) -> 62.99 | BA16: =IFERROR(__xludf.DUMMYFUNCTION("""COMPUTED_VALUE"""),28.66) -> 28.66 | BB16: =IFERROR(__xludf.DUMMYFUNCTION("""COMPUTED_VALUE"""),107.81) -> 107.81 | BC16: =IFERROR(__xludf.DUMMYFUNCTION("""COMPUTED_VALUE"""),174.96) -> 174.96 | BD16: =IFERROR(__xludf.DUMMYFUNCTION("""COMPUTED_VALUE"""),567.98) -> 567.98 | BE16: =IFERROR(__xludf.DUMMYFUNCTION("""COMPUTED_VALUE"""),217.51) -> 217.51 | BF16: =IFERROR(__xludf.DUMMYFUNCTION("""COMPUTED_VALUE"""),136.4) -> 136.4 | BG16: =IFERROR(__xludf.DUMMYFUNCTION("""COMPUTED_VALUE"""),7.19) -> 7.19 | BH16: =IFERROR(__xludf.DUMMYFUNCTION("""COMPUTED_VALUE"""),232.82) -> 232.82 | BI16: =IFERROR(__xludf.DUMMYFUNCTION("""COMPUTED_VALUE"""),495.37) -> 495.37 | BJ16: =IFERROR(__xludf.DUMMYFUNCTION("""COMPUTED_VALUE"""),48.28) -> 48.28 | BK16: =IFERROR(__xludf.DUMMYFUNCTION("""COMPUTED_VALUE"""),10.6) -> 10.6 | BL16: =IFERROR(__xludf.DUMMYFUNCTION("""COMPUTED_VALUE"""),210.73) -> 210.73 | BM16: =IFERROR(__xludf.DUMMYFUNCTION("""COMPUTED_VALUE"""),103.91) -> 103.91
A17: 45446.667 | B17: =IFERROR(__xludf.DUMMYFUNCTION("""COMPUTED_VALUE"""),5283.4) -> 5283.4 | C17: =IFERROR(__xludf.DUMMYFUNCTION("""COMPUTED_VALUE"""),16828.67) -> 16828.67 | D17: =IFERROR(__xludf.DUMMYFUNCTION("""COMPUTED_VALUE"""),38571.03) -> 38571.03 | E17: =IFERROR(__xludf.DUMMYFUNCTION("""COMPUTED_VALUE"""),2059.68) -> 2059.68 | F17: =IFERROR(__xludf.DUMMYFUNCTION("""COMPUTED_VALUE"""),439.02) -> 439.02 | G17: =IFERROR(__xludf.DUMMYFUNCTION("""COMPUTED_VALUE"""),178.34) -> 178.34 | H17: =IFERROR(__xludf.DUMMYFUNCTION("""COMPUTED_VALUE"""),130.77) -> 130.77 | I17: =IFERROR(__xludf.DUMMYFUNCTION("""COMPUTED_VALUE"""),194.03) -> 194.03 | J17: =IFERROR(__xludf.DUMMYFUNCTION("""COMPUTED_VALUE"""),214.21) -> 214.21 | K17: =IFERROR(__xludf.DUMMYFUNCTION("""COMPUTED_VALUE"""),59.57) -> 59.57 | L17: =IFERROR(__xludf.DUMMYFUNCTION("""COMPUTED_VALUE"""),11.41) -> 11.41 | M17: =IFERROR(__xludf.DUMMYFUNCTION("""COMPUTED_VALUE"""),414.79) -> 414.79 | N17: =IFERROR(__xludf.DUMMYFUNCTION("""COMPUTED_VALUE"""),59.38) -> 59.38 | O17: =IFERROR(__xludf.DUMMYFUNCTION("""COMPUTED_VALUE"""),229.8) -> 229.8 | P17: =IFERROR(__xludf.DUMMYFUNCTION("""COMPUTED_VALUE"""),61.99) -> 61.99 | Q17: =IFERROR(__xludf.DUMMYFUNCTION("""COMPUTED_VALUE"""),331.36) -> 331.36 | R17: =IFERROR(__xludf.DUMMYFUNCTION("""COMPUTED_VALUE"""),54.1) -> 54.1 | S17: =IFERROR(__xludf.DUMMYFUNCTION("""COMPUTED_VALUE"""),151.07) -> 151.07 | T17: =IFERROR(__xludf.DUMMYFUNCTION("""COMPUTED_VALUE"""),157.46) -> 157.46 | U17: =IFERROR(__xludf.DUMMYFUNCTION("""COMPUTED_VALUE"""),341.49) -> 341.49 | V17: =IFERROR(__xludf.DUMMYFUNCTION("""COMPUTED_VALUE"""),34.72) -> 34.72 | W17: =IFERROR(__xludf.DUMMYFUNCTION("""COMPUTED_VALUE"""),62.93) -> 62.93 | X17: =IFERROR(__xludf.DUMMYFUNCTION("""COMPUTED_VALUE"""),93.68) -> 93.68 | Y17: =IFERROR(__xludf.DUMMYFUNCTION("""COMPUTED_VALUE"""),143.04) -> 143.04 | Z17: =IFERROR(__xludf.DUMMYFUNCTION("""COMPUTED_VALUE"""),120.98) -> 120.98 | AA17: =IFERROR(__xludf.DUMMYFUNCTION("""COMPUTED_VALUE"""),522.98) -> 522.98 | AB17: =IFERROR(__xludf.DUMMYFUNCTION("""COMPUTED_VALUE"""),53.61) -> 53.61 | AC17: =IFERROR(__xludf.DUMMYFUNCTION("""COMPUTED_VALUE"""),114.45) -> 114.45 | AD17: =IFERROR(__xludf.DUMMYFUNCTION("""COMPUTED_VALUE"""),248.62) -> 248.62 | AE17: =IFERROR(__xludf.DUMMYFUNCTION("""COMPUTED_VALUE"""),409.05) -> 409.05 | AF17: =IFERROR(__xludf.DUMMYFUNCTION("""COMPUTED_VALUE"""),298.26) -> 298.26 | AG17: =IFERROR(__xludf.DUMMYFUNCTION("""COMPUTED_VALUE"""),45.74) -> 45.74 | AH17: =IFERROR(__xludf.DUMMYFUNCTION("""COMPUTED_VALUE"""),63.43) -> 63.43 | AI17: =IFERROR(__xludf.DUMMYFUNCTION("""COMPUTED_VALUE"""),454.98) -> 454.98 | AJ17: =IFERROR(__xludf.DUMMYFUNCTION("""COMPUTED_VALUE"""),328.01) -> 328.01 | AK17: =IFERROR(__xludf.DUMMYFUNCTION("""COMPUTED_VALUE"""),89.89) -> 89.89 | AL17: =IFERROR(__xludf.DUMMYFUNCTION("""COMPUTED_VALUE"""),133.65) -> 133.65 | AM17: =IFERROR(__xludf.DUMMYFUNCTION("""COMPUTED_VALUE"""),403.86) -> 403.86 | AN17: =IFERROR(__xludf.DUMMYFUNCTION("""COMPUTED_VALUE"""),201.82) -> 201.82 | AO17: =IFERROR(__xludf.DUMMYFUNCTION("""COMPUTED_VALUE"""),467.6) -> 467.6 | AP17: =IFERROR(__xludf.DUMMYFUNCTION("""COMPUTED_VALUE"""),306.62) -> 306.62 | AQ17: =IFERROR(__xludf.DUMMYFUNCTION("""COMPUTED_VALUE"""),25.88) -> 25.88 | AR17: =IFERROR(__xludf.DUMMYFUNCTION("""COMPUTED_VALUE"""),82.12) -> 82.12 | AS17: =IFERROR(__xludf.DUMMYFUNCTION("""COMPUTED_VALUE"""),71.42) -> 71.42 | AT17: =IFERROR(__xludf.DUMMYFUNCTION("""COMPUTED_VALUE"""),413.52) -> 413.52 | AU17: =IFERROR(__xludf.DUMMYFUNCTION("""COMPUTED_VALUE"""),77.71) -> 77.71 | AV17: =IFERROR(__xludf.DUMMYFUNCTION("""COMPUTED_VALUE"""),115.0) -> 115 | AW17: =IFERROR(__xludf.DUMMYFUNCTION("""COMPUTED_VALUE"""),98.83) -> 98.83 | AX17: =IFERROR(__xludf.DUMMYFUNCTION("""COMPUTED_VALUE"""),41.24) -> 41.24 | AY17: =IFERROR(__xludf.DUMMYFUNCTION("""COMPUTED_VALUE"""),21.32) -> 21.32 | AZ17: =IFERROR(__xludf.DUMMYFUNCTION("""COMPUTED_VALUE"""),63.46) -> 63.46 | BA17: =IFERROR(__xludf.DUMMYFUNCTION("""COMPUTED_VALUE"""),29.31) -> 29.31 | BB17: =IFERROR(__xludf.DUMMYFUNCTION("""COMPUTED_VALUE"""),107.37) -> 107.37 | BC17: =IFERROR(__xludf.DUMMYFUNCTION("""COMPUTED_VALUE"""),173.08) -> 173.08 | BD17: =IFERROR(__xludf.DUMMYFUNCTION("""COMPUTED_VALUE"""),569.58) -> 569.58 | BE17: =IFERROR(__xludf.DUMMYFUNCTION("""COMPUTED_VALUE"""),212.17) -> 212.17 | BF17: =IFERROR(__xludf.DUMMYFUNCTION("""COMPUTED_VALUE"""),133.63) -> 133.63 | BG17: =IFERROR(__xludf.DUMMYFUNCTION("""COMPUTED_VALUE"""),6.95) -> 6.95 | BH17: =IFERROR(__xludf.DUMMYFUNCTION("""COMPUTED_VALUE"""),228.32) -> 228.32 | BI17: =IFERROR(__xludf.DUMMYFUNCTION("""COMPUTED_VALUE"""),497.44) -> 497.44 | BJ17: =IFERROR(__xludf.DUMMYFUNCTION("""COMPUTED_VALUE"""),48.3) -> 48.3 | BK17: =IFERROR(__xludf.DUMMYFUNCTION("""COMPUTED_VALUE"""),10.58) -> 10.58 | BL17: =IFERROR(__xludf.DUMMYFUNCTION("""COMPUTED_VALUE"""),201.3) -> 201.3 | BM17: =IFERROR(__xludf.DUMMYFUNCTION("""COMPUTED_VALUE"""),102.77) -> 102.77
A18: 45447.667 | B18: =IFERROR(__xludf.DUMMYFUNCTION("""COMPUTED_VALUE"""),5291.34) -> 5291.34 | C18: =IFERROR(__xludf.DUMMYFUNCTION("""COMPUTED_VALUE"""),16857.05) -> 16857.05 | D18: =IFERROR(__xludf.DUMMYFUNCTION("""COMPUTED_VALUE"""),38711.29) -> 38711.29 | E18: =IFERROR(__xludf.DUMMYFUNCTION("""COMPUTED_VALUE"""),2033.94) -> 2033.94 | F18: =IFERROR(__xludf.DUMMYFUNCTION("""COMPUTED_VALUE"""),448.37) -> 448.37 | G18: =IFERROR(__xludf.DUMMYFUNCTION("""COMPUTED_VALUE"""),179.34) -> 179.34 | H18: =IFERROR(__xludf.DUMMYFUNCTION("""COMPUTED_VALUE"""),132.82) -> 132.82 | I18: =IFERROR(__xludf.DUMMYFUNCTION("""COMPUTED_VALUE"""),194.35) -> 194.35 | J18: =IFERROR(__xludf.DUMMYFUNCTION("""COMPUTED_VALUE"""),212.22) -> 212.22 | K18: =IFERROR(__xludf.DUMMYFUNCTION("""COMPUTED_VALUE"""),58.87) -> 58.87 | L18: =IFERROR(__xludf.DUMMYFUNCTION("""COMPUTED_VALUE"""),11.09) -> 11.09 | M18: =IFERROR(__xludf.DUMMYFUNCTION("""COMPUTED_VALUE"""),409.53) -> 409.53 | N18: =IFERROR(__xludf.DUMMYFUNCTION("""COMPUTED_VALUE"""),58.07) -> 58.07 | O18: =IFERROR(__xludf.DUMMYFUNCTION("""COMPUTED_VALUE"""),234.13) -> 234.13 | P18: =IFERROR(__xludf.DUMMYFUNCTION("""COMPUTED_VALUE"""),61.27) -> 61.27 | Q18: =IFERROR(__xludf.DUMMYFUNCTION("""COMPUTED_VALUE"""),327.57) -> 327.57 | R18: =IFERROR(__xludf.DUMMYFUNCTION("""COMPUTED_VALUE"""),53.62) -> 53.62 | S18: =IFERROR(__xludf.DUMMYFUNCTION("""COMPUTED_VALUE"""),151.03) -> 151.03 | T18: =IFERROR(__xludf.DUMMYFUNCTION("""COMPUTED_VALUE"""),156.13) -> 156.13 | U18: =IFERROR(__xludf.DUMMYFUNCTION("""COMPUTED_VALUE"""),337.06) -> 337.06 | V18: =IFERROR(__xludf.DUMMYFUNCTION("""COMPUTED_VALUE"""),34.17) -> 34.17 | W18: =IFERROR(__xludf.DUMMYFUNCTION("""COMPUTED_VALUE"""),63.94) -> 63.94 | X18: =IFERROR(__xludf.DUMMYFUNCTION("""COMPUTED_VALUE"""),93.72) -> 93.72 | Y18: =IFERROR(__xludf.DUMMYFUNCTION("""COMPUTED_VALUE"""),145.12) -> 145.12 | Z18: =IFERROR(__xludf.DUMMYFUNCTION("""COMPUTED_VALUE"""),120.3) -> 120.3 | AA18: =IFERROR(__xludf.DUMMYFUNCTION("""COMPUTED_VALUE"""),520.98) -> 520.98 | AB18: =IFERROR(__xludf.DUMMYFUNCTION("""COMPUTED_VALUE"""),53.75) -> 53.75 | AC18: =IFERROR(__xludf.DUMMYFUNCTION("""COMPUTED_VALUE"""),112.67) -> 112.67 | AD18: =IFERROR(__xludf.DUMMYFUNCTION("""COMPUTED_VALUE"""),245.95) -> 245.95 | AE18: =IFERROR(__xludf.DUMMYFUNCTION("""COMPUTED_VALUE"""),410.74) -> 410.74 | AF18: =IFERROR(__xludf.DUMMYFUNCTION("""COMPUTED_VALUE"""),297.32) -> 297.32 | AG18: =IFERROR(__xludf.DUMMYFUNCTION("""COMPUTED_VALUE"""),45.26) -> 45.26 | AH18: =IFERROR(__xludf.DUMMYFUNCTION("""COMPUTED_VALUE"""),64.16) -> 64.16 | AI18: =IFERROR(__xludf.DUMMYFUNCTION("""COMPUTED_VALUE"""),455.3) -> 455.3 | AJ18: =IFERROR(__xludf.DUMMYFUNCTION("""COMPUTED_VALUE"""),328.26) -> 328.26 | AK18: =IFERROR(__xludf.DUMMYFUNCTION("""COMPUTED_VALUE"""),91.22) -> 91.22 | AL18: =IFERROR(__xludf.DUMMYFUNCTION("""COMPUTED_VALUE"""),134.76) -> 134.76 | AM18: =IFERROR(__xludf.DUMMYFUNCTION("""COMPUTED_VALUE"""),406.61) -> 406.61 | AN18: =IFERROR(__xludf.DUMMYFUNCTION("""COMPUTED_VALUE"""),199.16) -> 199.16 | AO18: =IFERROR(__xludf.DUMMYFUNCTION("""COMPUTED_VALUE"""),468.89) -> 468.89 | AP18: =IFERROR(__xludf.DUMMYFUNCTION("""COMPUTED_VALUE"""),306.78) -> 306.78 | AQ18: =IFERROR(__xludf.DUMMYFUNCTION("""COMPUTED_VALUE"""),25.81) -> 25.81 | AR18: =IFERROR(__xludf.DUMMYFUNCTION("""COMPUTED_VALUE"""),83.27) -> 83.27 | AS18: =IFERROR(__xludf.DUMMYFUNCTION("""COMPUTED_VALUE"""),70.31) -> 70.31 | AT18: =IFERROR(__xludf.DUMMYFUNCTION("""COMPUTED_VALUE"""),416.07) -> 416.07 | AU18: =IFERROR(__xludf.DUMMYFUNCTION("""COMPUTED_VALUE"""),77.15) -> 77.15 | AV18: =IFERROR(__xludf.DUMMYFUNCTION("""COMPUTED_VALUE"""),116.44) -> 116.44 | AW18: =IFERROR(__xludf.DUMMYFUNCTION("""COMPUTED_VALUE"""),99.21) -> 99.21 | AX18: =IFERROR(__xludf.DUMMYFUNCTION("""COMPUTED_VALUE"""),40.82) -> 40.82 | AY18: =IFERROR(__xludf.DUMMYFUNCTION("""COMPUTED_VALUE"""),22.1) -> 22.1 | AZ18: =IFERROR(__xludf.DUMMYFUNCTION("""COMPUTED_VALUE"""),63.33) -> 63.33 | BA18: =IFERROR(__xludf.DUMMYFUNCTION("""COMPUTED_VALUE"""),29.49) -> 29.49 | BB18: =IFERROR(__xludf.DUMMYFUNCTION("""COMPUTED_VALUE"""),107.9) -> 107.9 | BC18: =IFERROR(__xludf.DUMMYFUNCTION("""COMPUTED_VALUE"""),177.91) -> 177.91 | BD18: =IFERROR(__xludf.DUMMYFUNCTION("""COMPUTED_VALUE"""),569.67) -> 569.67 | BE18: =IFERROR(__xludf.DUMMYFUNCTION("""COMPUTED_VALUE"""),210.38) -> 210.38 | BF18: =IFERROR(__xludf.DUMMYFUNCTION("""COMPUTED_VALUE"""),134.48) -> 134.48 | BG18: =IFERROR(__xludf.DUMMYFUNCTION("""COMPUTED_VALUE"""),7.02) -> 7.02 | BH18: =IFERROR(__xludf.DUMMYFUNCTION("""COMPUTED_VALUE"""),227.62) -> 227.62 | BI18: =IFERROR(__xludf.DUMMYFUNCTION("""COMPUTED_VALUE"""),505.49) -> 505.49 | BJ18: =IFERROR(__xludf.DUMMYFUNCTION("""COMPUTED_VALUE"""),48.34) -> 48.34 | BK18: =IFERROR(__xludf.DUMMYFUNCTION("""COMPUTED_VALUE"""),10.53) -> 10.53 | BL18: =IFERROR(__xludf.DUMMYFUNCTION("""COMPUTED_VALUE"""),203.63) -> 203.63 | BM18: =IFERROR(__xludf.DUMMYFUNCTION("""COMPUTED_VALUE"""),103.33) -> 103.33
A19: 45448.667 | B19: =IFERROR(__xludf.DUMMYFUNCTION("""COMPUTED_VALUE"""),5354.03) -> 5354.03 | C19: =IFERROR(__xludf.DUMMYFUNCTION("""COMPUTED_VALUE"""),17187.91) -> 17187.91 | D19: =IFERROR(__xludf.DUMMYFUNCTION("""COMPUTED_VALUE"""),38807.33) -> 38807.33 | E19: =IFERROR(__xludf.DUMMYFUNCTION("""COMPUTED_VALUE"""),2063.87) -> 2063.87 | F19: =IFERROR(__xludf.DUMMYFUNCTION("""COMPUTED_VALUE"""),455.8) -> 455.8 | G19: =IFERROR(__xludf.DUMMYFUNCTION("""COMPUTED_VALUE"""),181.28) -> 181.28 | H19: =IFERROR(__xludf.DUMMYFUNCTION("""COMPUTED_VALUE"""),131.68) -> 131.68 | I19: =IFERROR(__xludf.DUMMYFUNCTION("""COMPUTED_VALUE"""),195.87) -> 195.87 | J19: =IFERROR(__xludf.DUMMYFUNCTION("""COMPUTED_VALUE"""),223.37) -> 223.37 | K19: =IFERROR(__xludf.DUMMYFUNCTION("""COMPUTED_VALUE"""),58.89) -> 58.89 | L19: =IFERROR(__xludf.DUMMYFUNCTION("""COMPUTED_VALUE"""),11.02) -> 11.02 | M19: =IFERROR(__xludf.DUMMYFUNCTION("""COMPUTED_VALUE"""),409.85) -> 409.85 | N19: =IFERROR(__xludf.DUMMYFUNCTION("""COMPUTED_VALUE"""),58.62) -> 58.62 | O19: =IFERROR(__xludf.DUMMYFUNCTION("""COMPUTED_VALUE"""),236.72) -> 236.72 | P19: =IFERROR(__xludf.DUMMYFUNCTION("""COMPUTED_VALUE"""),63.17) -> 63.17 | Q19: =IFERROR(__xludf.DUMMYFUNCTION("""COMPUTED_VALUE"""),329.45) -> 329.45 | R19: =IFERROR(__xludf.DUMMYFUNCTION("""COMPUTED_VALUE"""),54.28) -> 54.28 | S19: =IFERROR(__xludf.DUMMYFUNCTION("""COMPUTED_VALUE"""),153.8) -> 153.8 | T19: =IFERROR(__xludf.DUMMYFUNCTION("""COMPUTED_VALUE"""),154.98) -> 154.98 | U19: =IFERROR(__xludf.DUMMYFUNCTION("""COMPUTED_VALUE"""),334.18) -> 334.18 | V19: =IFERROR(__xludf.DUMMYFUNCTION("""COMPUTED_VALUE"""),34.11) -> 34.11 | W19: =IFERROR(__xludf.DUMMYFUNCTION("""COMPUTED_VALUE"""),63.92) -> 63.92 | X19: =IFERROR(__xludf.DUMMYFUNCTION("""COMPUTED_VALUE"""),92.6) -> 92.6 | Y19: =IFERROR(__xludf.DUMMYFUNCTION("""COMPUTED_VALUE"""),147.36) -> 147.36 | Z19: =IFERROR(__xludf.DUMMYFUNCTION("""COMPUTED_VALUE"""),114.38) -> 114.38 | AA19: =IFERROR(__xludf.DUMMYFUNCTION("""COMPUTED_VALUE"""),517.1) -> 517.1 | AB19: =IFERROR(__xludf.DUMMYFUNCTION("""COMPUTED_VALUE"""),53.01) -> 53.01 | AC19: =IFERROR(__xludf.DUMMYFUNCTION("""COMPUTED_VALUE"""),113.12) -> 113.12 | AD19: =IFERROR(__xludf.DUMMYFUNCTION("""COMPUTED_VALUE"""),248.05) -> 248.05 | AE19: =IFERROR(__xludf.DUMMYFUNCTION("""COMPUTED_VALUE"""),422.4) -> 422.4 | AF19: =IFERROR(__xludf.DUMMYFUNCTION("""COMPUTED_VALUE"""),299.45) -> 299.45 | AG19: =IFERROR(__xludf.DUMMYFUNCTION("""COMPUTED_VALUE"""),45.62) -> 45.62 | AH19: =IFERROR(__xludf.DUMMYFUNCTION("""COMPUTED_VALUE"""),63.88) -> 63.88 | AI19: =IFERROR(__xludf.DUMMYFUNCTION("""COMPUTED_VALUE"""),461.68) -> 461.68 | AJ19: =IFERROR(__xludf.DUMMYFUNCTION("""COMPUTED_VALUE"""),330.26) -> 330.26 | AK19: =IFERROR(__xludf.DUMMYFUNCTION("""COMPUTED_VALUE"""),94.49) -> 94.49 | AL19: =IFERROR(__xludf.DUMMYFUNCTION("""COMPUTED_VALUE"""),135.34) -> 135.34 | AM19: =IFERROR(__xludf.DUMMYFUNCTION("""COMPUTED_VALUE"""),417.24) -> 417.24 | AN19: =IFERROR(__xludf.DUMMYFUNCTION("""COMPUTED_VALUE"""),197.26) -> 197.26 | AO19: =IFERROR(__xludf.DUMMYFUNCTION("""COMPUTED_VALUE"""),465.23) -> 465.23 | AP19: =IFERROR(__xludf.DUMMYFUNCTION("""COMPUTED_VALUE"""),308.27) -> 308.27 | AQ19: =IFERROR(__xludf.DUMMYFUNCTION("""COMPUTED_VALUE"""),25.82) -> 25.82 | AR19: =IFERROR(__xludf.DUMMYFUNCTION("""COMPUTED_VALUE"""),82.31) -> 82.31 | AS19: =IFERROR(__xludf.DUMMYFUNCTION("""COMPUTED_VALUE"""),70.33) -> 70.33 | AT19: =IFERROR(__xludf.DUMMYFUNCTION("""COMPUTED_VALUE"""),424.01) -> 424.01 | AU19: =IFERROR(__xludf.DUMMYFUNCTION("""COMPUTED_VALUE"""),77.05) -> 77.05 | AV19: =IFERROR(__xludf.DUMMYFUNCTION("""COMPUTED_VALUE"""),122.44) -> 122.44 | AW19: =IFERROR(__xludf.DUMMYFUNCTION("""COMPUTED_VALUE"""),100.78) -> 100.78 | AX19: =IFERROR(__xludf.DUMMYFUNCTION("""COMPUTED_VALUE"""),42.0) -> 42 | AY19: =IFERROR(__xludf.DUMMYFUNCTION("""COMPUTED_VALUE"""),22.96) -> 22.96 | AZ19: =IFERROR(__xludf.DUMMYFUNCTION("""COMPUTED_VALUE"""),63.53) -> 63.53 | BA19: =IFERROR(__xludf.DUMMYFUNCTION("""COMPUTED_VALUE"""),29.55) -> 29.55 | BB19: =IFERROR(__xludf.DUMMYFUNCTION("""COMPUTED_VALUE"""),108.44) -> 108.44 | BC19: =IFERROR(__xludf.DUMMYFUNCTION("""COMPUTED_VALUE"""),180.27) -> 180.27 | BD19: =IFERROR(__xludf.DUMMYFUNCTION("""COMPUTED_VALUE"""),575.28) -> 575.28 | BE19: =IFERROR(__xludf.DUMMYFUNCTION("""COMPUTED_VALUE"""),208.33) -> 208.33 | BF19: =IFERROR(__xludf.DUMMYFUNCTION("""COMPUTED_VALUE"""),135.09) -> 135.09 | BG19: =IFERROR(__xludf.DUMMYFUNCTION("""COMPUTED_VALUE"""),6.88) -> 6.88 | BH19: =IFERROR(__xludf.DUMMYFUNCTION("""COMPUTED_VALUE"""),227.41) -> 227.41 | BI19: =IFERROR(__xludf.DUMMYFUNCTION("""COMPUTED_VALUE"""),503.12) -> 503.12 | BJ19: =IFERROR(__xludf.DUMMYFUNCTION("""COMPUTED_VALUE"""),48.39) -> 48.39 | BK19: =IFERROR(__xludf.DUMMYFUNCTION("""COMPUTED_VALUE"""),10.49) -> 10.49 | BL19: =IFERROR(__xludf.DUMMYFUNCTION("""COMPUTED_VALUE"""),203.9) -> 203.9 | BM19: =IFERROR(__xludf.DUMMYFUNCTION("""COMPUTED_VALUE"""),101.5) -> 101.5
A20: 45449.667 | B20: =IFERROR(__xludf.DUMMYFUNCTION("""COMPUTED_VALUE"""),5352.96) -> 5352.96 | C20: =IFERROR(__xludf.DUMMYFUNCTION("""COMPUTED_VALUE"""),17173.12) -> 17173.12 | D20: =IFERROR(__xludf.DUMMYFUNCTION("""COMPUTED_VALUE"""),38886.17) -> 38886.17 | E20: =IFERROR(__xludf.DUMMYFUNCTION("""COMPUTED_VALUE"""),2049.44) -> 2049.44 | F20: =IFERROR(__xludf.DUMMYFUNCTION("""COMPUTED_VALUE"""),458.13) -> 458.13 | G20: =IFERROR(__xludf.DUMMYFUNCTION("""COMPUTED_VALUE"""),185.0) -> 185 | H20: =IFERROR(__xludf.DUMMYFUNCTION("""COMPUTED_VALUE"""),130.62) -> 130.62 | I20: =IFERROR(__xludf.DUMMYFUNCTION("""COMPUTED_VALUE"""),194.48) -> 194.48 | J20: =IFERROR(__xludf.DUMMYFUNCTION("""COMPUTED_VALUE"""),221.75) -> 221.75 | K20: =IFERROR(__xludf.DUMMYFUNCTION("""COMPUTED_VALUE"""),59.91) -> 59.91 | L20: =IFERROR(__xludf.DUMMYFUNCTION("""COMPUTED_VALUE"""),11.12) -> 11.12 | M20: =IFERROR(__xludf.DUMMYFUNCTION("""COMPUTED_VALUE"""),411.08) -> 411.08 | N20: =IFERROR(__xludf.DUMMYFUNCTION("""COMPUTED_VALUE"""),59.7) -> 59.7 | O20: =IFERROR(__xludf.DUMMYFUNCTION("""COMPUTED_VALUE"""),231.99) -> 231.99 | P20: =IFERROR(__xludf.DUMMYFUNCTION("""COMPUTED_VALUE"""),62.48) -> 62.48 | Q20: =IFERROR(__xludf.DUMMYFUNCTION("""COMPUTED_VALUE"""),328.29) -> 328.29 | R20: =IFERROR(__xludf.DUMMYFUNCTION("""COMPUTED_VALUE"""),55.47) -> 55.47 | S20: =IFERROR(__xludf.DUMMYFUNCTION("""COMPUTED_VALUE"""),154.82) -> 154.82 | T20: =IFERROR(__xludf.DUMMYFUNCTION("""COMPUTED_VALUE"""),155.93) -> 155.93 | U20: =IFERROR(__xludf.DUMMYFUNCTION("""COMPUTED_VALUE"""),337.91) -> 337.91 | V20: =IFERROR(__xludf.DUMMYFUNCTION("""COMPUTED_VALUE"""),34.06) -> 34.06 | W20: =IFERROR(__xludf.DUMMYFUNCTION("""COMPUTED_VALUE"""),64.15) -> 64.15 | X20: =IFERROR(__xludf.DUMMYFUNCTION("""COMPUTED_VALUE"""),91.89) -> 91.89 | Y20: =IFERROR(__xludf.DUMMYFUNCTION("""COMPUTED_VALUE"""),147.12) -> 147.12 | Z20: =IFERROR(__xludf.DUMMYFUNCTION("""COMPUTED_VALUE"""),112.37) -> 112.37 | AA20: =IFERROR(__xludf.DUMMYFUNCTION("""COMPUTED_VALUE"""),513.69) -> 513.69 | AB20: =IFERROR(__xludf.DUMMYFUNCTION("""COMPUTED_VALUE"""),53.39) -> 53.39 | AC20: =IFERROR(__xludf.DUMMYFUNCTION("""COMPUTED_VALUE"""),113.97) -> 113.97 | AD20: =IFERROR(__xludf.DUMMYFUNCTION("""COMPUTED_VALUE"""),250.27) -> 250.27 | AE20: =IFERROR(__xludf.DUMMYFUNCTION("""COMPUTED_VALUE"""),416.92) -> 416.92 | AF20: =IFERROR(__xludf.DUMMYFUNCTION("""COMPUTED_VALUE"""),298.27) -> 298.27 | AG20: =IFERROR(__xludf.DUMMYFUNCTION("""COMPUTED_VALUE"""),45.61) -> 45.61 | AH20: =IFERROR(__xludf.DUMMYFUNCTION("""COMPUTED_VALUE"""),63.85) -> 63.85 | AI20: =IFERROR(__xludf.DUMMYFUNCTION("""COMPUTED_VALUE"""),458.1) -> 458.1 | AJ20: =IFERROR(__xludf.DUMMYFUNCTION("""COMPUTED_VALUE"""),331.1) -> 331.1 | AK20: =IFERROR(__xludf.DUMMYFUNCTION("""COMPUTED_VALUE"""),96.12) -> 96.12 | AL20: =IFERROR(__xludf.DUMMYFUNCTION("""COMPUTED_VALUE"""),134.86) -> 134.86 | AM20: =IFERROR(__xludf.DUMMYFUNCTION("""COMPUTED_VALUE"""),418.15) -> 418.15 | AN20: =IFERROR(__xludf.DUMMYFUNCTION("""COMPUTED_VALUE"""),196.91) -> 196.91 | AO20: =IFERROR(__xludf.DUMMYFUNCTION("""COMPUTED_VALUE"""),468.62) -> 468.62 | AP20: =IFERROR(__xludf.DUMMYFUNCTION("""COMPUTED_VALUE"""),323.03) -> 323.03 | AQ20: =IFERROR(__xludf.DUMMYFUNCTION("""COMPUTED_VALUE"""),25.87) -> 25.87 | AR20: =IFERROR(__xludf.DUMMYFUNCTION("""COMPUTED_VALUE"""),82.34) -> 82.34 | AS20: =IFERROR(__xludf.DUMMYFUNCTION("""COMPUTED_VALUE"""),70.04) -> 70.04 | AT20: =IFERROR(__xludf.DUMMYFUNCTION("""COMPUTED_VALUE"""),424.52) -> 424.52 | AU20: =IFERROR(__xludf.DUMMYFUNCTION("""COMPUTED_VALUE"""),76.7) -> 76.7 | AV20: =IFERROR(__xludf.DUMMYFUNCTION("""COMPUTED_VALUE"""),121.0) -> 121 | AW20: =IFERROR(__xludf.DUMMYFUNCTION("""COMPUTED_VALUE"""),99.41) -> 99.41 | AX20: =IFERROR(__xludf.DUMMYFUNCTION("""COMPUTED_VALUE"""),42.2) -> 42.2 | AY20: =IFERROR(__xludf.DUMMYFUNCTION("""COMPUTED_VALUE"""),23.79) -> 23.79 | AZ20: =IFERROR(__xludf.DUMMYFUNCTION("""COMPUTED_VALUE"""),67.02) -> 67.02 | BA20: =IFERROR(__xludf.DUMMYFUNCTION("""COMPUTED_VALUE"""),28.8) -> 28.8 | BB20: =IFERROR(__xludf.DUMMYFUNCTION("""COMPUTED_VALUE"""),108.18) -> 108.18 | BC20: =IFERROR(__xludf.DUMMYFUNCTION("""COMPUTED_VALUE"""),179.77) -> 179.77 | BD20: =IFERROR(__xludf.DUMMYFUNCTION("""COMPUTED_VALUE"""),579.84) -> 579.84 | BE20: =IFERROR(__xludf.DUMMYFUNCTION("""COMPUTED_VALUE"""),210.04) -> 210.04 | BF20: =IFERROR(__xludf.DUMMYFUNCTION("""COMPUTED_VALUE"""),133.02) -> 133.02 | BG20: =IFERROR(__xludf.DUMMYFUNCTION("""COMPUTED_VALUE"""),6.94) -> 6.94 | BH20: =IFERROR(__xludf.DUMMYFUNCTION("""COMPUTED_VALUE"""),228.31) -> 228.31 | BI20: =IFERROR(__xludf.DUMMYFUNCTION("""COMPUTED_VALUE"""),501.92) -> 501.92 | BJ20: =IFERROR(__xludf.DUMMYFUNCTION("""COMPUTED_VALUE"""),48.39) -> 48.39 | BK20: =IFERROR(__xludf.DUMMYFUNCTION("""COMPUTED_VALUE"""),10.42) -> 10.42 | BL20: =IFERROR(__xludf.DUMMYFUNCTION("""COMPUTED_VALUE"""),202.5) -> 202.5 | BM20: =IFERROR(__xludf.DUMMYFUNCTION("""COMPUTED_VALUE"""),101.21) -> 101.21
A21: 45450.667 | B21: =IFERROR(__xludf.DUMMYFUNCTION("""COMPUTED_VALUE"""),5346.99) -> 5346.99 | C21: =IFERROR(__xludf.DUMMYFUNCTION("""COMPUTED_VALUE"""),17133.13) -> 17133.13 | D21: =IFERROR(__xludf.DUMMYFUNCTION("""COMPUTED_VALUE"""),38798.99) -> 38798.99 | E21: =IFERROR(__xludf.DUMMYFUNCTION("""COMPUTED_VALUE"""),2026.55) -> 2026.55 | F21: =IFERROR(__xludf.DUMMYFUNCTION("""COMPUTED_VALUE"""),465.43) -> 465.43 | G21: =IFERROR(__xludf.DUMMYFUNCTION("""COMPUTED_VALUE"""),184.3) -> 184.3 | H21: =IFERROR(__xludf.DUMMYFUNCTION("""COMPUTED_VALUE"""),128.25) -> 128.25 | I21: =IFERROR(__xludf.DUMMYFUNCTION("""COMPUTED_VALUE"""),196.89) -> 196.89 | J21: =IFERROR(__xludf.DUMMYFUNCTION("""COMPUTED_VALUE"""),221.73) -> 221.73 | K21: =IFERROR(__xludf.DUMMYFUNCTION("""COMPUTED_VALUE"""),60.31) -> 60.31 | L21: =IFERROR(__xludf.DUMMYFUNCTION("""COMPUTED_VALUE"""),11.07) -> 11.07 | M21: =IFERROR(__xludf.DUMMYFUNCTION("""COMPUTED_VALUE"""),413.72) -> 413.72 | N21: =IFERROR(__xludf.DUMMYFUNCTION("""COMPUTED_VALUE"""),58.19) -> 58.19 | O21: =IFERROR(__xludf.DUMMYFUNCTION("""COMPUTED_VALUE"""),225.43) -> 225.43 | P21: =IFERROR(__xludf.DUMMYFUNCTION("""COMPUTED_VALUE"""),62.71) -> 62.71 | Q21: =IFERROR(__xludf.DUMMYFUNCTION("""COMPUTED_VALUE"""),328.94) -> 328.94 | R21: =IFERROR(__xludf.DUMMYFUNCTION("""COMPUTED_VALUE"""),53.4) -> 53.4 | S21: =IFERROR(__xludf.DUMMYFUNCTION("""COMPUTED_VALUE"""),156.41) -> 156.41 | T21: =IFERROR(__xludf.DUMMYFUNCTION("""COMPUTED_VALUE"""),156.08) -> 156.08 | U21: =IFERROR(__xludf.DUMMYFUNCTION("""COMPUTED_VALUE"""),338.1) -> 338.1 | V21: =IFERROR(__xludf.DUMMYFUNCTION("""COMPUTED_VALUE"""),34.15) -> 34.15 | W21: =IFERROR(__xludf.DUMMYFUNCTION("""COMPUTED_VALUE"""),63.91) -> 63.91 | X21: =IFERROR(__xludf.DUMMYFUNCTION("""COMPUTED_VALUE"""),91.61) -> 91.61 | Y21: =IFERROR(__xludf.DUMMYFUNCTION("""COMPUTED_VALUE"""),146.35) -> 146.35 | Z21: =IFERROR(__xludf.DUMMYFUNCTION("""COMPUTED_VALUE"""),111.29) -> 111.29 | AA21: =IFERROR(__xludf.DUMMYFUNCTION("""COMPUTED_VALUE"""),513.55) -> 513.55 | AB21: =IFERROR(__xludf.DUMMYFUNCTION("""COMPUTED_VALUE"""),53.08) -> 53.08 | AC21: =IFERROR(__xludf.DUMMYFUNCTION("""COMPUTED_VALUE"""),112.75) -> 112.75 | AD21: =IFERROR(__xludf.DUMMYFUNCTION("""COMPUTED_VALUE"""),247.73) -> 247.73 | AE21: =IFERROR(__xludf.DUMMYFUNCTION("""COMPUTED_VALUE"""),412.93) -> 412.93 | AF21: =IFERROR(__xludf.DUMMYFUNCTION("""COMPUTED_VALUE"""),299.14) -> 299.14 | AG21: =IFERROR(__xludf.DUMMYFUNCTION("""COMPUTED_VALUE"""),45.72) -> 45.72 | AH21: =IFERROR(__xludf.DUMMYFUNCTION("""COMPUTED_VALUE"""),64.7) -> 64.7 | AI21: =IFERROR(__xludf.DUMMYFUNCTION("""COMPUTED_VALUE"""),454.91) -> 454.91 | AJ21: =IFERROR(__xludf.DUMMYFUNCTION("""COMPUTED_VALUE"""),327.03) -> 327.03 | AK21: =IFERROR(__xludf.DUMMYFUNCTION("""COMPUTED_VALUE"""),97.36) -> 97.36 | AL21: =IFERROR(__xludf.DUMMYFUNCTION("""COMPUTED_VALUE"""),133.79) -> 133.79 | AM21: =IFERROR(__xludf.DUMMYFUNCTION("""COMPUTED_VALUE"""),417.61) -> 417.61 | AN21: =IFERROR(__xludf.DUMMYFUNCTION("""COMPUTED_VALUE"""),199.95) -> 199.95 | AO21: =IFERROR(__xludf.DUMMYFUNCTION("""COMPUTED_VALUE"""),470.13) -> 470.13 | AP21: =IFERROR(__xludf.DUMMYFUNCTION("""COMPUTED_VALUE"""),317.86) -> 317.86 | AQ21: =IFERROR(__xludf.DUMMYFUNCTION("""COMPUTED_VALUE"""),25.85) -> 25.85 | AR21: =IFERROR(__xludf.DUMMYFUNCTION("""COMPUTED_VALUE"""),84.07) -> 84.07 | AS21: =IFERROR(__xludf.DUMMYFUNCTION("""COMPUTED_VALUE"""),70.05) -> 70.05 | AT21: =IFERROR(__xludf.DUMMYFUNCTION("""COMPUTED_VALUE"""),423.85) -> 423.85 | AU21: =IFERROR(__xludf.DUMMYFUNCTION("""COMPUTED_VALUE"""),75.39) -> 75.39 | AV21: =IFERROR(__xludf.DUMMYFUNCTION("""COMPUTED_VALUE"""),120.89) -> 120.89 | AW21: =IFERROR(__xludf.DUMMYFUNCTION("""COMPUTED_VALUE"""),98.66) -> 98.66 | AX21: =IFERROR(__xludf.DUMMYFUNCTION("""COMPUTED_VALUE"""),42.35) -> 42.35 | AY21: =IFERROR(__xludf.DUMMYFUNCTION("""COMPUTED_VALUE"""),23.31) -> 23.31 | AZ21: =IFERROR(__xludf.DUMMYFUNCTION("""COMPUTED_VALUE"""),67.3) -> 67.3 | BA21: =IFERROR(__xludf.DUMMYFUNCTION("""COMPUTED_VALUE"""),28.58) -> 28.58 | BB21: =IFERROR(__xludf.DUMMYFUNCTION("""COMPUTED_VALUE"""),108.11) -> 108.11 | BC21: =IFERROR(__xludf.DUMMYFUNCTION("""COMPUTED_VALUE"""),179.82) -> 179.82 | BD21: =IFERROR(__xludf.DUMMYFUNCTION("""COMPUTED_VALUE"""),581.09) -> 581.09 | BE21: =IFERROR(__xludf.DUMMYFUNCTION("""COMPUTED_VALUE"""),206.36) -> 206.36 | BF21: =IFERROR(__xludf.DUMMYFUNCTION("""COMPUTED_VALUE"""),137.18) -> 137.18 | BG21: =IFERROR(__xludf.DUMMYFUNCTION("""COMPUTED_VALUE"""),6.91) -> 6.91 | BH21: =IFERROR(__xludf.DUMMYFUNCTION("""COMPUTED_VALUE"""),227.97) -> 227.97 | BI21: =IFERROR(__xludf.DUMMYFUNCTION("""COMPUTED_VALUE"""),490.69) -> 490.69 | BJ21: =IFERROR(__xludf.DUMMYFUNCTION("""COMPUTED_VALUE"""),48.25) -> 48.25 | BK21: =IFERROR(__xludf.DUMMYFUNCTION("""COMPUTED_VALUE"""),10.47) -> 10.47 | BL21: =IFERROR(__xludf.DUMMYFUNCTION("""COMPUTED_VALUE"""),200.55) -> 200.55 | BM21: =IFERROR(__xludf.DUMMYFUNCTION("""COMPUTED_VALUE"""),101.54) -> 101.54
A22: 45453.667 | B22: =IFERROR(__xludf.DUMMYFUNCTION("""COMPUTED_VALUE"""),5360.79) -> 5360.79 | C22: =IFERROR(__xludf.DUMMYFUNCTION("""COMPUTED_VALUE"""),17192.53) -> 17192.53 | D22: =IFERROR(__xludf.DUMMYFUNCTION("""COMPUTED_VALUE"""),38868.04) -> 38868.04 | E22: =IFERROR(__xludf.DUMMYFUNCTION("""COMPUTED_VALUE"""),2031.61) -> 2031.61 | F22: =IFERROR(__xludf.DUMMYFUNCTION("""COMPUTED_VALUE"""),459.94) -> 459.94 | G22: =IFERROR(__xludf.DUMMYFUNCTION("""COMPUTED_VALUE"""),187.06) -> 187.06 | H22: =IFERROR(__xludf.DUMMYFUNCTION("""COMPUTED_VALUE"""),128.56) -> 128.56 | I22: =IFERROR(__xludf.DUMMYFUNCTION("""COMPUTED_VALUE"""),193.12) -> 193.12 | J22: =IFERROR(__xludf.DUMMYFUNCTION("""COMPUTED_VALUE"""),228.16) -> 228.16 | K22: =IFERROR(__xludf.DUMMYFUNCTION("""COMPUTED_VALUE"""),60.74) -> 60.74 | L22: =IFERROR(__xludf.DUMMYFUNCTION("""COMPUTED_VALUE"""),11.05) -> 11.05 | M22: =IFERROR(__xludf.DUMMYFUNCTION("""COMPUTED_VALUE"""),410.81) -> 410.81 | N22: =IFERROR(__xludf.DUMMYFUNCTION("""COMPUTED_VALUE"""),58.41) -> 58.41 | O22: =IFERROR(__xludf.DUMMYFUNCTION("""COMPUTED_VALUE"""),225.98) -> 225.98 | P22: =IFERROR(__xludf.DUMMYFUNCTION("""COMPUTED_VALUE"""),62.54) -> 62.54 | Q22: =IFERROR(__xludf.DUMMYFUNCTION("""COMPUTED_VALUE"""),329.61) -> 329.61 | R22: =IFERROR(__xludf.DUMMYFUNCTION("""COMPUTED_VALUE"""),53.6) -> 53.6 | S22: =IFERROR(__xludf.DUMMYFUNCTION("""COMPUTED_VALUE"""),156.11) -> 156.11 | T22: =IFERROR(__xludf.DUMMYFUNCTION("""COMPUTED_VALUE"""),156.74) -> 156.74 | U22: =IFERROR(__xludf.DUMMYFUNCTION("""COMPUTED_VALUE"""),338.65) -> 338.65 | V22: =IFERROR(__xludf.DUMMYFUNCTION("""COMPUTED_VALUE"""),34.38) -> 34.38 | W22: =IFERROR(__xludf.DUMMYFUNCTION("""COMPUTED_VALUE"""),63.59) -> 63.59 | X22: =IFERROR(__xludf.DUMMYFUNCTION("""COMPUTED_VALUE"""),92.32) -> 92.32 | Y22: =IFERROR(__xludf.DUMMYFUNCTION("""COMPUTED_VALUE"""),149.09) -> 149.09 | Z22: =IFERROR(__xludf.DUMMYFUNCTION("""COMPUTED_VALUE"""),110.19) -> 110.19 | AA22: =IFERROR(__xludf.DUMMYFUNCTION("""COMPUTED_VALUE"""),526.55) -> 526.55 | AB22: =IFERROR(__xludf.DUMMYFUNCTION("""COMPUTED_VALUE"""),53.15) -> 53.15 | AC22: =IFERROR(__xludf.DUMMYFUNCTION("""COMPUTED_VALUE"""),113.08) -> 113.08 | AD22: =IFERROR(__xludf.DUMMYFUNCTION("""COMPUTED_VALUE"""),253.72) -> 253.72 | AE22: =IFERROR(__xludf.DUMMYFUNCTION("""COMPUTED_VALUE"""),413.48) -> 413.48 | AF22: =IFERROR(__xludf.DUMMYFUNCTION("""COMPUTED_VALUE"""),294.68) -> 294.68 | AG22: =IFERROR(__xludf.DUMMYFUNCTION("""COMPUTED_VALUE"""),47.57) -> 47.57 | AH22: =IFERROR(__xludf.DUMMYFUNCTION("""COMPUTED_VALUE"""),65.25) -> 65.25 | AI22: =IFERROR(__xludf.DUMMYFUNCTION("""COMPUTED_VALUE"""),453.55) -> 453.55 | AJ22: =IFERROR(__xludf.DUMMYFUNCTION("""COMPUTED_VALUE"""),332.56) -> 332.56 | AK22: =IFERROR(__xludf.DUMMYFUNCTION("""COMPUTED_VALUE"""),97.38) -> 97.38 | AL22: =IFERROR(__xludf.DUMMYFUNCTION("""COMPUTED_VALUE"""),133.88) -> 133.88 | AM22: =IFERROR(__xludf.DUMMYFUNCTION("""COMPUTED_VALUE"""),418.38) -> 418.38 | AN22: =IFERROR(__xludf.DUMMYFUNCTION("""COMPUTED_VALUE"""),199.61) -> 199.61 | AO22: =IFERROR(__xludf.DUMMYFUNCTION("""COMPUTED_VALUE"""),467.46) -> 467.46 | AP22: =IFERROR(__xludf.DUMMYFUNCTION("""COMPUTED_VALUE"""),318.26) -> 318.26 | AQ22: =IFERROR(__xludf.DUMMYFUNCTION("""COMPUTED_VALUE"""),26.24) -> 26.24 | AR22: =IFERROR(__xludf.DUMMYFUNCTION("""COMPUTED_VALUE"""),83.14) -> 83.14 | AS22: =IFERROR(__xludf.DUMMYFUNCTION("""COMPUTED_VALUE"""),70.27) -> 70.27 | AT22: =IFERROR(__xludf.DUMMYFUNCTION("""COMPUTED_VALUE"""),427.87) -> 427.87 | AU22: =IFERROR(__xludf.DUMMYFUNCTION("""COMPUTED_VALUE"""),76.97) -> 76.97 | AV22: =IFERROR(__xludf.DUMMYFUNCTION("""COMPUTED_VALUE"""),121.79) -> 121.79 | AW22: =IFERROR(__xludf.DUMMYFUNCTION("""COMPUTED_VALUE"""),97.75) -> 97.75 | AX22: =IFERROR(__xludf.DUMMYFUNCTION("""COMPUTED_VALUE"""),42.73) -> 42.73 | AY22: =IFERROR(__xludf.DUMMYFUNCTION("""COMPUTED_VALUE"""),23.13) -> 23.13 | AZ22: =IFERROR(__xludf.DUMMYFUNCTION("""COMPUTED_VALUE"""),67.09) -> 67.09 | BA22: =IFERROR(__xludf.DUMMYFUNCTION("""COMPUTED_VALUE"""),28.07) -> 28.07 | BB22: =IFERROR(__xludf.DUMMYFUNCTION("""COMPUTED_VALUE"""),107.09) -> 107.09 | BC22: =IFERROR(__xludf.DUMMYFUNCTION("""COMPUTED_VALUE"""),180.69) -> 180.69 | BD22: =IFERROR(__xludf.DUMMYFUNCTION("""COMPUTED_VALUE"""),581.48) -> 581.48 | BE22: =IFERROR(__xludf.DUMMYFUNCTION("""COMPUTED_VALUE"""),208.02) -> 208.02 | BF22: =IFERROR(__xludf.DUMMYFUNCTION("""COMPUTED_VALUE"""),144.67) -> 144.67 | BG22: =IFERROR(__xludf.DUMMYFUNCTION("""COMPUTED_VALUE"""),6.81) -> 6.81 | BH22: =IFERROR(__xludf.DUMMYFUNCTION("""COMPUTED_VALUE"""),228.95) -> 228.95 | BI22: =IFERROR(__xludf.DUMMYFUNCTION("""COMPUTED_VALUE"""),495.0) -> 495 | BJ22: =IFERROR(__xludf.DUMMYFUNCTION("""COMPUTED_VALUE"""),48.25) -> 48.25 | BK22: =IFERROR(__xludf.DUMMYFUNCTION("""COMPUTED_VALUE"""),10.51) -> 10.51 | BL22: =IFERROR(__xludf.DUMMYFUNCTION("""COMPUTED_VALUE"""),201.71) -> 201.71 | BM22: =IFERROR(__xludf.DUMMYFUNCTION("""COMPUTED_VALUE"""),102.74) -> 102.74
A23: 45454.667 | B23: =IFERROR(__xludf.DUMMYFUNCTION("""COMPUTED_VALUE"""),5375.32) -> 5375.32 | C23: =IFERROR(__xludf.DUMMYFUNCTION("""COMPUTED_VALUE"""),17343.55) -> 17343.55 | D23: =IFERROR(__xludf.DUMMYFUNCTION("""COMPUTED_VALUE"""),38747.42) -> 38747.42 | E23: =IFERROR(__xludf.DUMMYFUNCTION("""COMPUTED_VALUE"""),2024.35) -> 2024.35 | F23: =IFERROR(__xludf.DUMMYFUNCTION("""COMPUTED_VALUE"""),462.69) -> 462.69 | G23: =IFERROR(__xludf.DUMMYFUNCTION("""COMPUTED_VALUE"""),187.23) -> 187.23 | H23: =IFERROR(__xludf.DUMMYFUNCTION("""COMPUTED_VALUE"""),127.92) -> 127.92 | I23: =IFERROR(__xludf.DUMMYFUNCTION("""COMPUTED_VALUE"""),207.15) -> 207.15 | J23: =IFERROR(__xludf.DUMMYFUNCTION("""COMPUTED_VALUE"""),229.97) -> 229.97 | K23: =IFERROR(__xludf.DUMMYFUNCTION("""COMPUTED_VALUE"""),58.76) -> 58.76 | L23: =IFERROR(__xludf.DUMMYFUNCTION("""COMPUTED_VALUE"""),10.73) -> 10.73 | M23: =IFERROR(__xludf.DUMMYFUNCTION("""COMPUTED_VALUE"""),408.5) -> 408.5 | N23: =IFERROR(__xludf.DUMMYFUNCTION("""COMPUTED_VALUE"""),56.8) -> 56.8 | O23: =IFERROR(__xludf.DUMMYFUNCTION("""COMPUTED_VALUE"""),225.74) -> 225.74 | P23: =IFERROR(__xludf.DUMMYFUNCTION("""COMPUTED_VALUE"""),62.0) -> 62 | Q23: =IFERROR(__xludf.DUMMYFUNCTION("""COMPUTED_VALUE"""),327.31) -> 327.31 | R23: =IFERROR(__xludf.DUMMYFUNCTION("""COMPUTED_VALUE"""),50.81) -> 50.81 | S23: =IFERROR(__xludf.DUMMYFUNCTION("""COMPUTED_VALUE"""),156.89) -> 156.89 | T23: =IFERROR(__xludf.DUMMYFUNCTION("""COMPUTED_VALUE"""),156.49) -> 156.49 | U23: =IFERROR(__xludf.DUMMYFUNCTION("""COMPUTED_VALUE"""),337.94) -> 337.94 | V23: =IFERROR(__xludf.DUMMYFUNCTION("""COMPUTED_VALUE"""),33.97) -> 33.97 | W23: =IFERROR(__xludf.DUMMYFUNCTION("""COMPUTED_VALUE"""),63.55) -> 63.55 | X23: =IFERROR(__xludf.DUMMYFUNCTION("""COMPUTED_VALUE"""),91.75) -> 91.75 | Y23: =IFERROR(__xludf.DUMMYFUNCTION("""COMPUTED_VALUE"""),149.88) -> 149.88 | Z23: =IFERROR(__xludf.DUMMYFUNCTION("""COMPUTED_VALUE"""),109.64) -> 109.64 | AA23: =IFERROR(__xludf.DUMMYFUNCTION("""COMPUTED_VALUE"""),527.95) -> 527.95 | AB23: =IFERROR(__xludf.DUMMYFUNCTION("""COMPUTED_VALUE"""),53.0) -> 53 | AC23: =IFERROR(__xludf.DUMMYFUNCTION("""COMPUTED_VALUE"""),112.17) -> 112.17 | AD23: =IFERROR(__xludf.DUMMYFUNCTION("""COMPUTED_VALUE"""),252.43) -> 252.43 | AE23: =IFERROR(__xludf.DUMMYFUNCTION("""COMPUTED_VALUE"""),410.94) -> 410.94 | AF23: =IFERROR(__xludf.DUMMYFUNCTION("""COMPUTED_VALUE"""),292.65) -> 292.65 | AG23: =IFERROR(__xludf.DUMMYFUNCTION("""COMPUTED_VALUE"""),48.21) -> 48.21 | AH23: =IFERROR(__xludf.DUMMYFUNCTION("""COMPUTED_VALUE"""),64.89) -> 64.89 | AI23: =IFERROR(__xludf.DUMMYFUNCTION("""COMPUTED_VALUE"""),444.27) -> 444.27 | AJ23: =IFERROR(__xludf.DUMMYFUNCTION("""COMPUTED_VALUE"""),335.72) -> 335.72 | AK23: =IFERROR(__xludf.DUMMYFUNCTION("""COMPUTED_VALUE"""),97.2) -> 97.2 | AL23: =IFERROR(__xludf.DUMMYFUNCTION("""COMPUTED_VALUE"""),134.59) -> 134.59 | AM23: =IFERROR(__xludf.DUMMYFUNCTION("""COMPUTED_VALUE"""),418.78) -> 418.78 | AN23: =IFERROR(__xludf.DUMMYFUNCTION("""COMPUTED_VALUE"""),194.36) -> 194.36 | AO23: =IFERROR(__xludf.DUMMYFUNCTION("""COMPUTED_VALUE"""),462.8) -> 462.8 | AP23: =IFERROR(__xludf.DUMMYFUNCTION("""COMPUTED_VALUE"""),318.04) -> 318.04 | AQ23: =IFERROR(__xludf.DUMMYFUNCTION("""COMPUTED_VALUE"""),25.77) -> 25.77 | AR23: =IFERROR(__xludf.DUMMYFUNCTION("""COMPUTED_VALUE"""),81.95) -> 81.95 | AS23: =IFERROR(__xludf.DUMMYFUNCTION("""COMPUTED_VALUE"""),69.06) -> 69.06 | AT23: =IFERROR(__xludf.DUMMYFUNCTION("""COMPUTED_VALUE"""),432.68) -> 432.68 | AU23: =IFERROR(__xludf.DUMMYFUNCTION("""COMPUTED_VALUE"""),72.74) -> 72.74 | AV23: =IFERROR(__xludf.DUMMYFUNCTION("""COMPUTED_VALUE"""),120.91) -> 120.91 | AW23: =IFERROR(__xludf.DUMMYFUNCTION("""COMPUTED_VALUE"""),96.5) -> 96.5 | AX23: =IFERROR(__xludf.DUMMYFUNCTION("""COMPUTED_VALUE"""),43.79) -> 43.79 | AY23: =IFERROR(__xludf.DUMMYFUNCTION("""COMPUTED_VALUE"""),23.85) -> 23.85 | AZ23: =IFERROR(__xludf.DUMMYFUNCTION("""COMPUTED_VALUE"""),64.77) -> 64.77 | BA23: =IFERROR(__xludf.DUMMYFUNCTION("""COMPUTED_VALUE"""),28.03) -> 28.03 | BB23: =IFERROR(__xludf.DUMMYFUNCTION("""COMPUTED_VALUE"""),106.92) -> 106.92 | BC23: =IFERROR(__xludf.DUMMYFUNCTION("""COMPUTED_VALUE"""),178.4) -> 178.4 | BD23: =IFERROR(__xludf.DUMMYFUNCTION("""COMPUTED_VALUE"""),575.89) -> 575.89 | BE23: =IFERROR(__xludf.DUMMYFUNCTION("""COMPUTED_VALUE"""),205.31) -> 205.31 | BF23: =IFERROR(__xludf.DUMMYFUNCTION("""COMPUTED_VALUE"""),139.03) -> 139.03 | BG23: =IFERROR(__xludf.DUMMYFUNCTION("""COMPUTED_VALUE"""),6.82) -> 6.82 | BH23: =IFERROR(__xludf.DUMMYFUNCTION("""COMPUTED_VALUE"""),227.41) -> 227.41 | BI23: =IFERROR(__xludf.DUMMYFUNCTION("""COMPUTED_VALUE"""),496.22) -> 496.22 | BJ23: =IFERROR(__xludf.DUMMYFUNCTION("""COMPUTED_VALUE"""),48.29) -> 48.29 | BK23: =IFERROR(__xludf.DUMMYFUNCTION("""COMPUTED_VALUE"""),10.64) -> 10.64 | BL23: =IFERROR(__xludf.DUMMYFUNCTION("""COMPUTED_VALUE"""),202.13) -> 202.13 | BM23: =IFERROR(__xludf.DUMMYFUNCTION("""COMPUTED_VALUE"""),100.87) -> 100.87
A24: 45455.667 | B24: =IFERROR(__xludf.DUMMYFUNCTION("""COMPUTED_VALUE"""),5421.03) -> 5421.03 | C24: =IFERROR(__xludf.DUMMYFUNCTION("""COMPUTED_VALUE"""),17608.44) -> 17608.44 | D24: =IFERROR(__xludf.DUMMYFUNCTION("""COMPUTED_VALUE"""),38712.21) -> 38712.21 | E24: =IFERROR(__xludf.DUMMYFUNCTION("""COMPUTED_VALUE"""),2057.1) -> 2057.1 | F24: =IFERROR(__xludf.DUMMYFUNCTION("""COMPUTED_VALUE"""),459.87) -> 459.87 | G24: =IFERROR(__xludf.DUMMYFUNCTION("""COMPUTED_VALUE"""),186.89) -> 186.89 | H24: =IFERROR(__xludf.DUMMYFUNCTION("""COMPUTED_VALUE"""),128.13) -> 128.13 | I24: =IFERROR(__xludf.DUMMYFUNCTION("""COMPUTED_VALUE"""),213.07) -> 213.07 | J24: =IFERROR(__xludf.DUMMYFUNCTION("""COMPUTED_VALUE"""),237.65) -> 237.65 | K24: =IFERROR(__xludf.DUMMYFUNCTION("""COMPUTED_VALUE"""),58.61) -> 58.61 | L24: =IFERROR(__xludf.DUMMYFUNCTION("""COMPUTED_VALUE"""),10.77) -> 10.77 | M24: =IFERROR(__xludf.DUMMYFUNCTION("""COMPUTED_VALUE"""),408.77) -> 408.77 | N24: =IFERROR(__xludf.DUMMYFUNCTION("""COMPUTED_VALUE"""),57.39) -> 57.39 | O24: =IFERROR(__xludf.DUMMYFUNCTION("""COMPUTED_VALUE"""),230.63) -> 230.63 | P24: =IFERROR(__xludf.DUMMYFUNCTION("""COMPUTED_VALUE"""),64.38) -> 64.38 | Q24: =IFERROR(__xludf.DUMMYFUNCTION("""COMPUTED_VALUE"""),328.73) -> 328.73 | R24: =IFERROR(__xludf.DUMMYFUNCTION("""COMPUTED_VALUE"""),52.44) -> 52.44 | S24: =IFERROR(__xludf.DUMMYFUNCTION("""COMPUTED_VALUE"""),158.0) -> 158 | T24: =IFERROR(__xludf.DUMMYFUNCTION("""COMPUTED_VALUE"""),154.22) -> 154.22 | U24: =IFERROR(__xludf.DUMMYFUNCTION("""COMPUTED_VALUE"""),336.05) -> 336.05 | V24: =IFERROR(__xludf.DUMMYFUNCTION("""COMPUTED_VALUE"""),35.16) -> 35.16 | W24: =IFERROR(__xludf.DUMMYFUNCTION("""COMPUTED_VALUE"""),62.88) -> 62.88 | X24: =IFERROR(__xludf.DUMMYFUNCTION("""COMPUTED_VALUE"""),91.14) -> 91.14 | Y24: =IFERROR(__xludf.DUMMYFUNCTION("""COMPUTED_VALUE"""),149.59) -> 149.59 | Z24: =IFERROR(__xludf.DUMMYFUNCTION("""COMPUTED_VALUE"""),108.87) -> 108.87 | AA24: =IFERROR(__xludf.DUMMYFUNCTION("""COMPUTED_VALUE"""),531.4) -> 531.4 | AB24: =IFERROR(__xludf.DUMMYFUNCTION("""COMPUTED_VALUE"""),53.19) -> 53.19 | AC24: =IFERROR(__xludf.DUMMYFUNCTION("""COMPUTED_VALUE"""),110.93) -> 110.93 | AD24: =IFERROR(__xludf.DUMMYFUNCTION("""COMPUTED_VALUE"""),248.6) -> 248.6 | AE24: =IFERROR(__xludf.DUMMYFUNCTION("""COMPUTED_VALUE"""),427.36) -> 427.36 | AF24: =IFERROR(__xludf.DUMMYFUNCTION("""COMPUTED_VALUE"""),294.34) -> 294.34 | AG24: =IFERROR(__xludf.DUMMYFUNCTION("""COMPUTED_VALUE"""),48.86) -> 48.86 | AH24: =IFERROR(__xludf.DUMMYFUNCTION("""COMPUTED_VALUE"""),64.34) -> 64.34 | AI24: =IFERROR(__xludf.DUMMYFUNCTION("""COMPUTED_VALUE"""),448.7) -> 448.7 | AJ24: =IFERROR(__xludf.DUMMYFUNCTION("""COMPUTED_VALUE"""),344.14) -> 344.14 | AK24: =IFERROR(__xludf.DUMMYFUNCTION("""COMPUTED_VALUE"""),97.44) -> 97.44 | AL24: =IFERROR(__xludf.DUMMYFUNCTION("""COMPUTED_VALUE"""),136.05) -> 136.05 | AM24: =IFERROR(__xludf.DUMMYFUNCTION("""COMPUTED_VALUE"""),428.1) -> 428.1 | AN24: =IFERROR(__xludf.DUMMYFUNCTION("""COMPUTED_VALUE"""),191.53) -> 191.53 | AO24: =IFERROR(__xludf.DUMMYFUNCTION("""COMPUTED_VALUE"""),459.11) -> 459.11 | AP24: =IFERROR(__xludf.DUMMYFUNCTION("""COMPUTED_VALUE"""),309.81) -> 309.81 | AQ24: =IFERROR(__xludf.DUMMYFUNCTION("""COMPUTED_VALUE"""),25.8) -> 25.8 | AR24: =IFERROR(__xludf.DUMMYFUNCTION("""COMPUTED_VALUE"""),82.23) -> 82.23 | AS24: =IFERROR(__xludf.DUMMYFUNCTION("""COMPUTED_VALUE"""),69.02) -> 69.02 | AT24: =IFERROR(__xludf.DUMMYFUNCTION("""COMPUTED_VALUE"""),441.06) -> 441.06 | AU24: =IFERROR(__xludf.DUMMYFUNCTION("""COMPUTED_VALUE"""),72.26) -> 72.26 | AV24: =IFERROR(__xludf.DUMMYFUNCTION("""COMPUTED_VALUE"""),125.2) -> 125.2 | AW24: =IFERROR(__xludf.DUMMYFUNCTION("""COMPUTED_VALUE"""),97.45) -> 97.45 | AX24: =IFERROR(__xludf.DUMMYFUNCTION("""COMPUTED_VALUE"""),43.63) -> 43.63 | AY24: =IFERROR(__xludf.DUMMYFUNCTION("""COMPUTED_VALUE"""),23.77) -> 23.77 | AZ24: =IFERROR(__xludf.DUMMYFUNCTION("""COMPUTED_VALUE"""),63.43) -> 63.43 | BA24: =IFERROR(__xludf.DUMMYFUNCTION("""COMPUTED_VALUE"""),27.66) -> 27.66 | BB24: =IFERROR(__xludf.DUMMYFUNCTION("""COMPUTED_VALUE"""),106.77) -> 106.77 | BC24: =IFERROR(__xludf.DUMMYFUNCTION("""COMPUTED_VALUE"""),173.79) -> 173.79 | BD24: =IFERROR(__xludf.DUMMYFUNCTION("""COMPUTED_VALUE"""),575.69) -> 575.69 | BE24: =IFERROR(__xludf.DUMMYFUNCTION("""COMPUTED_VALUE"""),205.65) -> 205.65 | BF24: =IFERROR(__xludf.DUMMYFUNCTION("""COMPUTED_VALUE"""),141.88) -> 141.88 | BG24: =IFERROR(__xludf.DUMMYFUNCTION("""COMPUTED_VALUE"""),6.78) -> 6.78 | BH24: =IFERROR(__xludf.DUMMYFUNCTION("""COMPUTED_VALUE"""),226.47) -> 226.47 | BI24: =IFERROR(__xludf.DUMMYFUNCTION("""COMPUTED_VALUE"""),493.07) -> 493.07 | BJ24: =IFERROR(__xludf.DUMMYFUNCTION("""COMPUTED_VALUE"""),48.27) -> 48.27 | BK24: =IFERROR(__xludf.DUMMYFUNCTION("""COMPUTED_VALUE"""),10.63) -> 10.63 | BL24: =IFERROR(__xludf.DUMMYFUNCTION("""COMPUTED_VALUE"""),200.87) -> 200.87 | BM24: =IFERROR(__xludf.DUMMYFUNCTION("""COMPUTED_VALUE"""),100.8) -> 100.8
A25: 45456.667 | B25: =IFERROR(__xludf.DUMMYFUNCTION("""COMPUTED_VALUE"""),5433.74) -> 5433.74 | C25: =IFERROR(__xludf.DUMMYFUNCTION("""COMPUTED_VALUE"""),17667.56) -> 17667.56 | D25: =IFERROR(__xludf.DUMMYFUNCTION("""COMPUTED_VALUE"""),38647.1) -> 38647.1 | E25: =IFERROR(__xludf.DUMMYFUNCTION("""COMPUTED_VALUE"""),2038.91) -> 2038.91 | F25: =IFERROR(__xludf.DUMMYFUNCTION("""COMPUTED_VALUE"""),458.74) -> 458.74 | G25: =IFERROR(__xludf.DUMMYFUNCTION("""COMPUTED_VALUE"""),183.83) -> 183.83 | H25: =IFERROR(__xludf.DUMMYFUNCTION("""COMPUTED_VALUE"""),129.22) -> 129.22 | I25: =IFERROR(__xludf.DUMMYFUNCTION("""COMPUTED_VALUE"""),214.24) -> 214.24 | J25: =IFERROR(__xludf.DUMMYFUNCTION("""COMPUTED_VALUE"""),237.55) -> 237.55 | K25: =IFERROR(__xludf.DUMMYFUNCTION("""COMPUTED_VALUE"""),58.5) -> 58.5 | L25: =IFERROR(__xludf.DUMMYFUNCTION("""COMPUTED_VALUE"""),10.6) -> 10.6 | M25: =IFERROR(__xludf.DUMMYFUNCTION("""COMPUTED_VALUE"""),405.92) -> 405.92 | N25: =IFERROR(__xludf.DUMMYFUNCTION("""COMPUTED_VALUE"""),57.35) -> 57.35 | O25: =IFERROR(__xludf.DUMMYFUNCTION("""COMPUTED_VALUE"""),233.84) -> 233.84 | P25: =IFERROR(__xludf.DUMMYFUNCTION("""COMPUTED_VALUE"""),63.99) -> 63.99 | Q25: =IFERROR(__xludf.DUMMYFUNCTION("""COMPUTED_VALUE"""),326.36) -> 326.36 | R25: =IFERROR(__xludf.DUMMYFUNCTION("""COMPUTED_VALUE"""),52.92) -> 52.92 | S25: =IFERROR(__xludf.DUMMYFUNCTION("""COMPUTED_VALUE"""),157.56) -> 157.56 | T25: =IFERROR(__xludf.DUMMYFUNCTION("""COMPUTED_VALUE"""),152.84) -> 152.84 | U25: =IFERROR(__xludf.DUMMYFUNCTION("""COMPUTED_VALUE"""),334.15) -> 334.15 | V25: =IFERROR(__xludf.DUMMYFUNCTION("""COMPUTED_VALUE"""),34.49) -> 34.49 | W25: =IFERROR(__xludf.DUMMYFUNCTION("""COMPUTED_VALUE"""),62.99) -> 62.99 | X25: =IFERROR(__xludf.DUMMYFUNCTION("""COMPUTED_VALUE"""),90.61) -> 90.61 | Y25: =IFERROR(__xludf.DUMMYFUNCTION("""COMPUTED_VALUE"""),149.76) -> 149.76 | Z25: =IFERROR(__xludf.DUMMYFUNCTION("""COMPUTED_VALUE"""),106.53) -> 106.53 | AA25: =IFERROR(__xludf.DUMMYFUNCTION("""COMPUTED_VALUE"""),528.75) -> 528.75 | AB25: =IFERROR(__xludf.DUMMYFUNCTION("""COMPUTED_VALUE"""),53.69) -> 53.69 | AC25: =IFERROR(__xludf.DUMMYFUNCTION("""COMPUTED_VALUE"""),110.04) -> 110.04 | AD25: =IFERROR(__xludf.DUMMYFUNCTION("""COMPUTED_VALUE"""),248.6) -> 248.6 | AE25: =IFERROR(__xludf.DUMMYFUNCTION("""COMPUTED_VALUE"""),416.68) -> 416.68 | AF25: =IFERROR(__xludf.DUMMYFUNCTION("""COMPUTED_VALUE"""),292.52) -> 292.52 | AG25: =IFERROR(__xludf.DUMMYFUNCTION("""COMPUTED_VALUE"""),47.65) -> 47.65 | AH25: =IFERROR(__xludf.DUMMYFUNCTION("""COMPUTED_VALUE"""),63.56) -> 63.56 | AI25: =IFERROR(__xludf.DUMMYFUNCTION("""COMPUTED_VALUE"""),446.35) -> 446.35 | AJ25: =IFERROR(__xludf.DUMMYFUNCTION("""COMPUTED_VALUE"""),347.88) -> 347.88 | AK25: =IFERROR(__xludf.DUMMYFUNCTION("""COMPUTED_VALUE"""),96.17) -> 96.17 | AL25: =IFERROR(__xludf.DUMMYFUNCTION("""COMPUTED_VALUE"""),135.26) -> 135.26 | AM25: =IFERROR(__xludf.DUMMYFUNCTION("""COMPUTED_VALUE"""),422.9) -> 422.9 | AN25: =IFERROR(__xludf.DUMMYFUNCTION("""COMPUTED_VALUE"""),193.66) -> 193.66 | AO25: =IFERROR(__xludf.DUMMYFUNCTION("""COMPUTED_VALUE"""),458.56) -> 458.56 | AP25: =IFERROR(__xludf.DUMMYFUNCTION("""COMPUTED_VALUE"""),307.49) -> 307.49 | AQ25: =IFERROR(__xludf.DUMMYFUNCTION("""COMPUTED_VALUE"""),25.18) -> 25.18 | AR25: =IFERROR(__xludf.DUMMYFUNCTION("""COMPUTED_VALUE"""),81.66) -> 81.66 | AS25: =IFERROR(__xludf.DUMMYFUNCTION("""COMPUTED_VALUE"""),68.66) -> 68.66 | AT25: =IFERROR(__xludf.DUMMYFUNCTION("""COMPUTED_VALUE"""),441.58) -> 441.58 | AU25: =IFERROR(__xludf.DUMMYFUNCTION("""COMPUTED_VALUE"""),73.18) -> 73.18 | AV25: =IFERROR(__xludf.DUMMYFUNCTION("""COMPUTED_VALUE"""),129.61) -> 129.61 | AW25: =IFERROR(__xludf.DUMMYFUNCTION("""COMPUTED_VALUE"""),97.44) -> 97.44 | AX25: =IFERROR(__xludf.DUMMYFUNCTION("""COMPUTED_VALUE"""),42.9) -> 42.9 | AY25: =IFERROR(__xludf.DUMMYFUNCTION("""COMPUTED_VALUE"""),23.27) -> 23.27 | AZ25: =IFERROR(__xludf.DUMMYFUNCTION("""COMPUTED_VALUE"""),61.54) -> 61.54 | BA25: =IFERROR(__xludf.DUMMYFUNCTION("""COMPUTED_VALUE"""),27.65) -> 27.65 | BB25: =IFERROR(__xludf.DUMMYFUNCTION("""COMPUTED_VALUE"""),105.03) -> 105.03 | BC25: =IFERROR(__xludf.DUMMYFUNCTION("""COMPUTED_VALUE"""),175.11) -> 175.11 | BD25: =IFERROR(__xludf.DUMMYFUNCTION("""COMPUTED_VALUE"""),572.63) -> 572.63 | BE25: =IFERROR(__xludf.DUMMYFUNCTION("""COMPUTED_VALUE"""),199.35) -> 199.35 | BF25: =IFERROR(__xludf.DUMMYFUNCTION("""COMPUTED_VALUE"""),143.4) -> 143.4 | BG25: =IFERROR(__xludf.DUMMYFUNCTION("""COMPUTED_VALUE"""),6.76) -> 6.76 | BH25: =IFERROR(__xludf.DUMMYFUNCTION("""COMPUTED_VALUE"""),222.12) -> 222.12 | BI25: =IFERROR(__xludf.DUMMYFUNCTION("""COMPUTED_VALUE"""),497.3) -> 497.3 | BJ25: =IFERROR(__xludf.DUMMYFUNCTION("""COMPUTED_VALUE"""),48.35) -> 48.35 | BK25: =IFERROR(__xludf.DUMMYFUNCTION("""COMPUTED_VALUE"""),10.39) -> 10.39 | BL25: =IFERROR(__xludf.DUMMYFUNCTION("""COMPUTED_VALUE"""),201.22) -> 201.22 | BM25: =IFERROR(__xludf.DUMMYFUNCTION("""COMPUTED_VALUE"""),100.09) -> 100.09
A26: 45457.667 | B26: =IFERROR(__xludf.DUMMYFUNCTION("""COMPUTED_VALUE"""),5431.6) -> 5431.6 | C26: =IFERROR(__xludf.DUMMYFUNCTION("""COMPUTED_VALUE"""),17688.88) -> 17688.88 | D26: =IFERROR(__xludf.DUMMYFUNCTION("""COMPUTED_VALUE"""),38589.16) -> 38589.16 | E26: =IFERROR(__xludf.DUMMYFUNCTION("""COMPUTED_VALUE"""),2006.16) -> 2006.16 | F26: =IFERROR(__xludf.DUMMYFUNCTION("""COMPUTED_VALUE"""),525.31) -> 525.31 | G26: =IFERROR(__xludf.DUMMYFUNCTION("""COMPUTED_VALUE"""),183.66) -> 183.66 | H26: =IFERROR(__xludf.DUMMYFUNCTION("""COMPUTED_VALUE"""),129.3) -> 129.3 | I26: =IFERROR(__xludf.DUMMYFUNCTION("""COMPUTED_VALUE"""),212.49) -> 212.49 | J26: =IFERROR(__xludf.DUMMYFUNCTION("""COMPUTED_VALUE"""),237.03) -> 237.03 | K26: =IFERROR(__xludf.DUMMYFUNCTION("""COMPUTED_VALUE"""),58.02) -> 58.02 | L26: =IFERROR(__xludf.DUMMYFUNCTION("""COMPUTED_VALUE"""),10.41) -> 10.41 | M26: =IFERROR(__xludf.DUMMYFUNCTION("""COMPUTED_VALUE"""),405.54) -> 405.54 | N26: =IFERROR(__xludf.DUMMYFUNCTION("""COMPUTED_VALUE"""),56.83) -> 56.83 | O26: =IFERROR(__xludf.DUMMYFUNCTION("""COMPUTED_VALUE"""),231.69) -> 231.69 | P26: =IFERROR(__xludf.DUMMYFUNCTION("""COMPUTED_VALUE"""),64.35) -> 64.35 | Q26: =IFERROR(__xludf.DUMMYFUNCTION("""COMPUTED_VALUE"""),321.47) -> 321.47 | R26: =IFERROR(__xludf.DUMMYFUNCTION("""COMPUTED_VALUE"""),51.9) -> 51.9 | S26: =IFERROR(__xludf.DUMMYFUNCTION("""COMPUTED_VALUE"""),156.49) -> 156.49 | T26: =IFERROR(__xludf.DUMMYFUNCTION("""COMPUTED_VALUE"""),152.57) -> 152.57 | U26: =IFERROR(__xludf.DUMMYFUNCTION("""COMPUTED_VALUE"""),333.29) -> 333.29 | V26: =IFERROR(__xludf.DUMMYFUNCTION("""COMPUTED_VALUE"""),34.07) -> 34.07 | W26: =IFERROR(__xludf.DUMMYFUNCTION("""COMPUTED_VALUE"""),62.55) -> 62.55 | X26: =IFERROR(__xludf.DUMMYFUNCTION("""COMPUTED_VALUE"""),90.87) -> 90.87 | Y26: =IFERROR(__xludf.DUMMYFUNCTION("""COMPUTED_VALUE"""),149.92) -> 149.92 | Z26: =IFERROR(__xludf.DUMMYFUNCTION("""COMPUTED_VALUE"""),106.03) -> 106.03 | AA26: =IFERROR(__xludf.DUMMYFUNCTION("""COMPUTED_VALUE"""),521.41) -> 521.41 | AB26: =IFERROR(__xludf.DUMMYFUNCTION("""COMPUTED_VALUE"""),52.13) -> 52.13 | AC26: =IFERROR(__xludf.DUMMYFUNCTION("""COMPUTED_VALUE"""),109.11) -> 109.11 | AD26: =IFERROR(__xludf.DUMMYFUNCTION("""COMPUTED_VALUE"""),246.43) -> 246.43 | AE26: =IFERROR(__xludf.DUMMYFUNCTION("""COMPUTED_VALUE"""),409.98) -> 409.98 | AF26: =IFERROR(__xludf.DUMMYFUNCTION("""COMPUTED_VALUE"""),291.78) -> 291.78 | AG26: =IFERROR(__xludf.DUMMYFUNCTION("""COMPUTED_VALUE"""),46.77) -> 46.77 | AH26: =IFERROR(__xludf.DUMMYFUNCTION("""COMPUTED_VALUE"""),65.06) -> 65.06 | AI26: =IFERROR(__xludf.DUMMYFUNCTION("""COMPUTED_VALUE"""),446.46) -> 446.46 | AJ26: =IFERROR(__xludf.DUMMYFUNCTION("""COMPUTED_VALUE"""),346.84) -> 346.84 | AK26: =IFERROR(__xludf.DUMMYFUNCTION("""COMPUTED_VALUE"""),94.95) -> 94.95 | AL26: =IFERROR(__xludf.DUMMYFUNCTION("""COMPUTED_VALUE"""),135.67) -> 135.67 | AM26: =IFERROR(__xludf.DUMMYFUNCTION("""COMPUTED_VALUE"""),425.78) -> 425.78 | AN26: =IFERROR(__xludf.DUMMYFUNCTION("""COMPUTED_VALUE"""),193.78) -> 193.78 | AO26: =IFERROR(__xludf.DUMMYFUNCTION("""COMPUTED_VALUE"""),458.34) -> 458.34 | AP26: =IFERROR(__xludf.DUMMYFUNCTION("""COMPUTED_VALUE"""),306.01) -> 306.01 | AQ26: =IFERROR(__xludf.DUMMYFUNCTION("""COMPUTED_VALUE"""),25.1) -> 25.1 | AR26: =IFERROR(__xludf.DUMMYFUNCTION("""COMPUTED_VALUE"""),81.04) -> 81.04 | AS26: =IFERROR(__xludf.DUMMYFUNCTION("""COMPUTED_VALUE"""),68.55) -> 68.55 | AT26: =IFERROR(__xludf.DUMMYFUNCTION("""COMPUTED_VALUE"""),442.57) -> 442.57 | AU26: =IFERROR(__xludf.DUMMYFUNCTION("""COMPUTED_VALUE"""),73.06) -> 73.06 | AV26: =IFERROR(__xludf.DUMMYFUNCTION("""COMPUTED_VALUE"""),131.88) -> 131.88 | AW26: =IFERROR(__xludf.DUMMYFUNCTION("""COMPUTED_VALUE"""),97.13) -> 97.13 | AX26: =IFERROR(__xludf.DUMMYFUNCTION("""COMPUTED_VALUE"""),42.0) -> 42 | AY26: =IFERROR(__xludf.DUMMYFUNCTION("""COMPUTED_VALUE"""),23.57) -> 23.57 | AZ26: =IFERROR(__xludf.DUMMYFUNCTION("""COMPUTED_VALUE"""),60.64) -> 60.64 | BA26: =IFERROR(__xludf.DUMMYFUNCTION("""COMPUTED_VALUE"""),27.53) -> 27.53 | BB26: =IFERROR(__xludf.DUMMYFUNCTION("""COMPUTED_VALUE"""),104.23) -> 104.23 | BC26: =IFERROR(__xludf.DUMMYFUNCTION("""COMPUTED_VALUE"""),175.99) -> 175.99 | BD26: =IFERROR(__xludf.DUMMYFUNCTION("""COMPUTED_VALUE"""),572.05) -> 572.05 | BE26: =IFERROR(__xludf.DUMMYFUNCTION("""COMPUTED_VALUE"""),197.13) -> 197.13 | BF26: =IFERROR(__xludf.DUMMYFUNCTION("""COMPUTED_VALUE"""),142.01) -> 142.01 | BG26: =IFERROR(__xludf.DUMMYFUNCTION("""COMPUTED_VALUE"""),6.68) -> 6.68 | BH26: =IFERROR(__xludf.DUMMYFUNCTION("""COMPUTED_VALUE"""),222.1) -> 222.1 | BI26: =IFERROR(__xludf.DUMMYFUNCTION("""COMPUTED_VALUE"""),497.12) -> 497.12 | BJ26: =IFERROR(__xludf.DUMMYFUNCTION("""COMPUTED_VALUE"""),48.35) -> 48.35 | BK26: =IFERROR(__xludf.DUMMYFUNCTION("""COMPUTED_VALUE"""),10.17) -> 10.17 | BL26: =IFERROR(__xludf.DUMMYFUNCTION("""COMPUTED_VALUE"""),203.64) -> 203.64 | BM26: =IFERROR(__xludf.DUMMYFUNCTION("""COMPUTED_VALUE"""),99.97) -> 99.97
A27: 45460.667 | B27: =IFERROR(__xludf.DUMMYFUNCTION("""COMPUTED_VALUE"""),5473.23) -> 5473.23 | C27: =IFERROR(__xludf.DUMMYFUNCTION("""COMPUTED_VALUE"""),17857.02) -> 17857.02 | D27: =IFERROR(__xludf.DUMMYFUNCTION("""COMPUTED_VALUE"""),38778.1) -> 38778.1 | E27: =IFERROR(__xludf.DUMMYFUNCTION("""COMPUTED_VALUE"""),2022.01) -> 2022.01 | F27: =IFERROR(__xludf.DUMMYFUNCTION("""COMPUTED_VALUE"""),518.74) -> 518.74 | G27: =IFERROR(__xludf.DUMMYFUNCTION("""COMPUTED_VALUE"""),184.06) -> 184.06 | H27: =IFERROR(__xludf.DUMMYFUNCTION("""COMPUTED_VALUE"""),128.72) -> 128.72 | I27: =IFERROR(__xludf.DUMMYFUNCTION("""COMPUTED_VALUE"""),216.67) -> 216.67 | J27: =IFERROR(__xludf.DUMMYFUNCTION("""COMPUTED_VALUE"""),242.86) -> 242.86 | K27: =IFERROR(__xludf.DUMMYFUNCTION("""COMPUTED_VALUE"""),58.17) -> 58.17 | L27: =IFERROR(__xludf.DUMMYFUNCTION("""COMPUTED_VALUE"""),10.59) -> 10.59 | M27: =IFERROR(__xludf.DUMMYFUNCTION("""COMPUTED_VALUE"""),407.32) -> 407.32 | N27: =IFERROR(__xludf.DUMMYFUNCTION("""COMPUTED_VALUE"""),56.25) -> 56.25 | O27: =IFERROR(__xludf.DUMMYFUNCTION("""COMPUTED_VALUE"""),226.46) -> 226.46 | P27: =IFERROR(__xludf.DUMMYFUNCTION("""COMPUTED_VALUE"""),65.12) -> 65.12 | Q27: =IFERROR(__xludf.DUMMYFUNCTION("""COMPUTED_VALUE"""),322.4) -> 322.4 | R27: =IFERROR(__xludf.DUMMYFUNCTION("""COMPUTED_VALUE"""),51.29) -> 51.29 | S27: =IFERROR(__xludf.DUMMYFUNCTION("""COMPUTED_VALUE"""),157.63) -> 157.63 | T27: =IFERROR(__xludf.DUMMYFUNCTION("""COMPUTED_VALUE"""),153.19) -> 153.19 | U27: =IFERROR(__xludf.DUMMYFUNCTION("""COMPUTED_VALUE"""),333.9) -> 333.9 | V27: =IFERROR(__xludf.DUMMYFUNCTION("""COMPUTED_VALUE"""),34.5) -> 34.5 | W27: =IFERROR(__xludf.DUMMYFUNCTION("""COMPUTED_VALUE"""),62.62) -> 62.62 | X27: =IFERROR(__xludf.DUMMYFUNCTION("""COMPUTED_VALUE"""),90.65) -> 90.65 | Y27: =IFERROR(__xludf.DUMMYFUNCTION("""COMPUTED_VALUE"""),149.01) -> 149.01 | Z27: =IFERROR(__xludf.DUMMYFUNCTION("""COMPUTED_VALUE"""),108.65) -> 108.65 | AA27: =IFERROR(__xludf.DUMMYFUNCTION("""COMPUTED_VALUE"""),532.16) -> 532.16 | AB27: =IFERROR(__xludf.DUMMYFUNCTION("""COMPUTED_VALUE"""),53.14) -> 53.14 | AC27: =IFERROR(__xludf.DUMMYFUNCTION("""COMPUTED_VALUE"""),108.36) -> 108.36 | AD27: =IFERROR(__xludf.DUMMYFUNCTION("""COMPUTED_VALUE"""),250.06) -> 250.06 | AE27: =IFERROR(__xludf.DUMMYFUNCTION("""COMPUTED_VALUE"""),416.06) -> 416.06 | AF27: =IFERROR(__xludf.DUMMYFUNCTION("""COMPUTED_VALUE"""),293.83) -> 293.83 | AG27: =IFERROR(__xludf.DUMMYFUNCTION("""COMPUTED_VALUE"""),47.4) -> 47.4 | AH27: =IFERROR(__xludf.DUMMYFUNCTION("""COMPUTED_VALUE"""),64.27) -> 64.27 | AI27: =IFERROR(__xludf.DUMMYFUNCTION("""COMPUTED_VALUE"""),450.18) -> 450.18 | AJ27: =IFERROR(__xludf.DUMMYFUNCTION("""COMPUTED_VALUE"""),349.5) -> 349.5 | AK27: =IFERROR(__xludf.DUMMYFUNCTION("""COMPUTED_VALUE"""),96.74) -> 96.74 | AL27: =IFERROR(__xludf.DUMMYFUNCTION("""COMPUTED_VALUE"""),136.2) -> 136.2 | AM27: =IFERROR(__xludf.DUMMYFUNCTION("""COMPUTED_VALUE"""),430.0) -> 430 | AN27: =IFERROR(__xludf.DUMMYFUNCTION("""COMPUTED_VALUE"""),194.98) -> 194.98 | AO27: =IFERROR(__xludf.DUMMYFUNCTION("""COMPUTED_VALUE"""),459.01) -> 459.01 | AP27: =IFERROR(__xludf.DUMMYFUNCTION("""COMPUTED_VALUE"""),312.91) -> 312.91 | AQ27: =IFERROR(__xludf.DUMMYFUNCTION("""COMPUTED_VALUE"""),25.49) -> 25.49 | AR27: =IFERROR(__xludf.DUMMYFUNCTION("""COMPUTED_VALUE"""),79.95) -> 79.95 | AS27: =IFERROR(__xludf.DUMMYFUNCTION("""COMPUTED_VALUE"""),69.38) -> 69.38 | AT27: =IFERROR(__xludf.DUMMYFUNCTION("""COMPUTED_VALUE"""),448.37) -> 448.37 | AU27: =IFERROR(__xludf.DUMMYFUNCTION("""COMPUTED_VALUE"""),72.31) -> 72.31 | AV27: =IFERROR(__xludf.DUMMYFUNCTION("""COMPUTED_VALUE"""),130.98) -> 130.98 | AW27: =IFERROR(__xludf.DUMMYFUNCTION("""COMPUTED_VALUE"""),97.47) -> 97.47 | AX27: =IFERROR(__xludf.DUMMYFUNCTION("""COMPUTED_VALUE"""),41.63) -> 41.63 | AY27: =IFERROR(__xludf.DUMMYFUNCTION("""COMPUTED_VALUE"""),25.02) -> 25.02 | AZ27: =IFERROR(__xludf.DUMMYFUNCTION("""COMPUTED_VALUE"""),60.13) -> 60.13 | BA27: =IFERROR(__xludf.DUMMYFUNCTION("""COMPUTED_VALUE"""),26.98) -> 26.98 | BB27: =IFERROR(__xludf.DUMMYFUNCTION("""COMPUTED_VALUE"""),104.47) -> 104.47 | BC27: =IFERROR(__xludf.DUMMYFUNCTION("""COMPUTED_VALUE"""),177.38) -> 177.38 | BD27: =IFERROR(__xludf.DUMMYFUNCTION("""COMPUTED_VALUE"""),568.0) -> 568 | BE27: =IFERROR(__xludf.DUMMYFUNCTION("""COMPUTED_VALUE"""),195.2) -> 195.2 | BF27: =IFERROR(__xludf.DUMMYFUNCTION("""COMPUTED_VALUE"""),143.07) -> 143.07 | BG27: =IFERROR(__xludf.DUMMYFUNCTION("""COMPUTED_VALUE"""),6.94) -> 6.94 | BH27: =IFERROR(__xludf.DUMMYFUNCTION("""COMPUTED_VALUE"""),221.38) -> 221.38 | BI27: =IFERROR(__xludf.DUMMYFUNCTION("""COMPUTED_VALUE"""),489.23) -> 489.23 | BJ27: =IFERROR(__xludf.DUMMYFUNCTION("""COMPUTED_VALUE"""),48.34) -> 48.34 | BK27: =IFERROR(__xludf.DUMMYFUNCTION("""COMPUTED_VALUE"""),10.11) -> 10.11 | BL27: =IFERROR(__xludf.DUMMYFUNCTION("""COMPUTED_VALUE"""),206.38) -> 206.38 | BM27: =IFERROR(__xludf.DUMMYFUNCTION("""COMPUTED_VALUE"""),101.52) -> 101.52
A28: 45461.667 | B28: =IFERROR(__xludf.DUMMYFUNCTION("""COMPUTED_VALUE"""),5487.03) -> 5487.03 | C28: =IFERROR(__xludf.DUMMYFUNCTION("""COMPUTED_VALUE"""),17862.23) -> 17862.23 | D28: =IFERROR(__xludf.DUMMYFUNCTION("""COMPUTED_VALUE"""),38834.86) -> 38834.86 | E28: =IFERROR(__xludf.DUMMYFUNCTION("""COMPUTED_VALUE"""),2025.23) -> 2025.23 | F28: =IFERROR(__xludf.DUMMYFUNCTION("""COMPUTED_VALUE"""),522.25) -> 522.25 | G28: =IFERROR(__xludf.DUMMYFUNCTION("""COMPUTED_VALUE"""),182.81) -> 182.81 | H28: =IFERROR(__xludf.DUMMYFUNCTION("""COMPUTED_VALUE"""),130.47) -> 130.47 | I28: =IFERROR(__xludf.DUMMYFUNCTION("""COMPUTED_VALUE"""),214.29) -> 214.29 | J28: =IFERROR(__xludf.DUMMYFUNCTION("""COMPUTED_VALUE"""),247.83) -> 247.83 | K28: =IFERROR(__xludf.DUMMYFUNCTION("""COMPUTED_VALUE"""),58.68) -> 58.68 | L28: =IFERROR(__xludf.DUMMYFUNCTION("""COMPUTED_VALUE"""),10.56) -> 10.56 | M28: =IFERROR(__xludf.DUMMYFUNCTION("""COMPUTED_VALUE"""),407.95) -> 407.95 | N28: =IFERROR(__xludf.DUMMYFUNCTION("""COMPUTED_VALUE"""),56.66) -> 56.66 | O28: =IFERROR(__xludf.DUMMYFUNCTION("""COMPUTED_VALUE"""),223.65) -> 223.65 | P28: =IFERROR(__xludf.DUMMYFUNCTION("""COMPUTED_VALUE"""),65.72) -> 65.72 | Q28: =IFERROR(__xludf.DUMMYFUNCTION("""COMPUTED_VALUE"""),325.14) -> 325.14 | R28: =IFERROR(__xludf.DUMMYFUNCTION("""COMPUTED_VALUE"""),52.4) -> 52.4 | S28: =IFERROR(__xludf.DUMMYFUNCTION("""COMPUTED_VALUE"""),159.12) -> 159.12 | T28: =IFERROR(__xludf.DUMMYFUNCTION("""COMPUTED_VALUE"""),153.33) -> 153.33 | U28: =IFERROR(__xludf.DUMMYFUNCTION("""COMPUTED_VALUE"""),334.8) -> 334.8 | V28: =IFERROR(__xludf.DUMMYFUNCTION("""COMPUTED_VALUE"""),34.77) -> 34.77 | W28: =IFERROR(__xludf.DUMMYFUNCTION("""COMPUTED_VALUE"""),62.63) -> 62.63 | X28: =IFERROR(__xludf.DUMMYFUNCTION("""COMPUTED_VALUE"""),90.39) -> 90.39 | Y28: =IFERROR(__xludf.DUMMYFUNCTION("""COMPUTED_VALUE"""),149.56) -> 149.56 | Z28: =IFERROR(__xludf.DUMMYFUNCTION("""COMPUTED_VALUE"""),107.24) -> 107.24 | AA28: =IFERROR(__xludf.DUMMYFUNCTION("""COMPUTED_VALUE"""),533.64) -> 533.64 | AB28: =IFERROR(__xludf.DUMMYFUNCTION("""COMPUTED_VALUE"""),54.55) -> 54.55 | AC28: =IFERROR(__xludf.DUMMYFUNCTION("""COMPUTED_VALUE"""),109.38) -> 109.38 | AD28: =IFERROR(__xludf.DUMMYFUNCTION("""COMPUTED_VALUE"""),248.09) -> 248.09 | AE28: =IFERROR(__xludf.DUMMYFUNCTION("""COMPUTED_VALUE"""),414.36) -> 414.36 | AF28: =IFERROR(__xludf.DUMMYFUNCTION("""COMPUTED_VALUE"""),298.0) -> 298 | AG28: =IFERROR(__xludf.DUMMYFUNCTION("""COMPUTED_VALUE"""),47.44) -> 47.44 | AH28: =IFERROR(__xludf.DUMMYFUNCTION("""COMPUTED_VALUE"""),63.15) -> 63.15 | AI28: =IFERROR(__xludf.DUMMYFUNCTION("""COMPUTED_VALUE"""),457.43) -> 457.43 | AJ28: =IFERROR(__xludf.DUMMYFUNCTION("""COMPUTED_VALUE"""),353.87) -> 353.87 | AK28: =IFERROR(__xludf.DUMMYFUNCTION("""COMPUTED_VALUE"""),96.75) -> 96.75 | AL28: =IFERROR(__xludf.DUMMYFUNCTION("""COMPUTED_VALUE"""),136.38) -> 136.38 | AM28: =IFERROR(__xludf.DUMMYFUNCTION("""COMPUTED_VALUE"""),435.0) -> 435 | AN28: =IFERROR(__xludf.DUMMYFUNCTION("""COMPUTED_VALUE"""),197.0) -> 197 | AO28: =IFERROR(__xludf.DUMMYFUNCTION("""COMPUTED_VALUE"""),460.0) -> 460 | AP28: =IFERROR(__xludf.DUMMYFUNCTION("""COMPUTED_VALUE"""),313.23) -> 313.23 | AQ28: =IFERROR(__xludf.DUMMYFUNCTION("""COMPUTED_VALUE"""),25.55) -> 25.55 | AR28: =IFERROR(__xludf.DUMMYFUNCTION("""COMPUTED_VALUE"""),79.75) -> 79.75 | AS28: =IFERROR(__xludf.DUMMYFUNCTION("""COMPUTED_VALUE"""),69.86) -> 69.86 | AT28: =IFERROR(__xludf.DUMMYFUNCTION("""COMPUTED_VALUE"""),446.34) -> 446.34 | AU28: =IFERROR(__xludf.DUMMYFUNCTION("""COMPUTED_VALUE"""),70.44) -> 70.44 | AV28: =IFERROR(__xludf.DUMMYFUNCTION("""COMPUTED_VALUE"""),135.58) -> 135.58 | AW28: =IFERROR(__xludf.DUMMYFUNCTION("""COMPUTED_VALUE"""),96.5) -> 96.5 | AX28: =IFERROR(__xludf.DUMMYFUNCTION("""COMPUTED_VALUE"""),42.23) -> 42.23 | AY28: =IFERROR(__xludf.DUMMYFUNCTION("""COMPUTED_VALUE"""),25.82) -> 25.82 | AZ28: =IFERROR(__xludf.DUMMYFUNCTION("""COMPUTED_VALUE"""),59.12) -> 59.12 | BA28: =IFERROR(__xludf.DUMMYFUNCTION("""COMPUTED_VALUE"""),27.41) -> 27.41 | BB28: =IFERROR(__xludf.DUMMYFUNCTION("""COMPUTED_VALUE"""),104.77) -> 104.77 | BC28: =IFERROR(__xludf.DUMMYFUNCTION("""COMPUTED_VALUE"""),177.61) -> 177.61 | BD28: =IFERROR(__xludf.DUMMYFUNCTION("""COMPUTED_VALUE"""),569.17) -> 569.17 | BE28: =IFERROR(__xludf.DUMMYFUNCTION("""COMPUTED_VALUE"""),194.14) -> 194.14 | BF28: =IFERROR(__xludf.DUMMYFUNCTION("""COMPUTED_VALUE"""),145.96) -> 145.96 | BG28: =IFERROR(__xludf.DUMMYFUNCTION("""COMPUTED_VALUE"""),6.95) -> 6.95 | BH28: =IFERROR(__xludf.DUMMYFUNCTION("""COMPUTED_VALUE"""),222.58) -> 222.58 | BI28: =IFERROR(__xludf.DUMMYFUNCTION("""COMPUTED_VALUE"""),481.05) -> 481.05 | BJ28: =IFERROR(__xludf.DUMMYFUNCTION("""COMPUTED_VALUE"""),48.45) -> 48.45 | BK28: =IFERROR(__xludf.DUMMYFUNCTION("""COMPUTED_VALUE"""),10.05) -> 10.05 | BL28: =IFERROR(__xludf.DUMMYFUNCTION("""COMPUTED_VALUE"""),207.89) -> 207.89 | BM28: =IFERROR(__xludf.DUMMYFUNCTION("""COMPUTED_VALUE"""),101.5) -> 101.5
A29: 45463.667 | B29: =IFERROR(__xludf.DUMMYFUNCTION("""COMPUTED_VALUE"""),5473.17) -> 5473.17 | C29: =IFERROR(__xludf.DUMMYFUNCTION("""COMPUTED_VALUE"""),17721.59) -> 17721.59 | D29: =IFERROR(__xludf.DUMMYFUNCTION("""COMPUTED_VALUE"""),39134.76) -> 39134.76 | E29: =IFERROR(__xludf.DUMMYFUNCTION("""COMPUTED_VALUE"""),2017.39) -> 2017.39 | F29: =IFERROR(__xludf.DUMMYFUNCTION("""COMPUTED_VALUE"""),522.95) -> 522.95 | G29: =IFERROR(__xludf.DUMMYFUNCTION("""COMPUTED_VALUE"""),186.1) -> 186.1 | H29: =IFERROR(__xludf.DUMMYFUNCTION("""COMPUTED_VALUE"""),130.26) -> 130.26 | I29: =IFERROR(__xludf.DUMMYFUNCTION("""COMPUTED_VALUE"""),209.68) -> 209.68 | J29: =IFERROR(__xludf.DUMMYFUNCTION("""COMPUTED_VALUE"""),239.99) -> 239.99 | K29: =IFERROR(__xludf.DUMMYFUNCTION("""COMPUTED_VALUE"""),58.84) -> 58.84 | L29: =IFERROR(__xludf.DUMMYFUNCTION("""COMPUTED_VALUE"""),10.72) -> 10.72 | M29: =IFERROR(__xludf.DUMMYFUNCTION("""COMPUTED_VALUE"""),409.15) -> 409.15 | N29: =IFERROR(__xludf.DUMMYFUNCTION("""COMPUTED_VALUE"""),57.21) -> 57.21 | O29: =IFERROR(__xludf.DUMMYFUNCTION("""COMPUTED_VALUE"""),225.58) -> 225.58 | P29: =IFERROR(__xludf.DUMMYFUNCTION("""COMPUTED_VALUE"""),64.22) -> 64.22 | Q29: =IFERROR(__xludf.DUMMYFUNCTION("""COMPUTED_VALUE"""),329.13) -> 329.13 | R29: =IFERROR(__xludf.DUMMYFUNCTION("""COMPUTED_VALUE"""),52.22) -> 52.22 | S29: =IFERROR(__xludf.DUMMYFUNCTION("""COMPUTED_VALUE"""),158.72) -> 158.72 | T29: =IFERROR(__xludf.DUMMYFUNCTION("""COMPUTED_VALUE"""),156.64) -> 156.64 | U29: =IFERROR(__xludf.DUMMYFUNCTION("""COMPUTED_VALUE"""),337.88) -> 337.88 | V29: =IFERROR(__xludf.DUMMYFUNCTION("""COMPUTED_VALUE"""),34.68) -> 34.68 | W29: =IFERROR(__xludf.DUMMYFUNCTION("""COMPUTED_VALUE"""),62.18) -> 62.18 | X29: =IFERROR(__xludf.DUMMYFUNCTION("""COMPUTED_VALUE"""),90.53) -> 90.53 | Y29: =IFERROR(__xludf.DUMMYFUNCTION("""COMPUTED_VALUE"""),147.89) -> 147.89 | Z29: =IFERROR(__xludf.DUMMYFUNCTION("""COMPUTED_VALUE"""),107.58) -> 107.58 | AA29: =IFERROR(__xludf.DUMMYFUNCTION("""COMPUTED_VALUE"""),525.0) -> 525 | AB29: =IFERROR(__xludf.DUMMYFUNCTION("""COMPUTED_VALUE"""),53.84) -> 53.84 | AC29: =IFERROR(__xludf.DUMMYFUNCTION("""COMPUTED_VALUE"""),111.74) -> 111.74 | AD29: =IFERROR(__xludf.DUMMYFUNCTION("""COMPUTED_VALUE"""),252.52) -> 252.52 | AE29: =IFERROR(__xludf.DUMMYFUNCTION("""COMPUTED_VALUE"""),420.09) -> 420.09 | AF29: =IFERROR(__xludf.DUMMYFUNCTION("""COMPUTED_VALUE"""),299.63) -> 299.63 | AG29: =IFERROR(__xludf.DUMMYFUNCTION("""COMPUTED_VALUE"""),47.77) -> 47.77 | AH29: =IFERROR(__xludf.DUMMYFUNCTION("""COMPUTED_VALUE"""),68.49) -> 68.49 | AI29: =IFERROR(__xludf.DUMMYFUNCTION("""COMPUTED_VALUE"""),458.05) -> 458.05 | AJ29: =IFERROR(__xludf.DUMMYFUNCTION("""COMPUTED_VALUE"""),353.44) -> 353.44 | AK29: =IFERROR(__xludf.DUMMYFUNCTION("""COMPUTED_VALUE"""),97.03) -> 97.03 | AL29: =IFERROR(__xludf.DUMMYFUNCTION("""COMPUTED_VALUE"""),137.11) -> 137.11 | AM29: =IFERROR(__xludf.DUMMYFUNCTION("""COMPUTED_VALUE"""),432.55) -> 432.55 | AN29: =IFERROR(__xludf.DUMMYFUNCTION("""COMPUTED_VALUE"""),198.67) -> 198.67 | AO29: =IFERROR(__xludf.DUMMYFUNCTION("""COMPUTED_VALUE"""),466.34) -> 466.34 | AP29: =IFERROR(__xludf.DUMMYFUNCTION("""COMPUTED_VALUE"""),310.77) -> 310.77 | AQ29: =IFERROR(__xludf.DUMMYFUNCTION("""COMPUTED_VALUE"""),25.74) -> 25.74 | AR29: =IFERROR(__xludf.DUMMYFUNCTION("""COMPUTED_VALUE"""),80.17) -> 80.17 | AS29: =IFERROR(__xludf.DUMMYFUNCTION("""COMPUTED_VALUE"""),70.85) -> 70.85 | AT29: =IFERROR(__xludf.DUMMYFUNCTION("""COMPUTED_VALUE"""),445.7) -> 445.7 | AU29: =IFERROR(__xludf.DUMMYFUNCTION("""COMPUTED_VALUE"""),72.46) -> 72.46 | AV29: =IFERROR(__xludf.DUMMYFUNCTION("""COMPUTED_VALUE"""),130.78) -> 130.78 | AW29: =IFERROR(__xludf.DUMMYFUNCTION("""COMPUTED_VALUE"""),96.6) -> 96.6 | AX29: =IFERROR(__xludf.DUMMYFUNCTION("""COMPUTED_VALUE"""),41.73) -> 41.73 | AY29: =IFERROR(__xludf.DUMMYFUNCTION("""COMPUTED_VALUE"""),25.56) -> 25.56 | AZ29: =IFERROR(__xludf.DUMMYFUNCTION("""COMPUTED_VALUE"""),59.8) -> 59.8 | BA29: =IFERROR(__xludf.DUMMYFUNCTION("""COMPUTED_VALUE"""),27.74) -> 27.74 | BB29: =IFERROR(__xludf.DUMMYFUNCTION("""COMPUTED_VALUE"""),105.07) -> 105.07 | BC29: =IFERROR(__xludf.DUMMYFUNCTION("""COMPUTED_VALUE"""),176.44) -> 176.44 | BD29: =IFERROR(__xludf.DUMMYFUNCTION("""COMPUTED_VALUE"""),557.21) -> 557.21 | BE29: =IFERROR(__xludf.DUMMYFUNCTION("""COMPUTED_VALUE"""),194.54) -> 194.54 | BF29: =IFERROR(__xludf.DUMMYFUNCTION("""COMPUTED_VALUE"""),144.0) -> 144 | BG29: =IFERROR(__xludf.DUMMYFUNCTION("""COMPUTED_VALUE"""),6.99) -> 6.99 | BH29: =IFERROR(__xludf.DUMMYFUNCTION("""COMPUTED_VALUE"""),225.17) -> 225.17 | BI29: =IFERROR(__xludf.DUMMYFUNCTION("""COMPUTED_VALUE"""),484.52) -> 484.52 | BJ29: =IFERROR(__xludf.DUMMYFUNCTION("""COMPUTED_VALUE"""),48.48) -> 48.48 | BK29: =IFERROR(__xludf.DUMMYFUNCTION("""COMPUTED_VALUE"""),10.26) -> 10.26 | BL29: =IFERROR(__xludf.DUMMYFUNCTION("""COMPUTED_VALUE"""),208.77) -> 208.77 | BM29: =IFERROR(__xludf.DUMMYFUNCTION("""COMPUTED_VALUE"""),101.84) -> 101.84
A30: 45464.667 | B30: =IFERROR(__xludf.DUMMYFUNCTION("""COMPUTED_VALUE"""),5464.62) -> 5464.62 | C30: =IFERROR(__xludf.DUMMYFUNCTION("""COMPUTED_VALUE"""),17689.36) -> 17689.36 | D30: =IFERROR(__xludf.DUMMYFUNCTION("""COMPUTED_VALUE"""),39150.33) -> 39150.33 | E30: =IFERROR(__xludf.DUMMYFUNCTION("""COMPUTED_VALUE"""),2022.03) -> 2022.03 | F30: =IFERROR(__xludf.DUMMYFUNCTION("""COMPUTED_VALUE"""),533.44) -> 533.44 | G30: =IFERROR(__xludf.DUMMYFUNCTION("""COMPUTED_VALUE"""),189.08) -> 189.08 | H30: =IFERROR(__xludf.DUMMYFUNCTION("""COMPUTED_VALUE"""),130.54) -> 130.54 | I30: =IFERROR(__xludf.DUMMYFUNCTION("""COMPUTED_VALUE"""),207.49) -> 207.49 | J30: =IFERROR(__xludf.DUMMYFUNCTION("""COMPUTED_VALUE"""),235.41) -> 235.41 | K30: =IFERROR(__xludf.DUMMYFUNCTION("""COMPUTED_VALUE"""),58.82) -> 58.82 | L30: =IFERROR(__xludf.DUMMYFUNCTION("""COMPUTED_VALUE"""),10.44) -> 10.44 | M30: =IFERROR(__xludf.DUMMYFUNCTION("""COMPUTED_VALUE"""),409.62) -> 409.62 | N30: =IFERROR(__xludf.DUMMYFUNCTION("""COMPUTED_VALUE"""),56.58) -> 56.58 | O30: =IFERROR(__xludf.DUMMYFUNCTION("""COMPUTED_VALUE"""),224.0) -> 224 | P30: =IFERROR(__xludf.DUMMYFUNCTION("""COMPUTED_VALUE"""),62.88) -> 62.88 | Q30: =IFERROR(__xludf.DUMMYFUNCTION("""COMPUTED_VALUE"""),327.84) -> 327.84 | R30: =IFERROR(__xludf.DUMMYFUNCTION("""COMPUTED_VALUE"""),51.57) -> 51.57 | S30: =IFERROR(__xludf.DUMMYFUNCTION("""COMPUTED_VALUE"""),158.85) -> 158.85 | T30: =IFERROR(__xludf.DUMMYFUNCTION("""COMPUTED_VALUE"""),155.28) -> 155.28 | U30: =IFERROR(__xludf.DUMMYFUNCTION("""COMPUTED_VALUE"""),339.98) -> 339.98 | V30: =IFERROR(__xludf.DUMMYFUNCTION("""COMPUTED_VALUE"""),34.77) -> 34.77 | W30: =IFERROR(__xludf.DUMMYFUNCTION("""COMPUTED_VALUE"""),62.77) -> 62.77 | X30: =IFERROR(__xludf.DUMMYFUNCTION("""COMPUTED_VALUE"""),90.34) -> 90.34 | Y30: =IFERROR(__xludf.DUMMYFUNCTION("""COMPUTED_VALUE"""),148.35) -> 148.35 | Z30: =IFERROR(__xludf.DUMMYFUNCTION("""COMPUTED_VALUE"""),106.87) -> 106.87 | AA30: =IFERROR(__xludf.DUMMYFUNCTION("""COMPUTED_VALUE"""),521.83) -> 521.83 | AB30: =IFERROR(__xludf.DUMMYFUNCTION("""COMPUTED_VALUE"""),54.15) -> 54.15 | AC30: =IFERROR(__xludf.DUMMYFUNCTION("""COMPUTED_VALUE"""),110.76) -> 110.76 | AD30: =IFERROR(__xludf.DUMMYFUNCTION("""COMPUTED_VALUE"""),253.66) -> 253.66 | AE30: =IFERROR(__xludf.DUMMYFUNCTION("""COMPUTED_VALUE"""),414.65) -> 414.65 | AF30: =IFERROR(__xludf.DUMMYFUNCTION("""COMPUTED_VALUE"""),298.25) -> 298.25 | AG30: =IFERROR(__xludf.DUMMYFUNCTION("""COMPUTED_VALUE"""),47.72) -> 47.72 | AH30: =IFERROR(__xludf.DUMMYFUNCTION("""COMPUTED_VALUE"""),70.67) -> 70.67 | AI30: =IFERROR(__xludf.DUMMYFUNCTION("""COMPUTED_VALUE"""),450.18) -> 450.18 | AJ30: =IFERROR(__xludf.DUMMYFUNCTION("""COMPUTED_VALUE"""),355.8) -> 355.8 | AK30: =IFERROR(__xludf.DUMMYFUNCTION("""COMPUTED_VALUE"""),98.16) -> 98.16 | AL30: =IFERROR(__xludf.DUMMYFUNCTION("""COMPUTED_VALUE"""),137.84) -> 137.84 | AM30: =IFERROR(__xludf.DUMMYFUNCTION("""COMPUTED_VALUE"""),432.56) -> 432.56 | AN30: =IFERROR(__xludf.DUMMYFUNCTION("""COMPUTED_VALUE"""),196.3) -> 196.3 | AO30: =IFERROR(__xludf.DUMMYFUNCTION("""COMPUTED_VALUE"""),467.6) -> 467.6 | AP30: =IFERROR(__xludf.DUMMYFUNCTION("""COMPUTED_VALUE"""),311.82) -> 311.82 | AQ30: =IFERROR(__xludf.DUMMYFUNCTION("""COMPUTED_VALUE"""),25.69) -> 25.69 | AR30: =IFERROR(__xludf.DUMMYFUNCTION("""COMPUTED_VALUE"""),81.64) -> 81.64 | AS30: =IFERROR(__xludf.DUMMYFUNCTION("""COMPUTED_VALUE"""),71.27) -> 71.27 | AT30: =IFERROR(__xludf.DUMMYFUNCTION("""COMPUTED_VALUE"""),449.78) -> 449.78 | AU30: =IFERROR(__xludf.DUMMYFUNCTION("""COMPUTED_VALUE"""),72.81) -> 72.81 | AV30: =IFERROR(__xludf.DUMMYFUNCTION("""COMPUTED_VALUE"""),126.57) -> 126.57 | AW30: =IFERROR(__xludf.DUMMYFUNCTION("""COMPUTED_VALUE"""),95.92) -> 95.92 | AX30: =IFERROR(__xludf.DUMMYFUNCTION("""COMPUTED_VALUE"""),39.72) -> 39.72 | AY30: =IFERROR(__xludf.DUMMYFUNCTION("""COMPUTED_VALUE"""),23.84) -> 23.84 | AZ30: =IFERROR(__xludf.DUMMYFUNCTION("""COMPUTED_VALUE"""),60.61) -> 60.61 | BA30: =IFERROR(__xludf.DUMMYFUNCTION("""COMPUTED_VALUE"""),27.74) -> 27.74 | BB30: =IFERROR(__xludf.DUMMYFUNCTION("""COMPUTED_VALUE"""),105.61) -> 105.61 | BC30: =IFERROR(__xludf.DUMMYFUNCTION("""COMPUTED_VALUE"""),176.73) -> 176.73 | BD30: =IFERROR(__xludf.DUMMYFUNCTION("""COMPUTED_VALUE"""),564.6) -> 564.6 | BE30: =IFERROR(__xludf.DUMMYFUNCTION("""COMPUTED_VALUE"""),193.58) -> 193.58 | BF30: =IFERROR(__xludf.DUMMYFUNCTION("""COMPUTED_VALUE"""),139.04) -> 139.04 | BG30: =IFERROR(__xludf.DUMMYFUNCTION("""COMPUTED_VALUE"""),6.99) -> 6.99 | BH30: =IFERROR(__xludf.DUMMYFUNCTION("""COMPUTED_VALUE"""),226.11) -> 226.11 | BI30: =IFERROR(__xludf.DUMMYFUNCTION("""COMPUTED_VALUE"""),482.59) -> 482.59 | BJ30: =IFERROR(__xludf.DUMMYFUNCTION("""COMPUTED_VALUE"""),48.46) -> 48.46 | BK30: =IFERROR(__xludf.DUMMYFUNCTION("""COMPUTED_VALUE"""),10.47) -> 10.47 | BL30: =IFERROR(__xludf.DUMMYFUNCTION("""COMPUTED_VALUE"""),208.99) -> 208.99 | BM30: =IFERROR(__xludf.DUMMYFUNCTION("""COMPUTED_VALUE"""),102.27) -> 102.27
